Workbook

Sheet Setup
B1: Travel Estimate & Expense — User Testing Workbook
B2: Math is shown as live formulas on each scenario tab. You verify the app against these numbers by hand; the Result cells only compare what you type.
B4: SETTINGS (blue = edit)
B5: Fee multiplier (travel_settings.fee_multiplier) | C5: 1.1274 | D5: Applied to every ODC line except per diem meals and EWW. Confirm the Supervisor review screen shows "Fee Multiplier Used: 1.1274x" before you start.
B6: Dollar tolerance for PASS | C6: 0.01 | D6: Cents. A value within this of the expected figure counts as PASS.
B7: App build under test (commit) | C7: a3249e3 | D7: Update if the app is redeployed during testing.
B8: Tester name | D8: Add initials to every Event Name you type (see rule below).
B9: Test date
B10: Browser / device
B12: HOW TO USE
B13: 1. Steps tab | C13: Run-sheet | D13: Go scenario by scenario. Do the step, check what it says, set the Status. One person runs one scenario at a time.
B14: 2. Scenario tabs (S1-S8) | C14: Inputs + math | D14: Type the blue inputs exactly. Read the math rows. Then fill the yellow Actual cells in the Screen Checkpoints; Result turns PASS/FAIL.
B15: 3. Emails tab | C15: Count + verify | D15: Log every email that arrives. The summary at the top compares expected vs received per scenario.
B16: 4. Controls tab | C16: Coverage | D16: Shows every control and which scenarios exercise it. A GAP means no scenario touches it.
B17: 5. Watch List tab | C17: Suspected issues | D17: Hypotheses from reading the code. Confirm or clear each during the run.
B18: 6. Defects tab | C18: Log | D18: Anything wrong that is not already on the Watch List.
B20: EVENT NAME RULE (so emails can be matched)
B21: Type exactly | C21: S2 Customer Site Visit - JD | D21: Scenario ID + name + your initials. The Event Name appears in the heading of the full emails. The short notices name the trip by city and show the Tracking # once one exists. Note the time of each action to tell look-alike emails apart.
B23: TRACKING NUMBERS
B24: Format | C24: SLIN code + hyphen + 5 digits | D24: Example: 6200AE-00001. The SLIN is the one the Supervisor picks at approval.
B25: When it is issued | C25: First Supervisor approval only | D25: A request returned by the Prime and approved again keeps the same number. A request denied or cancelled before its first approval never gets one.
B26: Where it must appear | C26: Every message after approval | D26: Both approval emails, the authorize / return / deny notices, the submit emails on a resubmission, and every expense email. The expense report uses the same number as its estimate.
B27: Counter | C27: One sequence across all SLINs | D27: 00001, 00002, 00003 ... in approval order (Watch W7).
B29: WHICH COSTS ARE MULTIPLIED BY TRAVELERS
B30: Per traveler (x Travelers) | C30: Total Lodging Cost, Airfare, Baggage, Airport Parking | D30: Enter the amount for ONE traveler. Per Diem Meals is also per traveler.
B31: Trip-level (not multiplied) | C31: Rental Car, Gas, Parking, Tolls, Rideshare, Mileage, Shipping (to), Shipping (back) | D31: Enter the amount for the whole trip.
B32: Marked up by the multiplier | C32: Everything above except Per Diem Meals | D32: EWW is never marked up.
B34: THE MATH, IN ONE PLACE
B35: Nights | C35: Return date - Leave date
B36: Per Diem Meals (per traveler) | C36: 1.5 x M&IE + (Nights - 1, min 0) x M&IE | D36: First and last day are each 75% (1.5x combined); every day in between is 100%.
B37: Per Traveler Subtotal | C37: Per Diem + Total Lodging + Airfare + Airport Parking + Baggage
B38: Trip Lead Total | C38: Per Traveler Subtotal x Travelers + trip-level costs | D38: Internal figure (no markup).
B39: EWW Total | C39: Sum over travelers of (rate x hours) | D39: Entered by the Supervisor at review.
B40: Billable to Prime (ODC) | C40: (per-traveler costs x Travelers + trip-level costs) x multiplier + Per Diem x Travelers
B41: Grand Total to Prime | C41: Billable to Prime (ODC) + EWW Total | D41: The only total the Prime sees.
B42: GSA lodging limit | C42: Room Cost / Nights must be <= GSA Lodging Rate | D42: Fees and taxes do NOT count. Over the limit => 3 comparison quotes required.
B44: WHERE A NUMBER SHOWS UP
B45: Employee form | C45: Nights, Full Days, Per Diem, Per Traveler Subtotal, Trip Lead Total | D45: No markup figures for an Employee.
B46: My Estimates list / Supervisor queue | C46: Grand Total = Trip Lead Total + EWW (internal)
B47: Supervisor review | C47: All of the above + EWW, Grand Total, Billable to Prime (ODC), Grand Total to Prime, per-line Billable column | D47: Line items are per traveler / per trip, so they do not sum to the totals when Travelers > 1.
B48: Prime queue + email | C48: Grand Total to Prime (stored figure)
B49: Prime review form | C49: Every ODC field shown already marked up (rounded to cents), totals recomputed from those | D49: Matches the Prime queue, the emails and the Supervisor figures to the cent: every marked-up line is rounded first, then summed.
B50: Expense form | C50: Estimated (internal, unmarked) vs Actual per category; totals; Variance vs Estimate
B52: LEGEND
B53: Blue text | C53: Input to type
B54: Black text | C54: Formula (do not edit)
B55: Green text | C55: Link to another tab
B56: Yellow cell | C56: You fill this in
B57: Gray cell | C57: Informational, no check

Sheet Scenarios
A1: Scenario index
A2: Eight scripted scenarios covering every role, every status, and every control. Progress columns fill in as you work the Steps and Emails tabs.
A4: ID | B4: Scenario | C4: Travel type | D4: Max travelers | E4: EWW travelers | F4: What it proves | G4: Steps | H4: Steps done | I4: Emails exp. | J4: Emails rcvd
A5: S1 | B5: Solo drive trip, under GSA, no EWW | C5: Drive (personal vehicle) | D5: 1 | E5: 0 | F5: Baseline. One traveler, no flights, no EWW. Proves the core math, the happy path through every role, a clean expense report (no variance), the tracking number, and the full email set. | G5: 20 | H5: =COUNTIFS(Steps!$A$5:$A$24,A5,Steps!$J$5:$J$24,"Pass")+COUNTIFS(Steps!$A$5:$A$24,A5,Steps!$J$5:$J$24,"Observe") -> 0 | I5: =Emails!B5 -> 8 | J5: =Emails!C5 -> 0
A6: S2 | B6: Fly + rental car, 2 travelers, 1 with EWW | C6: Fly + rental car | D6: 2 | E6: 1 | F6: Per-traveler vs trip-level math with two travelers, one EWW traveler (Traveler 2 has none), and the richest expense report: two categories >10% over, two additional (unestimated) categories, receipt add/remove and form Cancel. Proves EWW carries from the estimate to the expense exactly. | G6: 17 | H6: =COUNTIFS(Steps!$A$25:$A$41,A6,Steps!$J$25:$J$41,"Pass")+COUNTIFS(Steps!$A$25:$A$41,A6,Steps!$J$25:$J$41,"Observe") -> 0 | I6: =Emails!B6 -> 8 | J6: =Emails!C6 -> 0
A7: S3 | B7: Lodging limit rules (fees/taxes excluded, over-limit quotes) | C7: Fly, hotel conference | D7: 1 | E7: 1 | F7: The per diem lodging limit applies to the ROOM rate only. S3a proves taxes and fees do not trigger the limit. S3b proves an over-limit room rate forces three comparison quotes, and that the quotes flow to the Supervisor. | G7: 13 | H7: =COUNTIFS(Steps!$A$42:$A$54,A7,Steps!$J$42:$J$54,"Pass")+COUNTIFS(Steps!$A$42:$A$54,A7,Steps!$J$42:$J$54,"Observe") -> 0 | I7: =Emails!B7 -> 9 | J7: =Emails!C7 -> 0
A8: S4 | B8: Long stay, 4 travelers, 2 with EWW | C8: Fly + rideshare + shipping | D8: 4 | E8: 2 | F8: Maximum multiplier effect: 4 travelers, 10 nights, two EWW travelers with different rates and hours. Exercises traveler add/remove, an actual-date change on the expense side, and a variance on rideshare and return shipping. | G8: 11 | H8: =COUNTIFS(Steps!$A$55:$A$65,A8,Steps!$J$55:$J$65,"Pass")+COUNTIFS(Steps!$A$55:$A$65,A8,Steps!$J$55:$J$65,"Observe") -> 0 | I8: =Emails!B8 -> 8 | J8: =Emails!C8 -> 0
A9: S5 | B9: Edge dates: one night and same day | C9: Fly (1 night) / local (same day) | D9: 1 | E9: 1 | F9: GSA first/last-day rule at its boundaries. One night = two 75% days (1.5x M&IE, zero full days). Same day (0 nights) is an observation: record what the app produces and take it to the team (Watch W1 has the question written out). | G9: 8 | H9: =COUNTIFS(Steps!$A$66:$A$73,A9,Steps!$J$66:$J$73,"Pass")+COUNTIFS(Steps!$A$66:$A$73,A9,Steps!$J$66:$J$73,"Observe") -> 0 | I9: =Emails!B9 -> 9 | J9: =Emails!C9 -> 0
A10: S6 | B10: Validation rules + Supervisor return and resubmit | C10: Fly, 2 travelers | D10: 2 | E10: 1 | F10: Every blocking rule on the estimate form, then a Return round-trip: the Supervisor enters EWW and returns the estimate, the employee sees the note, corrects airfare and resubmits, and the EWW survives. | G10: 15 | H10: =COUNTIFS(Steps!$A$74:$A$88,A10,Steps!$J$74:$J$88,"Pass")+COUNTIFS(Steps!$A$74:$A$88,A10,Steps!$J$74:$J$88,"Observe") -> 0 | I10: =Emails!B10 -> 8 | J10: =Emails!C10 -> 0
A11: S7 | B11: Deny, return and cancel paths | C11: Fly, 1 traveler (light data) | D11: 1 | E11: 0 | F11: Every way an estimate can end other than paid: Supervisor deny, Prime return then deny, and employee cancel from draft and submitted. Denied requests are stored read-only. A returned request keeps its tracking number through re-approval. Math is light here; the focus is status, notes, tracking number and emails. | G11: 13 | H11: =COUNTIFS(Steps!$A$89:$A$101,A11,Steps!$J$89:$J$101,"Pass")+COUNTIFS(Steps!$A$89:$A$101,A11,Steps!$J$89:$J$101,"Observe") -> 0 | I11: =Emails!B11 -> 17 | J11: =Emails!C11 -> 0
A12: S8 | B12: Expense return and resubmit, expense deny | C12: Fly, 1 traveler (light data) | D12: 1 | E12: 0 | F12: The expense-side rejection paths. Two minimal authorized estimates: S8a's expense report is returned, corrected and resubmitted, then approved; S8b's is denied and stored read-only. | G12: 13 | H12: =COUNTIFS(Steps!$A$102:$A$114,A12,Steps!$J$102:$J$114,"Pass")+COUNTIFS(Steps!$A$102:$A$114,A12,Steps!$J$102:$J$114,"Observe") -> 0 | I12: =Emails!B12 -> 19 | J12: =Emails!C12 -> 0

Sheet Steps
A1: Run-sheet — every step of every scenario
A2: Do the step, read the Check column, set Status. "Observe" = record what you see, no pass/fail (policy or known-risk items).
A4: Scenario | B4: Step | C4: Persona | D4: Estimate | E4: Do this | F4: Controls | G4: Check / expect | H4: Emails | I4: Email IDs | J4: Status | K4: Your notes
A5: S1 | B5: 1 | C5: Employee | D5: S1 | E5: Travel > My Estimates > New Travel Estimate. Type Event Name, City, pick State from the list, pick a Contract. | F5: E01, E02, E03, E04 | G5: Rate fields auto-fill from the GSA lookup (any value is fine - you overwrite them next). | H5: 0
A6: S1 | B6: 2 | C6: Employee | D6: S1 | E6: Set Leave Date and Return Date. Leave Travelers at 1. | F6: E05, E06, E07 | G6: Checkpoints A1 (Nights) and A2 (Full Days). | H6: 0
A7: S1 | B7: 3 | C7: Employee | D7: S1 | E7: AFTER the lookup finishes, overwrite GSA Lodging Rate and Meals (M&IE) Rate with the scripted values. Click a field, type the number, Tab out. | F7: E11, E12, E33 | G7: Field clears on click and reformats as $X.XX on Tab. Checkpoint A3 (Per Diem Meals Total). | H7: 0
A8: S1 | B8: 4 | C8: Employee | D8: S1 | E8: Enter Room Cost, Total Lodging Cost, Lodging Fees, Lodging Taxes, then Mileage, Gas, Parking, Tolls. Leave everything else at $0.00. | F8: E13, E14, E15, E16, E25, E26, E27, E29 | G8: No red GSA warning appears. Checkpoints A4 and A5. Employee view shows only Per Traveler Subtotal and Trip Lead Total (no markup figures). | H8: 0
A9: S1 | B9: 5 | C9: Employee | D9: S1 | E9: Click Save as Draft. Then open the draft from the Pending card (Edit Draft). | F9: E30, L01, G03, L03 | G9: Toast says "Draft saved." Row shows status draft. Every value and the Event Name persist after reopening. No email for a draft. | H9: 0
A10: S1 | B10: 6 | C10: Employee | D10: S1 | E10: Click Submit Estimate. | F10: E31, G03 | G10: Toast "Travel estimate submitted." Row moves to status submitted. Checkpoint B1. No tracking number exists yet. | H10: 2 | I10: S1-E1, S1-E2
A11: S1 | B11: 7 | C11: Supervisor | D11: S1 | E11: Switch Role > Supervisor. Travel > Approvals. Find the estimate under "Estimates Needing Approval" and click Review. Click Close once, then click Review again. | F11: G01, S01, S11, S12 | G11: Close dismisses the review without a decision. Queue Grand Total matches B1. Form is read-only. Fee Multiplier Used shows 1.1274x (if not, stop and fix Setup C5). Tracking Number reads "Assigned on approval". | H11: 0
A12: S1 | B12: 8 | C12: Supervisor | D12: S1 | E12: Leave every EWW rate/hours field at $0.00 / 0 (no EWW on this trip). | F12: S02, S03 | G12: Checkpoints C1-C6 and the billable line column (C-L rows). | H12: 0
A13: S1 | B13: 9 | C13: Supervisor | D13: S1 | E13: Billing Assignment: pick Contract, then Task Order, then SLIN. Click Approve. | F13: S04, S05, S06, S08 | G13: Task Order list filters to the chosen Contract; SLIN list filters to the chosen Task Order. Queue drops the row. Tracking # = the SLIN code you picked, a hyphen, and 5 digits (e.g. 6200AE-00001). Record it. It must appear in both approval emails. | H13: 2 | I13: S1-E3, S1-E4
A14: S1 | B14: 10 | C14: Prime | D14: S1 | E14: Switch Role > Prime. Travel > Travel Authorizations. Check the queue row, then click Review. | F14: G01, P01, P07 | G14: Queue Tracking # matches the email; Grand Total = D2. Review form shows marked-up amounts only (no Room Cost, Fees, Taxes, GSA warning). Checkpoints E1-E4 must match the queue to the cent. | H14: 0
A15: S1 | B15: 11 | C15: Prime | D15: S1 | E15: Click Authorize Travel. | F15: P02 | G15: Queue drops the row. The email names the trip and shows the tracking number. | H15: 1 | I15: S1-E5
A16: S1 | B16: 12 | C16: Employee | D16: S1 | E16: Switch Role > Employee. Travel > My Estimates. Open the estimate (View). | F16: G01, L01 | G16: Status approved. Read-only detail shows the same Tracking Number. Checkpoint D1. | H16: 0
A17: S1 | B17: 13 | C17: Employee | D17: S1 | E17: Travel > My Expenses > New Travel Expense Report. Pick the estimate from "Authorized Estimate". | F17: X01 | G17: Dropdown label ends with [Tracking #]. Dates, travelers and M&IE prefill. Only categories with an estimate > $0 appear (Lodging, Gas, Parking, Tolls, Mileage). EWW shows as a read-only total ($0.00 here). Checkpoint X-A. | H17: 0
A18: S1 | B18: 14 | C18: Employee | D18: S1 | E18: Change Actual Leave Date to 11/10, watch Nights and Per Diem, then set it back to 11/09. Also retype the Actual Return Date (11/12). | F18: X02, X03 | G18: Nights drops to 2 and Per Diem Meals Total recalculates live, then both return to the original values. | H18: 0
A19: S1 | B19: 15 | C19: Employee | D19: S1 | E19: Enter the Actual cost for each visible category. Upload one receipt (image or PDF) in every category that has an amount. | F19: X08, X09, E33 | G19: No variance box appears for any category (all within 10%). Checkpoint X-B (live totals) and X-C (category table). | H19: 0
A20: S1 | B20: 16 | C20: Employee | D20: S1 | E20: Save as Draft, then reopen it (Edit Draft). | F20: X15, X18 | G20: Actuals, receipts and totals persist. No email for a draft. | H20: 0
A21: S1 | B21: 17 | C21: Employee | D21: S1 | E21: Submit Expense Report. | F21: X16 | G21: Report shows in My Expense Reports as submitted. Checkpoint X-D. The estimate now reads expensed. Both emails show the trip, tracking number, actual vs estimated by category, and totals. | H21: 2 | I21: S1-E6, S1-E7
A22: S1 | B22: 18 | C22: Supervisor | D22: S1 | E22: Switch Role > Supervisor. Approvals > Expense Reports Needing Approval > Review. | F22: G01, V01, V07 | G22: Header counts: Categories >10% Over = 0, Added Categories = 0. Form is read-only; receipts open. | H22: 0
A23: S1 | B23: 19 | C23: Supervisor | D23: S1 | E23: Click Approve (finalizes reimbursement). | F23: V02 | G23: Row leaves the queue. | H23: 1 | I23: S1-E8
A24: S1 | B24: 20 | C24: Employee | D24: S1 | E24: Switch Role > Employee. Check My Estimates and My Expenses. | F24: G01, L03, L02 | G24: Expense status approved. Estimate sits in the Paid / Cancelled card as paid and has NO red cancel (x). | H24: 0
A25: S2 | B25: 1 | C25: Employee | D25: S2 | E25: New Travel Estimate. Type Event Name, City, State, pick Contract. Set Leave and Return Dates. | F25: E01, E02, E03, E04, E05, E06 | G25: Checkpoints A1, A2. | H25: 0
A26: S2 | B26: 2 | C26: Employee | D26: S2 | E26: Set Travelers to 2. Pick any roster employee for Traveler 2. | F26: E07, E08 | G26: Traveler 1 is locked ("You"). The Traveler 2 list does not offer the person already chosen. | H26: 0
A27: S2 | B27: 3 | C27: Employee | D27: S2 | E27: Overwrite GSA Lodging Rate and M&IE Rate. Enter Room Cost, Total Lodging, Fees, Taxes, Airfare, Airport Parking, Rental Car, Gas, Parking, Shipping (to), Shipping (back). Leave Baggage and Tolls at $0.00. | F27: E11, E12, E13, E14, E15, E16, E19, E21, E22, E23, E24, E25, E26, E33 | G27: Checkpoints A3-A5. Lodging, airfare and airport parking are PER TRAVELER (the app multiplies by 2); rental car, gas, parking and shipping are TRIP-LEVEL (not multiplied). There are no EWW fields on this form. | H27: 0
A28: S2 | B28: 4 | C28: Employee | D28: S2 | E28: Submit Estimate. | F28: E31, G03 | G28: Checkpoint B1. Open each email: the EWW table lists both travelers at $0.00. | H28: 2 | I28: S2-E1, S2-E2
A29: S2 | B29: 5 | C29: Supervisor | D29: S2 | E29: Switch Role > Supervisor. Approvals > Review the estimate. | F29: G01, S01, S12 | G29: Read-only copy of the form. Note the line-item values are per traveler. | H29: 0
A30: S2 | B30: 6 | C30: Supervisor | D30: S2 | E30: Enter EWW (payroll-verified): Traveler 1 rate 62.50, hours 12. Traveler 2 stays $0.00 / 0. | F30: S02, S03 | G30: EWW Cost for Traveler 1 updates live; EWW Total, Grand Total and both Prime figures update. Checkpoints C1-C7 and the billable line rows. | H30: 0
A31: S2 | B31: 7 | C31: Supervisor | D31: S2 | E31: Assign Contract / Task Order / SLIN and click Approve. | F31: S04, S05, S06, S08 | G31: Emails now include the EWW table (Traveler 1 = $750.00) and the tracking number. Tracking # = the SLIN code you picked, a hyphen, and 5 digits (e.g. 6200AE-00001). Record it. | H31: 2 | I31: S2-E3, S2-E4
A32: S2 | B32: 8 | C32: Prime | D32: S2 | E32: Prime queue: check Tracking # and Grand Total, open Review, then Authorize Travel. | F32: G01, P01, P02, P07 | G32: Checkpoints D2 and E1-E4. The Prime form total must equal the queue total to the cent (every marked-up line is rounded first). | H32: 1 | I32: S2-E5
A33: S2 | B33: 9 | C33: Employee | D33: S2 | E33: Travel > My Expenses > New Travel Expense Report. Pick the estimate, change nothing, then click Cancel on the form. | F33: X01, X17 | G33: Returns to the list; nothing saved. Then start the report again. | H33: 0
A34: S2 | B34: 10 | C34: Employee | D34: S2 | E34: Select the estimate again and read the EWW box. Do not look for EWW rate or hours fields. | F34: X19 | G34: There are no EWW fields to type. A read-only EWW Total shows $750.00, the exact total payroll verified on the estimate (checkpoint X-A1). | H34: 0
A35: S2 | B35: 11 | C35: Employee | D35: S2 | E35: Enter the Actual costs for the eight visible categories. | F35: X05, X08, E33 | G35: Variance boxes appear for Airfare and Gas ONLY (checkpoint X-C). Totals show EWW $750.00 and Variance +$338.40 once all actuals are in. | H35: 0
A36: S2 | B36: 12 | C36: Employee | D36: S2 | E36: Click Submit Expense Report with the variance notes still blank. | F36: X16 | G36: Blocked with "Explain the variance for ... " naming the first category. Type the notes from the table and continue. | H36: 0
A37: S2 | B37: 13 | C37: Employee | D37: S2 | E37: Additional Expenses: add Baggage and Tolls from "+ Add an expense category". Enter the actuals. Add Rideshare, then remove it with the x. | F37: X12, X14 | G37: Estimated shows "-" for added rows. Submit is blocked until each added row has a note ("Explain why ... wasn't on the original estimate"). | H37: 0
A38: S2 | B38: 14 | C38: Employee | D38: S2 | E38: Fill in the notes for Baggage and Tolls. Upload a receipt on Airfare, remove it with the x, upload it again. Upload a receipt on every other category with an amount. | F38: X13, X09, X10, X11 | G38: Thumbnails show; removed receipt disappears. | H38: 0
A39: S2 | B39: 15 | C39: Employee | D39: S2 | E39: Save as Draft, reopen with Edit Draft, then Submit Expense Report. | F39: X15, X18, X16 | G39: Notes, additional rows and receipts persist. Checkpoints X-B, X-C, X-D. Both emails list the explanations. | H39: 2 | I39: S2-E6, S2-E7
A40: S2 | B40: 16 | C40: Supervisor | D40: S2 | E40: Approvals > Expense Reports Needing Approval > Review. | F40: G01, V01, V07 | G40: Header: Categories >10% Over = 2, Added Categories = 2. Variance explanations are visible. | H40: 0
A41: S2 | B41: 17 | C41: Supervisor | D41: S2 | E41: Approve. | F41: V02 | G41: Estimate becomes paid. | H41: 1 | I41: S2-E8
A42: S3 | B42: 1 | C42: Employee | D42: S3a | E42: New estimate S3a. Fill header, dates, rates. Click Refresh GSA Rates, wait for it to finish, then re-enter the scripted GSA Lodging Rate and M&IE Rate. | F42: E01, E02, E03, E04, E05, E06, E10, E11, E12 | G42: Refresh overwrites the rate fields (or shows a lookup message). Rates must be re-typed afterward. | H42: 0
A43: S3 | B43: 2 | C43: Employee | D43: S3a | E43: Enter Room Cost, Fees, Taxes, Total Lodging, Airfare, Baggage, Airport Parking, Rideshare. | F43: E13, E14, E15, E16, E19, E20, E21, E28, E33 | G43: NO red warning box: room average/night is under the rate even though total/night is over it (checkpoints F1-F3). | H43: 0
A44: S3 | B44: 3 | C44: Employee | D44: S3a | E44: Submit Estimate (no quotes). | F44: E31 | G44: Submits cleanly. | H44: 2 | I44: S3-E1, S3-E2
A45: S3 | B45: 4 | C45: Supervisor | D45: S3a | E45: Review: no lodging warning shown. Assign billing and Approve. | F45: G01, S01, S04, S05, S06, S08 | G45: Checkpoints C1-C6 (no EWW). Tracking # = the SLIN code you picked, a hyphen, and 5 digits (e.g. 6200AE-00001). Record it. | H45: 2 | I45: S3-E3, S3-E4
A46: S3 | B46: 5 | C46: Employee | D46: S3b | E46: New estimate S3b. Header, dates, rates. Enter Room Cost 468.00, Fees, Taxes, Total Lodging, Airfare, Baggage, Airport Parking, Rideshare. | F46: E01, E02, E03, E04, E13, E14, E15, E16, E34 | G46: Red box appears: "Lodging cost exceeds GSA rate", with the average room cost (checkpoint F1) and "3 comparison quotes are required to submit." | H46: 0
A47: S3 | B47: 6 | C47: Employee | D47: S3b | E47: Click Submit Estimate with no quotes. | F47: E31 | G47: Blocked: "Lodging cost exceeds the GSA rate - upload 3 comparison quotes with rates entered before submitting." | H47: 0
A48: S3 | B48: 7 | C48: Employee | D48: S3b | E48: Click Upload Comparison Quotes. Upload one file. | F48: E17 | G48: A "Saving a draft..." message flashes first (the app saves a draft silently so quotes can attach). The modal lists the file; the button behind it reads "(1 of 3)". The draft shows in the Pending card the next time the list reloads (after Submit or a refresh). | H48: 0
A49: S3 | B49: 8 | C49: Employee | D49: S3b | E49: Upload the second and third files (you can select several at once). Then try for a fourth. | F49: E17 | G49: At 3 the upload control is replaced by a "3 quotes attached" message. Selecting extra files at once uploads only up to the limit and says so. | H49: 0
A50: S3 | B50: 9 | C50: Employee | D50: S3b | E50: Type a nightly rate for each quote: 138.00, 149.00, 152.00. Close the modal. | F50: E18 | G50: Modal shows "Average of entered rates: $146.33". Submit is still blocked until all three have rates; after that it is allowed. | H50: 0
A51: S3 | B51: 10 | C51: Employee | D51: S3b | E51: Submit Estimate. | F51: E31 | G51: Submits. | H51: 2 | I51: S3-E5, S3-E6
A52: S3 | B52: 11 | C52: Supervisor | D52: S3b | E52: Review. Open the lodging warning area. | F52: G01, S01, S12 | G52: Warning shows "3 of 3 required comparison quotes attached" with each quote linked and "Average of quoted rates: $146.33/night". Quote links open. | H52: 0
A53: S3 | B53: 12 | C53: Supervisor | D53: S3b | E53: Enter EWW: Traveler 1 rate 52.00, hours 5. Assign billing and Approve. | F53: S02, S03, S04, S05, S06, S08 | G53: Checkpoints C1-C7. A second tracking number is issued: it must be the next number up from S3a's. | H53: 2 | I53: S3-E7, S3-E8
A54: S3 | B54: 13 | C54: Prime | D54: S3b | E54: Open Review, then Authorize Travel. | F54: G01, P01, P02, P07 | G54: Review hides Room Cost, Fees, Taxes and the GSA warning/quotes. Checkpoints E1-E4. | H54: 1 | I54: S3-E9
A55: S4 | B55: 1 | C55: Employee | D55: S4 | E55: New estimate. Header, Contract, dates. Set Travelers to 4 and pick a different roster employee for each of Travelers 2, 3 and 4. | F55: E01, E02, E03, E04, E05, E06, E07, E08 | G55: Each picker excludes people already chosen. | H55: 0
A56: S4 | B56: 2 | C56: Employee | D56: S4 | E56: Click the x next to Traveler 4. Then set Travelers back to 4 and pick the employee again. | F56: E09 | G56: Remove drops to 3 travelers and the Travelers dropdown follows; adding returns a blank slot. | H56: 0
A57: S4 | B57: 3 | C57: Employee | D57: S4 | E57: Overwrite GSA and M&IE rates, then enter all lodging, flight, shipping and rideshare amounts. | F57: E11, E12, E13, E14, E15, E16, E19, E20, E21, E22, E23, E28, E33 | G57: Checkpoints A1-A5. Totals are large because per-traveler lines are multiplied by 4. | H57: 0
A58: S4 | B58: 4 | C58: Employee | D58: S4 | E58: Submit Estimate. | F58: E31 | G58: Checkpoint B1. | H58: 2 | I58: S4-E1, S4-E2
A59: S4 | B59: 5 | C59: Supervisor | D59: S4 | E59: Review. Enter EWW (payroll-verified): Traveler 1 rate 55.00 hours 8; Traveler 3 rate 48.75 hours 16; Travelers 2 and 4 stay at zero. | F59: G01, S01, S02, S03 | G59: Each EWW Cost updates (T1 $440.00, T3 $780.00). Checkpoints C1-C7 and billable lines. | H59: 0
A60: S4 | B60: 6 | C60: Supervisor | D60: S4 | E60: Assign billing and Approve. | F60: S04, S05, S06, S08 | G60: Emails list all 4 travelers in the EWW table. Tracking # = the SLIN code you picked, a hyphen, and 5 digits (e.g. 6200AE-00001). Record it. | H60: 2 | I60: S4-E3, S4-E4
A61: S4 | B61: 7 | C61: Prime | D61: S4 | E61: Queue, Review, Authorize. | F61: G01, P01, P02, P07 | G61: Checkpoints D2, E1-E4. With 4 travelers the Prime form total must still equal the queue total to the cent. | H61: 1 | I61: S4-E5
A62: S4 | B62: 8 | C62: Employee | D62: S4 | E62: New Expense Report. Pick the estimate. Read the EWW box, then change Actual Return Date to 12/10. | F62: X01, X03, X04, X19 | G62: EWW shows a read-only $1,220.00 (the exact total, not an average). Nights drops to 9 and Per Diem recalculates (checkpoints X-A, X-B). Number of Travelers prefilled as 4. | H62: 0
A63: S4 | B63: 9 | C63: Employee | D63: S4 | E63: Enter the Actual costs. | F63: X05, X08, E33 | G63: Variance boxes: Rideshare and Shipping (back) ONLY. | H63: 0
A64: S4 | B64: 10 | C64: Employee | D64: S4 | E64: Type the variance notes, upload a receipt on every category with an amount, Save as Draft, reopen, Submit Expense Report. | F64: X09, X11, X15, X18, X16 | G64: Checkpoints X-B, X-C, X-D. | H64: 2 | I64: S4-E6, S4-E7
A65: S4 | B65: 11 | C65: Supervisor | D65: S4 | E65: Expense review: header counts, then Approve. | F65: G01, V01, V02, V07 | G65: Categories >10% Over = 2, Added = 0. | H65: 1 | I65: S4-E8
A66: S5 | B66: 1 | C66: Employee | D66: S5a | E66: New estimate S5a. Header, Contract, dates (12/14 to 12/15). Overwrite rates. Enter lodging, airfare and rideshare. | F66: E01, E02, E03, E04, E05, E06, E11, E12, E13, E14, E15, E16, E19, E28 | G66: Nights = 1, Full Days = 0, Per Diem = 1.5 x M&IE (checkpoints A1-A5). | H66: 0
A67: S5 | B67: 2 | C67: Employee | D67: S5a | E67: After the rates are overwritten, change the Leave Date to another day and back to 12/14. | F67: E05 | G67: Changing the date re-runs the GSA lookup and may overwrite your rates. Re-enter the scripted values before submitting. Record whether it did. | H67: 0
A68: S5 | B68: 3 | C68: Employee | D68: S5a | E68: Submit Estimate. | F68: E31 | G68: Checkpoint B1. | H68: 2 | I68: S5-E1, S5-E2
A69: S5 | B69: 4 | C69: Supervisor | D69: S5a | E69: Review. Enter EWW Traveler 1 rate 40.00 hours 6. Assign billing, Approve. | F69: G01, S01, S02, S03, S04, S05, S06, S08 | G69: Checkpoints C1-C7. | H69: 2 | I69: S5-E3, S5-E4
A70: S5 | B70: 5 | C70: Prime | D70: S5a | E70: Review and Authorize. | F70: G01, P01, P02, P07 | G70: Checkpoints D2, E1-E4. | H70: 1 | I70: S5-E5
A71: S5 | B71: 6 | C71: Employee | D71: S5b | E71: New estimate S5b with the SAME Leave and Return Date (12/17). Enter rates, rideshare only. | F71: E01, E02, E03, E04, E05, E06, E11, E12, E28 | G71: Nights = 0, Full Days = 0. Record the Per Diem the app shows. WATCH W1: the formula gives 1.5 x M&IE for a single day. Mark as OBSERVE, not pass/fail. | H71: 0
A72: S5 | B72: 7 | C72: Employee | D72: S5b | E72: Submit Estimate. | F72: E31 | G72: Submits (same-day is allowed). | H72: 2 | I72: S5-E6, S5-E7
A73: S5 | B73: 8 | C73: Supervisor | D73: S5b | E73: Review, assign billing, Approve. | F73: G01, S01, S04, S05, S06, S08 | G73: Checkpoints C1-C6. | H73: 2 | I73: S5-E8, S5-E9
A74: S6 | B74: 1 | C74: Employee | D74: S6 v1 | E74: VALIDATION 1: Open a blank New Travel Estimate and click Submit Estimate. | F74: E31 | G74: Error: "City, State, Contract, and both dates are required to submit." Nothing saved, no email. | H74: 0
A75: S6 | B75: 2 | C75: Employee | D75: S6 v1 | E75: VALIDATION 2: Fill City, State, both dates but leave Contract blank. Submit. | F75: E04 | G75: Same error. | H75: 0
A76: S6 | B76: 3 | C76: Employee | D76: S6 v1 | E76: VALIDATION 3: Set Return Date earlier than Leave Date. Pick a Contract. Submit. | F76: E05, E06 | G76: Error: "Return date must be on or after leave date." | H76: 0
A77: S6 | B77: 4 | C77: Employee | D77: S6 v1 | E77: VALIDATION 4: Fix the dates. Set Travelers to 2 and leave Traveler 2 empty. Submit. | F77: E07, E08 | G77: Error: "Select an employee for Traveler 2 ..." . | H77: 0
A78: S6 | B78: 5 | C78: Employee | D78: S6 v1 | E78: VALIDATION 5: Pick Traveler 2. Enter a GSA Lodging Rate of 100 and a Room Cost high enough to exceed it. Submit with no quotes. | F78: E13, E34 | G78: Error asks for 3 comparison quotes. Then set the Room Cost back below the limit; the warning disappears. | H78: 0
A79: S6 | B79: 6 | C79: Employee | D79: S6 v1 | E79: VALIDATION 6: In any currency field type abc, then -5, then 1234.5, then 12.345, tabbing out each time. | F79: E33 | G79: Record what each becomes (W2). Per the code: abc becomes $0.00, -5 becomes $-5.00, 1234.5 becomes $1234.50 (no thousands comma), 12.345 becomes $12.35. | H79: 0
A80: S6 | B80: 7 | C80: Employee | D80: S6 v1 | E80: VALIDATION 7: With the form edited and unsaved, try to reload the page or close the tab. | F80: E35 | G80: Browser asks to confirm leaving the page. Switch Role and Sign Out should warn too. | H80: 0
A81: S6 | B81: 8 | C81: Employee | D81: S6 v1 | E81: VALIDATION 8: Click Cancel at the bottom of the form. | F81: E32 | G81: Returns to the estimate list; nothing is saved. | H81: 0
A82: S6 | B82: 9 | C82: Employee | D82: S6 v1 | E82: Now build the real estimate (version 1 inputs, Travelers 2, airfare 640.00). Submit. | F82: E01, E02, E03, E04, E05, E06, E07, E08, E11, E12, E13, E14, E15, E16, E19, E20, E21, E28, E31 | G82: Checkpoints A1-A5 (v1), B1. | H82: 2 | I82: S6-E1, S6-E2
A83: S6 | B83: 10 | C83: Supervisor | D83: S6 v1 | E83: Review. Enter EWW (payroll-verified) Traveler 1 rate 45.00 hours 10. Click Return with the note box empty. | F83: G01, S01, S02, S03, S09 | G83: Blocked: "A note is required to return or deny this estimate." The note box appears. | H83: 0
A84: S6 | B84: 11 | C84: Supervisor | D84: S6 v1 | E84: Type the note "Airfare is higher than comparable fares - please recheck fare class". Click Return. | F84: S07, S09 | G84: Checkpoints C1-C7 (v1) were visible before returning. The email names the trip and shows the note. No tracking number exists yet, so none appears. | H84: 1 | I84: S6-E3
A85: S6 | B85: 12 | C85: Employee | D85: S6 v2 | E85: Switch Role > Employee. Find the estimate: the button now reads Edit & Resubmit. Open it. | F85: G01, L01, L04 | G85: Red banner "This request was returned" shows the Supervisor's note. | H85: 0
A86: S6 | B86: 13 | C86: Employee | D86: S6 v2 | E86: Change Airfare to 512.00. Resubmit. | F86: E19, E31 | G86: Checkpoint B1 (v2) includes the retained EWW. Emails show the EWW table with Traveler 1 = $450.00. | H86: 2 | I86: S6-E4, S6-E5
A87: S6 | B87: 14 | C87: Supervisor | D87: S6 v2 | E87: Review again. EWW should still read 45.00 x 10 for Traveler 1. Assign billing and Approve. | F87: G01, S01, S04, S05, S06, S08 | G87: Checkpoints C1-C7 (v2). Tracking Number is assigned only now (this is the FIRST approval). Tracking # = the SLIN code you picked, a hyphen, and 5 digits (e.g. 6200AE-00001). Record it. | H87: 2 | I87: S6-E6, S6-E7
A88: S6 | B88: 15 | C88: Prime | D88: S6 v2 | E88: Review and Authorize. | F88: G01, P01, P02, P07 | G88: Checkpoints D2, E1-E4 (v2). | H88: 1 | I88: S6-E8
A89: S7 | B89: 1 | C89: Employee | D89: S7a | E89: Create and submit estimate S7a. | F89: E01, E02, E03, E04, E05, E06, E11, E12, E13, E14, E15, E16, E19, E31 | G89: Checkpoint B1. | H89: 2 | I89: S7-E1, S7-E2
A90: S7 | B90: 2 | C90: Supervisor | D90: S7a | E90: Review and click Deny with no note, then with the note "Not funded this quarter". | F90: G01, S01, S10, S07 | G90: First click blocked (note required). Second succeeds. No tracking number is ever issued to a request denied at first review. The email names the trip and shows the note. | H90: 1 | I90: S7-E3
A91: S7 | B91: 3 | C91: Employee | D91: S7a | E91: Look at the S7a row, then open it. | F91: G01, L01, L04, L02 | G91: Status denied. The row button reads View and there is NO red cancel (x). The detail is read-only, with a red banner "This request was denied" and the note. There is no way to edit or resubmit. | H91: 0
A92: S7 | B92: 4 | C92: Employee | D92: S7b | E92: Create and submit estimate S7b. | F92: E31 | G92: Checkpoint B1. | H92: 2 | I92: S7-E4, S7-E5
A93: S7 | B93: 5 | C93: Supervisor | D93: S7b | E93: Assign billing and Approve. | F93: G01, S01, S04, S05, S06, S08 | G93: Record Tracking Number #1. Tracking # = the SLIN code you picked, a hyphen, and 5 digits (e.g. 6200AE-00001). Record it. | H93: 2 | I93: S7-E6, S7-E7
A94: S7 | B94: 6 | C94: Prime | D94: S7b | E94: Review. Click Return with no note, then with the note "Please add the customer PO to the event name". | F94: G01, P01, P03, P05 | G94: First click blocked. Second returns it. The email subject and body carry the trip AND tracking number #1. | H94: 1 | I94: S7-E8
A95: S7 | B95: 7 | C95: Employee | D95: S7b | E95: Open S7b (Edit & Resubmit). Banner shows the Prime's note. Resubmit unchanged. | F95: G01, L01, L04, E31 | G95: Resubmit emails now carry tracking number #1 in the subject and heading (it was issued at the first approval and stays with the request). | H95: 2 | I95: S7-E9, S7-E10
A96: S7 | B96: 8 | C96: Supervisor | D96: S7b | E96: Open the Review again, check the Tracking Number field, then Approve again. | F96: G01, S01, S04, S05, S06, S08 | G96: The review header already shows tracking number #1 (not "Assigned on approval"). After approving, the number must be UNCHANGED: only the first approval issues one. Both emails show #1. | H96: 2 | I96: S7-E11, S7-E12
A97: S7 | B97: 9 | C97: Prime | D97: S7b | E97: Review and click Deny with the note "Budget exhausted". | F97: G01, P01, P04, P05, P06 | G97: Status denied. The email carries the trip, tracking number #1 and the note. | H97: 1 | I97: S7-E13
A98: S7 | B98: 10 | C98: Employee | D98: S7b | E98: Look at the S7b row, then open it. | F98: G01, L01, L02 | G98: Status denied: button reads View, no red cancel (x), read-only detail with the denial note and the same tracking number. | H98: 0
A99: S7 | B99: 11 | C99: Employee | D99: S7c-1 | E99: Create estimate S7c-1 and click Save as Draft only. Then click the red x on its row and accept the confirmation. | F99: E30, L02 | G99: Confirmation prompt appears; Dismiss leaves it alone, OK cancels it. Cancelled row leaves the Pending card and appears under Paid / Cancelled with status cancelled. A cancellation email arrives (no tracking number: none issued). | H99: 1 | I99: S7-E14
A100: S7 | B100: 12 | C100: Employee | D100: S7c-2 | E100: Create and submit estimate S7c-2. Then cancel it with the red x. | F100: E31, L02, L03 | G100: Row moves to Paid / Cancelled; opening it is read-only. | H100: 3 | I100: S7-E15, S7-E16, S7-E17
A101: S7 | B101: 13 | C101: Supervisor | D101: S7a | E101: Approvals queue and Prime queue. | F101: G01 | G101: None of the cancelled or denied estimates appear in any queue. | H101: 0
...

Sheet S1
A1: S1 — Solo drive trip, under GSA, no EWW
A2: Baseline. One traveler, no flights, no EWW. Proves the core math, the happy path through every role, a clean expense report (no variance), the tracking number, and the full email set.
A3: Travel type: Drive (personal vehicle) | Expected emails: 8 | Fee multiplier from Setup tab
A5: 1. INPUTS — type these exactly (blue)
A6: Ref | B6: Field / what to read | C6: Screen label / how it is calculated | D6: S1
B7: Event Name | C7: Add your initials at the end | D7: S1 Regional Workshop - xx
B8: City | D8: Columbia
B9: State | C9: Pick from the list | D9: SC
B10: Contract | C10: Pick any contract; note which one | D10: (any)
B11: Leave Date | D11: 46335
B12: Return Date | D12: 46338
B13: Travelers | C13: Traveler 2-4: pick any roster employee | D13: 1
B14: GSA Lodging Rate (per night) | C14: Overwrite AFTER the lookup finishes | D14: 110
B15: Meals (M&IE) Rate (per day) | C15: Overwrite AFTER the lookup finishes | D15: 68
B16: Room Cost (subject to per diem limit) | C16: Per traveler, whole stay | D16: 306
B17: Total Lodging Cost (incl. taxes & fees) | C17: Per traveler, whole stay | D17: 368.25
B18: Lodging Fees | C18: Recorded only | D18: 24
B19: Lodging Taxes | C19: Recorded only | D19: 38.25
B20: Airfare (avg) | C20: Per traveler | D20: 0
B21: Baggage | C21: Per traveler | D21: 0
B22: Airport Parking | C22: Per traveler | D22: 0
B23: Shipping (to) | C23: Trip-level | D23: 0
B24: Shipping (back) | C24: Trip-level | D24: 0
... B30: Mileage (Personal Vehicle) | C30: Trip-level | D30: 187.6
B31: Entered by the SUPERVISOR at review (not on the submit form)
B32: Traveler 1 EWW Rate (per hour) | C32: Supervisor review > EWW Rate | D32: 0
B33: Traveler 1 EWW Hours | D33: 0
B34: Traveler 2 EWW Rate (per hour) | D34: 0
B35: Traveler 2 EWW Hours | D35: 0
B36: Traveler 3 EWW Rate (per hour) | D36: 0
B37: Traveler 3 EWW Hours | D37: 0
B38: Traveler 4 EWW Rate (per hour) | D38: 0
B39: Traveler 4 EWW Hours | D39: 0
B40: EWW already saved when submitted? (1 = yes) | C40: Only a resubmission after a Supervisor return carries EWW | D40: 0
A42: 2. EXPECTED MATH — live formulas (read these to follow the arithmetic)
A43: Ref | B43: Field / what to read | C43: Screen label / how it is calculated | D43: S1
B44: Nights | C44: Return Date - Leave Date (never below 0) | D44: =MAX(0,D12-D11) -> 3
B45: Full Days (1x) | C45: Nights - 1, minimum 0 | D45: =MAX(D44-1,0) -> 2
B46: Per Diem Meals Total (per traveler) | C46: 1.5 x M&IE + Full Days x M&IE | D46: =1.5*D15+D45*D15 -> 238
B47: Per-traveler costs (excl. meals) | C47: Total Lodging + Airfare + Airport Parking + Baggage | D47: =D17+D20+D22+D21 -> 368.25
B48: Per Traveler Subtotal | C48: Per Diem + per-traveler costs | D48: =D46+D47 -> 606.25
B49: Trip-level costs | C49: Rental + Gas + Parking + Tolls + Rideshare + Mileage + Shipping to + Shipping back | D49: =D25+D26+D27+D28+D29+D30+D23+D24 -> 288.45
B50: Trip Lead Total | C50: Per Traveler Subtotal x Travelers + trip-level costs | D50: =D48*D13+D49 -> 894.7
B51: EWW Cost — Traveler 1 | C51: Rate x Hours (only if that traveler exists) | D51: =IF(1<=D13,D32*D33,0) -> 0
B52: EWW Cost — Traveler 2 | C52: Rate x Hours (only if that traveler exists) | D52: =IF(2<=D13,D34*D35,0) -> 0
B53: EWW Cost — Traveler 3 | C53: Rate x Hours (only if that traveler exists) | D53: =IF(3<=D13,D36*D37,0) -> 0
B54: EWW Cost — Traveler 4 | C54: Rate x Hours (only if that traveler exists) | D54: =IF(4<=D13,D38*D39,0) -> 0
B55: EWW Total | C55: Sum of the four EWW Costs | D55: =SUM(D51:D54) -> 0
B56: Grand Total (ODC + EWW) | C56: Trip Lead Total + EWW Total | D56: =D50+D55 -> 894.7
B57: Billable column, line by line (amount x multiplier, rounded to cents) | C57: Supervisor review "Billable to Prime" column, approved-email column, Prime form field
B58: Total Lodging Cost | C58: ROUND(Total Lodging Cost x multiplier, 2) | D58: =ROUND(D17*Setup!$C$5,2) -> 415.17
B59: Airfare (avg) | C59: ROUND(Airfare (avg) x multiplier, 2) | D59: =ROUND(D20*Setup!$C$5,2) -> 0
B60: Baggage | C60: ROUND(Baggage x multiplier, 2) | D60: =ROUND(D21*Setup!$C$5,2) -> 0
B61: Airport Parking | C61: ROUND(Airport Parking x multiplier, 2) | D61: =ROUND(D22*Setup!$C$5,2) -> 0
B62: Rental Car | C62: ROUND(Rental Car x multiplier, 2) | D62: =ROUND(D25*Setup!$C$5,2) -> 0
B63: Gas | C63: ROUND(Gas x multiplier, 2) | D63: =ROUND(D26*Setup!$C$5,2) -> 59.02
B64: Parking | C64: ROUND(Parking x multiplier, 2) | D64: =ROUND(D27*Setup!$C$5,2) -> 40.59
B65: Tolls | C65: ROUND(Tolls x multiplier, 2) | D65: =ROUND(D28*Setup!$C$5,2) -> 14.09
B66: Rideshare Estimate | C66: ROUND(Rideshare Estimate x multiplier, 2) | D66: =ROUND(D29*Setup!$C$5,2) -> 0
B67: Mileage (Personal Vehicle) | C67: ROUND(Mileage (Personal Vehicle) x multiplier, 2) | D67: =ROUND(D30*Setup!$C$5,2) -> 211.5
B68: Shipping (to) | C68: ROUND(Shipping (to) x multiplier, 2) | D68: =ROUND(D23*Setup!$C$5,2) -> 0
B69: Shipping (back) | C69: ROUND(Shipping (back) x multiplier, 2) | D69: =ROUND(D24*Setup!$C$5,2) -> 0
B70: Marked-up ODC | C70: (4 rounded per-traveler lines) x Travelers + (8 rounded trip-level lines) | D70: =(D58+D59+D61+D60)*D13+D62+D63+D64+D65+D66+D67+D68+D69 -> 740.37
B71: Per Diem Meals, all travelers (not marked up) | C71: Per Diem x Travelers | D71: =D46*D13 -> 238
B72: Billable to Prime (ODC) | C72: Marked-up ODC + Per Diem all travelers | D72: =D70+D71 -> 978.37
B73: Grand Total to Prime | C73: Billable to Prime (ODC) + EWW Total | D73: =D72+D55 -> 978.37
B74: Markup added (information) | C74: Grand Total to Prime - Grand Total | D74: =D73-D56 -> 83.67
B75: Grand Total on lists right after submit | C75: Trip Lead Total + EWW if EWW was already saved | D75: =D50+D40*D55 -> 894.7
B76: Average ROOM cost per night | C76: Room Cost / Nights (0 if no nights) | D76: =IF(D44>0,D16/D44,0) -> 102
B77: Over the GSA limit? | C77: YES when average room cost per night > GSA Lodging Rate | D77: =IF(AND(D44>0,D76>D14),"YES","No") -> No
B78: Total lodging per night (NOT used for the limit) | C78: Total Lodging / Nights — shown to prove fees/taxes are excluded | D78: =IF(D44>0,D17/D44,0) -> 122.75
B79: Typing check: Room + Fees + Taxes - Total | C79: Should be $0.00; if not, one of the four inputs was mistyped | D79: =ROUND(D16+D18+D19-D17,2) -> 0
B80: Per Traveler Subtotal as the Prime sees it | C80: Per Diem (unmarked) + the 4 rounded per-traveler lines | D80: =D46+D58+D59+D61+D60 -> 653.17
A82: 3. SCREEN CHECKPOINTS — compare each screen to Expected, type what you see in the yellow cell
A83: Ref | B83: Field / what to read | C83: Screen label / how it is calculated | D83: S1 Expected | E83: Actual (you) | F83: Result
A84: A1 | B84: Nights | C84: Employee form (live) | D84: =D44 -> 3 | F84: =IF(E84="","",IF(ABS(E84-D84)<=Setup!$C$6,"PASS","FAIL"))
A85: A2 | B85: Full Days (1x) | C85: Employee form (live) | D85: =D45 -> 2 | F85: =IF(E85="","",IF(ABS(E85-D85)<=Setup!$C$6,"PASS","FAIL"))
A86: A3 | B86: Per Diem Meals Total | C86: Employee form (live) | D86: =D46 -> 238 | F86: =IF(E86="","",IF(ABS(E86-D86)<=Setup!$C$6,"PASS","FAIL"))
A87: A4 | B87: Per Traveler Subtotal | C87: Employee form (live) | D87: =D48 -> 606.25 | F87: =IF(E87="","",IF(ABS(E87-D87)<=Setup!$C$6,"PASS","FAIL"))
A88: A5 | B88: Trip Lead Total | C88: Employee form (live) | D88: =D50 -> 894.7 | F88: =IF(E88="","",IF(ABS(E88-D88)<=Setup!$C$6,"PASS","FAIL"))
A89: B1 | B89: Grand Total right after submit | C89: My Estimates list AND Supervisor queue (before Supervisor enters EWW) | D89: =D75 -> 894.7 | F89: =IF(E89="","",IF(ABS(E89-D89)<=Setup!$C$6,"PASS","FAIL"))
A90: C1 | B90: Per Traveler Subtotal | C90: Supervisor review | D90: =D48 -> 606.25 | F90: =IF(E90="","",IF(ABS(E90-D90)<=Setup!$C$6,"PASS","FAIL"))
A91: C2 | B91: Trip Lead Total | C91: Supervisor review | D91: =D50 -> 894.7 | F91: =IF(E91="","",IF(ABS(E91-D91)<=Setup!$C$6,"PASS","FAIL"))
A92: C3 | B92: EWW Total | C92: Supervisor review (after entering EWW) | D92: =D55 -> 0 | F92: =IF(E92="","",IF(ABS(E92-D92)<=Setup!$C$6,"PASS","FAIL"))
A93: C4 | B93: Grand Total (ODC + EWW) | C93: Supervisor review | D93: =D56 -> 894.7 | F93: =IF(E93="","",IF(ABS(E93-D93)<=Setup!$C$6,"PASS","FAIL"))
A94: C5 | B94: Billable to Prime (ODC) | C94: Supervisor review | D94: =D72 -> 978.37 | F94: =IF(E94="","",IF(ABS(E94-D94)<=Setup!$C$6,"PASS","FAIL"))
A95: C6 | B95: Grand Total to Prime | C95: Supervisor review | D95: =D73 -> 978.37 | F95: =IF(E95="","",IF(ABS(E95-D95)<=Setup!$C$6,"PASS","FAIL"))
A96: CL.lodging | B96: Billable column: Total Lodging Cost | C96: Supervisor review > Billable to Prime Breakdown | D96: =D58 -> 415.17 | F96: =IF(E96="","",IF(ABS(E96-D96)<=Setup!$C$6,"PASS","FAIL"))
A97: CL.gas | B97: Billable column: Gas | C97: Supervisor review > Billable to Prime Breakdown | D97: =D63 -> 59.02 | F97: =IF(E97="","",IF(ABS(E97-D97)<=Setup!$C$6,"PASS","FAIL"))
A98: CL.parking | B98: Billable column: Parking | C98: Supervisor review > Billable to Prime Breakdown | D98: =D64 -> 40.59 | F98: =IF(E98="","",IF(ABS(E98-D98)<=Setup!$C$6,"PASS","FAIL"))
A99: CL.tolls | B99: Billable column: Tolls | C99: Supervisor review > Billable to Prime Breakdown | D99: =D65 -> 14.09 | F99: =IF(E99="","",IF(ABS(E99-D99)<=Setup!$C$6,"PASS","FAIL"))
A100: CL.mileage | B100: Billable column: Mileage (Personal Vehicle) | C100: Supervisor review > Billable to Prime Breakdown | D100: =D67 -> 211.5 | F100: =IF(E100="","",IF(ABS(E100-D100)<=Setup!$C$6,"PASS","FAIL"))
A101: D1 | B101: Grand Total after approval | C101: My Estimates list (now includes EWW) | D101: =D56 -> 894.7 | F101: =IF(E101="","",IF(ABS(E101-D101)<=Setup!$C$6,"PASS","FAIL"))
A102: D2 | B102: Grand Total (Prime queue) | C102: Prime > Travel Authorizations queue | D102: =D73 -> 978.37 | F102: =IF(E102="","",IF(ABS(E102-D102)<=Setup!$C$6,"PASS","FAIL"))
A103: E1 | B103: Per Traveler Subtotal | C103: Prime review form | D103: =D80 -> 653.17 | F103: =IF(E103="","",IF(ABS(E103-D103)<=Setup!$C$6,"PASS","FAIL"))
A104: E2 | B104: Trip Lead Total | C104: Prime review form | D104: =D72 -> 978.37 | F104: =IF(E104="","",IF(ABS(E104-D104)<=Setup!$C$6,"PASS","FAIL"))
A105: E3 | B105: EWW Total | C105: Prime review form | D105: =D55 -> 0 | F105: =IF(E105="","",IF(ABS(E105-D105)<=Setup!$C$6,"PASS","FAIL"))
A106: E4 | B106: Grand Total (must equal D2 exactly) | C106: Prime review form | D106: =D73 -> 978.37 | F106: =IF(E106="","",IF(ABS(E106-D106)<=Setup!$C$6,"PASS","FAIL"))
A107: F1 | B107: Average room cost per night | C107: Employee form warning text / math only | D107: =D76 -> 102 | F107: =IF(E107="","",IF(ABS(E107-D107)<=Setup!$C$6,"PASS","FAIL"))
A108: F2 | B108: Red over-limit warning shown? (type YES or No) | C108: Employee form | D108: =D77 -> No | F108: =IF(E108="","",IF(UPPER(E108)=UPPER(D108),"PASS","FAIL"))
...

Sheet S2
A1: S2 — Fly + rental car, 2 travelers, 1 with EWW
A2: Per-traveler vs trip-level math with two travelers, one EWW traveler (Traveler 2 has none), and the richest expense report: two categories >10% over, two additional (unestimated) categories, receipt add/remove and form Cancel. Proves EWW carries from the estimate to the expense exactly.
A3: Travel type: Fly + rental car | Expected emails: 8 | Fee multiplier from Setup tab
A5: 1. INPUTS — type these exactly (blue)
A6: Ref | B6: Field / what to read | C6: Screen label / how it is calculated | D6: S2
B7: Event Name | C7: Add your initials at the end | D7: S2 Customer Site Visit - xx
B8: City | D8: Austin
B9: State | C9: Pick from the list | D9: TX
B10: Contract | C10: Pick any contract; note which one | D10: (any)
B11: Leave Date | D11: 46342
B12: Return Date | D12: 46345
B13: Travelers | C13: Traveler 2-4: pick any roster employee | D13: 2
B14: GSA Lodging Rate (per night) | C14: Overwrite AFTER the lookup finishes | D14: 150
B15: Meals (M&IE) Rate (per day) | C15: Overwrite AFTER the lookup finishes | D15: 74
B16: Room Cost (subject to per diem limit) | C16: Per traveler, whole stay | D16: 420
B17: Total Lodging Cost (incl. taxes & fees) | C17: Per traveler, whole stay | D17: 513.8
B18: Lodging Fees | C18: Recorded only | D18: 35
B19: Lodging Taxes | C19: Recorded only | D19: 58.8
B20: Airfare (avg) | C20: Per traveler | D20: 385
B21: Baggage | C21: Per traveler | D21: 0
B22: Airport Parking | C22: Per traveler | D22: 60
B23: Shipping (to) | C23: Trip-level | D23: 85
B24: Shipping (back) | C24: Trip-level | D24: 85
... B30: Mileage (Personal Vehicle) | C30: Trip-level | D30: 0
B31: Entered by the SUPERVISOR at review (not on the submit form)
B32: Traveler 1 EWW Rate (per hour) | C32: Supervisor review > EWW Rate | D32: 62.5
B33: Traveler 1 EWW Hours | D33: 12
B34: Traveler 2 EWW Rate (per hour) | D34: 0
B35: Traveler 2 EWW Hours | D35: 0
B36: Traveler 3 EWW Rate (per hour) | D36: 0
B37: Traveler 3 EWW Hours | D37: 0
B38: Traveler 4 EWW Rate (per hour) | D38: 0
B39: Traveler 4 EWW Hours | D39: 0
B40: EWW already saved when submitted? (1 = yes) | C40: Only a resubmission after a Supervisor return carries EWW | D40: 0
A42: 2. EXPECTED MATH — live formulas (read these to follow the arithmetic)
A43: Ref | B43: Field / what to read | C43: Screen label / how it is calculated | D43: S2
B44: Nights | C44: Return Date - Leave Date (never below 0) | D44: =MAX(0,D12-D11) -> 3
B45: Full Days (1x) | C45: Nights - 1, minimum 0 | D45: =MAX(D44-1,0) -> 2
B46: Per Diem Meals Total (per traveler) | C46: 1.5 x M&IE + Full Days x M&IE | D46: =1.5*D15+D45*D15 -> 259
B47: Per-traveler costs (excl. meals) | C47: Total Lodging + Airfare + Airport Parking + Baggage | D47: =D17+D20+D22+D21 -> 958.8
B48: Per Traveler Subtotal | C48: Per Diem + per-traveler costs | D48: =D46+D47 -> 1217.8
B49: Trip-level costs | C49: Rental + Gas + Parking + Tolls + Rideshare + Mileage + Shipping to + Shipping back | D49: =D25+D26+D27+D28+D29+D30+D23+D24 -> 454.5
B50: Trip Lead Total | C50: Per Traveler Subtotal x Travelers + trip-level costs | D50: =D48*D13+D49 -> 2890.1
B51: EWW Cost — Traveler 1 | C51: Rate x Hours (only if that traveler exists) | D51: =IF(1<=D13,D32*D33,0) -> 750
B52: EWW Cost — Traveler 2 | C52: Rate x Hours (only if that traveler exists) | D52: =IF(2<=D13,D34*D35,0) -> 0
B53: EWW Cost — Traveler 3 | C53: Rate x Hours (only if that traveler exists) | D53: =IF(3<=D13,D36*D37,0) -> 0
B54: EWW Cost — Traveler 4 | C54: Rate x Hours (only if that traveler exists) | D54: =IF(4<=D13,D38*D39,0) -> 0
B55: EWW Total | C55: Sum of the four EWW Costs | D55: =SUM(D51:D54) -> 750
B56: Grand Total (ODC + EWW) | C56: Trip Lead Total + EWW Total | D56: =D50+D55 -> 3640.1
B57: Billable column, line by line (amount x multiplier, rounded to cents) | C57: Supervisor review "Billable to Prime" column, approved-email column, Prime form field
B58: Total Lodging Cost | C58: ROUND(Total Lodging Cost x multiplier, 2) | D58: =ROUND(D17*Setup!$C$5,2) -> 579.26
B59: Airfare (avg) | C59: ROUND(Airfare (avg) x multiplier, 2) | D59: =ROUND(D20*Setup!$C$5,2) -> 434.05
B60: Baggage | C60: ROUND(Baggage x multiplier, 2) | D60: =ROUND(D21*Setup!$C$5,2) -> 0
B61: Airport Parking | C61: ROUND(Airport Parking x multiplier, 2) | D61: =ROUND(D22*Setup!$C$5,2) -> 67.64
B62: Rental Car | C62: ROUND(Rental Car x multiplier, 2) | D62: =ROUND(D25*Setup!$C$5,2) -> 242.39
B63: Gas | C63: ROUND(Gas x multiplier, 2) | D63: =ROUND(D26*Setup!$C$5,2) -> 46.79
B64: Parking | C64: ROUND(Parking x multiplier, 2) | D64: =ROUND(D27*Setup!$C$5,2) -> 31.57
B65: Tolls | C65: ROUND(Tolls x multiplier, 2) | D65: =ROUND(D28*Setup!$C$5,2) -> 0
B66: Rideshare Estimate | C66: ROUND(Rideshare Estimate x multiplier, 2) | D66: =ROUND(D29*Setup!$C$5,2) -> 0
B67: Mileage (Personal Vehicle) | C67: ROUND(Mileage (Personal Vehicle) x multiplier, 2) | D67: =ROUND(D30*Setup!$C$5,2) -> 0
B68: Shipping (to) | C68: ROUND(Shipping (to) x multiplier, 2) | D68: =ROUND(D23*Setup!$C$5,2) -> 95.83
B69: Shipping (back) | C69: ROUND(Shipping (back) x multiplier, 2) | D69: =ROUND(D24*Setup!$C$5,2) -> 95.83
B70: Marked-up ODC | C70: (4 rounded per-traveler lines) x Travelers + (8 rounded trip-level lines) | D70: =(D58+D59+D61+D60)*D13+D62+D63+D64+D65+D66+D67+D68+D69 -> 2674.31
B71: Per Diem Meals, all travelers (not marked up) | C71: Per Diem x Travelers | D71: =D46*D13 -> 518
B72: Billable to Prime (ODC) | C72: Marked-up ODC + Per Diem all travelers | D72: =D70+D71 -> 3192.31
B73: Grand Total to Prime | C73: Billable to Prime (ODC) + EWW Total | D73: =D72+D55 -> 3942.31
B74: Markup added (information) | C74: Grand Total to Prime - Grand Total | D74: =D73-D56 -> 302.21
B75: Grand Total on lists right after submit | C75: Trip Lead Total + EWW if EWW was already saved | D75: =D50+D40*D55 -> 2890.1
B76: Average ROOM cost per night | C76: Room Cost / Nights (0 if no nights) | D76: =IF(D44>0,D16/D44,0) -> 140
B77: Over the GSA limit? | C77: YES when average room cost per night > GSA Lodging Rate | D77: =IF(AND(D44>0,D76>D14),"YES","No") -> No
B78: Total lodging per night (NOT used for the limit) | C78: Total Lodging / Nights — shown to prove fees/taxes are excluded | D78: =IF(D44>0,D17/D44,0) -> 171.26667
B79: Typing check: Room + Fees + Taxes - Total | C79: Should be $0.00; if not, one of the four inputs was mistyped | D79: =ROUND(D16+D18+D19-D17,2) -> 0
B80: Per Traveler Subtotal as the Prime sees it | C80: Per Diem (unmarked) + the 4 rounded per-traveler lines | D80: =D46+D58+D59+D61+D60 -> 1339.95
A82: 3. SCREEN CHECKPOINTS — compare each screen to Expected, type what you see in the yellow cell
A83: Ref | B83: Field / what to read | C83: Screen label / how it is calculated | D83: S2 Expected | E83: Actual (you) | F83: Result
A84: A1 | B84: Nights | C84: Employee form (live) | D84: =D44 -> 3 | F84: =IF(E84="","",IF(ABS(E84-D84)<=Setup!$C$6,"PASS","FAIL"))
A85: A2 | B85: Full Days (1x) | C85: Employee form (live) | D85: =D45 -> 2 | F85: =IF(E85="","",IF(ABS(E85-D85)<=Setup!$C$6,"PASS","FAIL"))
A86: A3 | B86: Per Diem Meals Total | C86: Employee form (live) | D86: =D46 -> 259 | F86: =IF(E86="","",IF(ABS(E86-D86)<=Setup!$C$6,"PASS","FAIL"))
A87: A4 | B87: Per Traveler Subtotal | C87: Employee form (live) | D87: =D48 -> 1217.8 | F87: =IF(E87="","",IF(ABS(E87-D87)<=Setup!$C$6,"PASS","FAIL"))
A88: A5 | B88: Trip Lead Total | C88: Employee form (live) | D88: =D50 -> 2890.1 | F88: =IF(E88="","",IF(ABS(E88-D88)<=Setup!$C$6,"PASS","FAIL"))
A89: B1 | B89: Grand Total right after submit | C89: My Estimates list AND Supervisor queue (before Supervisor enters EWW) | D89: =D75 -> 2890.1 | F89: =IF(E89="","",IF(ABS(E89-D89)<=Setup!$C$6,"PASS","FAIL"))
A90: C1 | B90: Per Traveler Subtotal | C90: Supervisor review | D90: =D48 -> 1217.8 | F90: =IF(E90="","",IF(ABS(E90-D90)<=Setup!$C$6,"PASS","FAIL"))
A91: C2 | B91: Trip Lead Total | C91: Supervisor review | D91: =D50 -> 2890.1 | F91: =IF(E91="","",IF(ABS(E91-D91)<=Setup!$C$6,"PASS","FAIL"))
A92: C3 | B92: EWW Total | C92: Supervisor review (after entering EWW) | D92: =D55 -> 750 | F92: =IF(E92="","",IF(ABS(E92-D92)<=Setup!$C$6,"PASS","FAIL"))
A93: C4 | B93: Grand Total (ODC + EWW) | C93: Supervisor review | D93: =D56 -> 3640.1 | F93: =IF(E93="","",IF(ABS(E93-D93)<=Setup!$C$6,"PASS","FAIL"))
A94: C5 | B94: Billable to Prime (ODC) | C94: Supervisor review | D94: =D72 -> 3192.31 | F94: =IF(E94="","",IF(ABS(E94-D94)<=Setup!$C$6,"PASS","FAIL"))
A95: C6 | B95: Grand Total to Prime | C95: Supervisor review | D95: =D73 -> 3942.31 | F95: =IF(E95="","",IF(ABS(E95-D95)<=Setup!$C$6,"PASS","FAIL"))
A96: C7.1 | B96: EWW Cost — Traveler 1 | C96: Supervisor review (live as you type) | D96: =D51 -> 750 | F96: =IF(E96="","",IF(ABS(E96-D96)<=Setup!$C$6,"PASS","FAIL"))
A97: CL.lodging | B97: Billable column: Total Lodging Cost | C97: Supervisor review > Billable to Prime Breakdown | D97: =D58 -> 579.26 | F97: =IF(E97="","",IF(ABS(E97-D97)<=Setup!$C$6,"PASS","FAIL"))
A98: CL.airfare | B98: Billable column: Airfare (avg) | C98: Supervisor review > Billable to Prime Breakdown | D98: =D59 -> 434.05 | F98: =IF(E98="","",IF(ABS(E98-D98)<=Setup!$C$6,"PASS","FAIL"))
A99: CL.airportParking | B99: Billable column: Airport Parking | C99: Supervisor review > Billable to Prime Breakdown | D99: =D61 -> 67.64 | F99: =IF(E99="","",IF(ABS(E99-D99)<=Setup!$C$6,"PASS","FAIL"))
A100: CL.rentalCar | B100: Billable column: Rental Car | C100: Supervisor review > Billable to Prime Breakdown | D100: =D62 -> 242.39 | F100: =IF(E100="","",IF(ABS(E100-D100)<=Setup!$C$6,"PASS","FAIL"))
A101: CL.gas | B101: Billable column: Gas | C101: Supervisor review > Billable to Prime Breakdown | D101: =D63 -> 46.79 | F101: =IF(E101="","",IF(ABS(E101-D101)<=Setup!$C$6,"PASS","FAIL"))
A102: CL.parking | B102: Billable column: Parking | C102: Supervisor review > Billable to Prime Breakdown | D102: =D64 -> 31.57 | F102: =IF(E102="","",IF(ABS(E102-D102)<=Setup!$C$6,"PASS","FAIL"))
A103: CL.shipTo | B103: Billable column: Shipping (to) | C103: Supervisor review > Billable to Prime Breakdown | D103: =D68 -> 95.83 | F103: =IF(E103="","",IF(ABS(E103-D103)<=Setup!$C$6,"PASS","FAIL"))
A104: CL.shipBack | B104: Billable column: Shipping (back) | C104: Supervisor review > Billable to Prime Breakdown | D104: =D69 -> 95.83 | F104: =IF(E104="","",IF(ABS(E104-D104)<=Setup!$C$6,"PASS","FAIL"))
A105: D1 | B105: Grand Total after approval | C105: My Estimates list (now includes EWW) | D105: =D56 -> 3640.1 | F105: =IF(E105="","",IF(ABS(E105-D105)<=Setup!$C$6,"PASS","FAIL"))
A106: D2 | B106: Grand Total (Prime queue) | C106: Prime > Travel Authorizations queue | D106: =D73 -> 3942.31 | F106: =IF(E106="","",IF(ABS(E106-D106)<=Setup!$C$6,"PASS","FAIL"))
A107: E1 | B107: Per Traveler Subtotal | C107: Prime review form | D107: =D80 -> 1339.95 | F107: =IF(E107="","",IF(ABS(E107-D107)<=Setup!$C$6,"PASS","FAIL"))
A108: E2 | B108: Trip Lead Total | C108: Prime review form | D108: =D72 -> 3192.31 | F108: =IF(E108="","",IF(ABS(E108-D108)<=Setup!$C$6,"PASS","FAIL"))
...

Sheet S3
A1: S3 — Lodging limit rules (fees/taxes excluded, over-limit quotes)
A2: The per diem lodging limit applies to the ROOM rate only. S3a proves taxes and fees do not trigger the limit. S3b proves an over-limit room rate forces three comparison quotes, and that the quotes flow to the Supervisor.
A3: Travel type: Fly, hotel conference | Expected emails: 9 | Fee multiplier from Setup tab
A5: 1. INPUTS — type these exactly (blue)
A6: Ref | B6: Field / what to read | C6: Screen label / how it is calculated | D6: S3a | G6: S3b
B7: Event Name | C7: Add your initials at the end | D7: S3a Fees-Taxes Excluded - xx | G7: S3b Over Limit With Quotes - xx
B8: City | D8: Nashville | G8: Memphis
B9: State | C9: Pick from the list | D9: TN | G9: TN
B10: Contract | C10: Pick any contract; note which one | D10: (any) | G10: (any)
B11: Leave Date | D11: 46349 | G11: 46349
B12: Return Date | D12: 46352 | G12: 46352
B13: Travelers | C13: Traveler 2-4: pick any roster employee | D13: 1 | G13: 1
B14: GSA Lodging Rate (per night) | C14: Overwrite AFTER the lookup finishes | D14: 140 | G14: 140
B15: Meals (M&IE) Rate (per day) | C15: Overwrite AFTER the lookup finishes | D15: 69 | G15: 69
B16: Room Cost (subject to per diem limit) | C16: Per traveler, whole stay | D16: 405 | G16: 468
B17: Total Lodging Cost (incl. taxes & fees) | C17: Per traveler, whole stay | D17: 511.5 | G17: 584.55
B18: Lodging Fees | C18: Recorded only | D18: 45 | G18: 45
B19: Lodging Taxes | C19: Recorded only | D19: 61.5 | G19: 71.55
B20: Airfare (avg) | C20: Per traveler | D20: 298 | G20: 298
B21: Baggage | C21: Per traveler | D21: 35 | G21: 35
B22: Airport Parking | C22: Per traveler | D22: 54 | G22: 54
B23: Shipping (to) | C23: Trip-level | D23: 0 | G23: 0
B24: Shipping (back) | C24: Trip-level | D24: 0 | G24: 0
... B30: Mileage (Personal Vehicle) | C30: Trip-level | D30: 0 | G30: 0
B31: Entered by the SUPERVISOR at review (not on the submit form)
B32: Traveler 1 EWW Rate (per hour) | C32: Supervisor review > EWW Rate | D32: 0 | G32: 52
B33: Traveler 1 EWW Hours | D33: 0 | G33: 5
B34: Traveler 2 EWW Rate (per hour) | D34: 0 | G34: 0
B35: Traveler 2 EWW Hours | D35: 0 | G35: 0
B36: Traveler 3 EWW Rate (per hour) | D36: 0 | G36: 0
B37: Traveler 3 EWW Hours | D37: 0 | G37: 0
B38: Traveler 4 EWW Rate (per hour) | D38: 0 | G38: 0
B39: Traveler 4 EWW Hours | D39: 0 | G39: 0
B40: EWW already saved when submitted? (1 = yes) | C40: Only a resubmission after a Supervisor return carries EWW | D40: 0 | G40: 0
B41: Comparison quote 1 nightly rate | C41: Upload Comparison Quotes modal | G41: 138
B42: Comparison quote 2 nightly rate | G42: 149
B43: Comparison quote 3 nightly rate | G43: 152
A45: 2. EXPECTED MATH — live formulas (read these to follow the arithmetic)
A46: Ref | B46: Field / what to read | C46: Screen label / how it is calculated | D46: S3a | G46: S3b
B47: Nights | C47: Return Date - Leave Date (never below 0) | D47: =MAX(0,D12-D11) -> 3 | G47: =MAX(0,G12-G11) -> 3
B48: Full Days (1x) | C48: Nights - 1, minimum 0 | D48: =MAX(D47-1,0) -> 2 | G48: =MAX(G47-1,0) -> 2
B49: Per Diem Meals Total (per traveler) | C49: 1.5 x M&IE + Full Days x M&IE | D49: =1.5*D15+D48*D15 -> 241.5 | G49: =1.5*G15+G48*G15 -> 241.5
B50: Per-traveler costs (excl. meals) | C50: Total Lodging + Airfare + Airport Parking + Baggage | D50: =D17+D20+D22+D21 -> 898.5 | G50: =G17+G20+G22+G21 -> 971.55
B51: Per Traveler Subtotal | C51: Per Diem + per-traveler costs | D51: =D49+D50 -> 1140 | G51: =G49+G50 -> 1213.05
B52: Trip-level costs | C52: Rental + Gas + Parking + Tolls + Rideshare + Mileage + Shipping to + Shipping back | D52: =D25+D26+D27+D28+D29+D30+D23+D24 -> 62 | G52: =G25+G26+G27+G28+G29+G30+G23+G24 -> 62
B53: Trip Lead Total | C53: Per Traveler Subtotal x Travelers + trip-level costs | D53: =D51*D13+D52 -> 1202 | G53: =G51*G13+G52 -> 1275.05
B54: EWW Cost — Traveler 1 | C54: Rate x Hours (only if that traveler exists) | D54: =IF(1<=D13,D32*D33,0) -> 0 | G54: =IF(1<=G13,G32*G33,0) -> 260
B55: EWW Cost — Traveler 2 | C55: Rate x Hours (only if that traveler exists) | D55: =IF(2<=D13,D34*D35,0) -> 0 | G55: =IF(2<=G13,G34*G35,0) -> 0
B56: EWW Cost — Traveler 3 | C56: Rate x Hours (only if that traveler exists) | D56: =IF(3<=D13,D36*D37,0) -> 0 | G56: =IF(3<=G13,G36*G37,0) -> 0
B57: EWW Cost — Traveler 4 | C57: Rate x Hours (only if that traveler exists) | D57: =IF(4<=D13,D38*D39,0) -> 0 | G57: =IF(4<=G13,G38*G39,0) -> 0
B58: EWW Total | C58: Sum of the four EWW Costs | D58: =SUM(D54:D57) -> 0 | G58: =SUM(G54:G57) -> 260
B59: Grand Total (ODC + EWW) | C59: Trip Lead Total + EWW Total | D59: =D53+D58 -> 1202 | G59: =G53+G58 -> 1535.05
B60: Billable column, line by line (amount x multiplier, rounded to cents) | C60: Supervisor review "Billable to Prime" column, approved-email column, Prime form field
B61: Total Lodging Cost | C61: ROUND(Total Lodging Cost x multiplier, 2) | D61: =ROUND(D17*Setup!$C$5,2) -> 576.67 | G61: =ROUND(G17*Setup!$C$5,2) -> 659.02
B62: Airfare (avg) | C62: ROUND(Airfare (avg) x multiplier, 2) | D62: =ROUND(D20*Setup!$C$5,2) -> 335.97 | G62: =ROUND(G20*Setup!$C$5,2) -> 335.97
B63: Baggage | C63: ROUND(Baggage x multiplier, 2) | D63: =ROUND(D21*Setup!$C$5,2) -> 39.46 | G63: =ROUND(G21*Setup!$C$5,2) -> 39.46
B64: Airport Parking | C64: ROUND(Airport Parking x multiplier, 2) | D64: =ROUND(D22*Setup!$C$5,2) -> 60.88 | G64: =ROUND(G22*Setup!$C$5,2) -> 60.88
B65: Rental Car | C65: ROUND(Rental Car x multiplier, 2) | D65: =ROUND(D25*Setup!$C$5,2) -> 0 | G65: =ROUND(G25*Setup!$C$5,2) -> 0
B66: Gas | C66: ROUND(Gas x multiplier, 2) | D66: =ROUND(D26*Setup!$C$5,2) -> 0 | G66: =ROUND(G26*Setup!$C$5,2) -> 0
B67: Parking | C67: ROUND(Parking x multiplier, 2) | D67: =ROUND(D27*Setup!$C$5,2) -> 0 | G67: =ROUND(G27*Setup!$C$5,2) -> 0
B68: Tolls | C68: ROUND(Tolls x multiplier, 2) | D68: =ROUND(D28*Setup!$C$5,2) -> 0 | G68: =ROUND(G28*Setup!$C$5,2) -> 0
B69: Rideshare Estimate | C69: ROUND(Rideshare Estimate x multiplier, 2) | D69: =ROUND(D29*Setup!$C$5,2) -> 69.9 | G69: =ROUND(G29*Setup!$C$5,2) -> 69.9
B70: Mileage (Personal Vehicle) | C70: ROUND(Mileage (Personal Vehicle) x multiplier, 2) | D70: =ROUND(D30*Setup!$C$5,2) -> 0 | G70: =ROUND(G30*Setup!$C$5,2) -> 0
B71: Shipping (to) | C71: ROUND(Shipping (to) x multiplier, 2) | D71: =ROUND(D23*Setup!$C$5,2) -> 0 | G71: =ROUND(G23*Setup!$C$5,2) -> 0
B72: Shipping (back) | C72: ROUND(Shipping (back) x multiplier, 2) | D72: =ROUND(D24*Setup!$C$5,2) -> 0 | G72: =ROUND(G24*Setup!$C$5,2) -> 0
B73: Marked-up ODC | C73: (4 rounded per-traveler lines) x Travelers + (8 rounded trip-level lines) | D73: =(D61+D62+D64+D63)*D13+D65+D66+D67+D68+D69+D70+D71+D72 -> 1082.88 | G73: =(G61+G62+G64+G63)*G13+G65+G66+G67+G68+G69+G70+G71+G72 -> 1165.23
B74: Per Diem Meals, all travelers (not marked up) | C74: Per Diem x Travelers | D74: =D49*D13 -> 241.5 | G74: =G49*G13 -> 241.5
B75: Billable to Prime (ODC) | C75: Marked-up ODC + Per Diem all travelers | D75: =D73+D74 -> 1324.38 | G75: =G73+G74 -> 1406.73
B76: Grand Total to Prime | C76: Billable to Prime (ODC) + EWW Total | D76: =D75+D58 -> 1324.38 | G76: =G75+G58 -> 1666.73
B77: Markup added (information) | C77: Grand Total to Prime - Grand Total | D77: =D76-D59 -> 122.38 | G77: =G76-G59 -> 131.68
B78: Grand Total on lists right after submit | C78: Trip Lead Total + EWW if EWW was already saved | D78: =D53+D40*D58 -> 1202 | G78: =G53+G40*G58 -> 1275.05
B79: Average ROOM cost per night | C79: Room Cost / Nights (0 if no nights) | D79: =IF(D47>0,D16/D47,0) -> 135 | G79: =IF(G47>0,G16/G47,0) -> 156
B80: Over the GSA limit? | C80: YES when average room cost per night > GSA Lodging Rate | D80: =IF(AND(D47>0,D79>D14),"YES","No") -> No | G80: =IF(AND(G47>0,G79>G14),"YES","No") -> YES
B81: Total lodging per night (NOT used for the limit) | C81: Total Lodging / Nights — shown to prove fees/taxes are excluded | D81: =IF(D47>0,D17/D47,0) -> 170.5 | G81: =IF(G47>0,G17/G47,0) -> 194.85
B82: Typing check: Room + Fees + Taxes - Total | C82: Should be $0.00; if not, one of the four inputs was mistyped | D82: =ROUND(D16+D18+D19-D17,2) -> 0 | G82: =ROUND(G16+G18+G19-G17,2) -> 0
B83: Average of the three quote rates | C83: Shown in the quotes modal and on the Supervisor review | D83: =0 -> 0 | G83: =ROUND(AVERAGE(G41:G43),2) -> 146.33
B84: Per Traveler Subtotal as the Prime sees it | C84: Per Diem (unmarked) + the 4 rounded per-traveler lines | D84: =D49+D61+D62+D64+D63 -> 1254.48 | G84: =G49+G61+G62+G64+G63 -> 1336.83
A86: 3. SCREEN CHECKPOINTS — compare each screen to Expected, type what you see in the yellow cell
A87: Ref | B87: Field / what to read | C87: Screen label / how it is calculated | D87: S3a Expected | E87: Actual (you) | F87: Result | G87: S3b Expected | H87: Actual (you) | I87: Result
A88: A1 | B88: Nights | C88: Employee form (live) | D88: =D47 -> 3 | F88: =IF(E88="","",IF(ABS(E88-D88)<=Setup!$C$6,"PASS","FAIL")) | G88: =G47 -> 3 | I88: =IF(H88="","",IF(ABS(H88-G88)<=Setup!$C$6,"PASS","FAIL"))
A89: A2 | B89: Full Days (1x) | C89: Employee form (live) | D89: =D48 -> 2 | F89: =IF(E89="","",IF(ABS(E89-D89)<=Setup!$C$6,"PASS","FAIL")) | G89: =G48 -> 2 | I89: =IF(H89="","",IF(ABS(H89-G89)<=Setup!$C$6,"PASS","FAIL"))
A90: A3 | B90: Per Diem Meals Total | C90: Employee form (live) | D90: =D49 -> 241.5 | F90: =IF(E90="","",IF(ABS(E90-D90)<=Setup!$C$6,"PASS","FAIL")) | G90: =G49 -> 241.5 | I90: =IF(H90="","",IF(ABS(H90-G90)<=Setup!$C$6,"PASS","FAIL"))
A91: A4 | B91: Per Traveler Subtotal | C91: Employee form (live) | D91: =D51 -> 1140 | F91: =IF(E91="","",IF(ABS(E91-D91)<=Setup!$C$6,"PASS","FAIL")) | G91: =G51 -> 1213.05 | I91: =IF(H91="","",IF(ABS(H91-G91)<=Setup!$C$6,"PASS","FAIL"))
A92: A5 | B92: Trip Lead Total | C92: Employee form (live) | D92: =D53 -> 1202 | F92: =IF(E92="","",IF(ABS(E92-D92)<=Setup!$C$6,"PASS","FAIL")) | G92: =G53 -> 1275.05 | I92: =IF(H92="","",IF(ABS(H92-G92)<=Setup!$C$6,"PASS","FAIL"))
A93: B1 | B93: Grand Total right after submit | C93: My Estimates list AND Supervisor queue (before Supervisor enters EWW) | D93: =D78 -> 1202 | F93: =IF(E93="","",IF(ABS(E93-D93)<=Setup!$C$6,"PASS","FAIL")) | G93: =G78 -> 1275.05 | I93: =IF(H93="","",IF(ABS(H93-G93)<=Setup!$C$6,"PASS","FAIL"))
A94: C1 | B94: Per Traveler Subtotal | C94: Supervisor review | D94: =D51 -> 1140 | F94: =IF(E94="","",IF(ABS(E94-D94)<=Setup!$C$6,"PASS","FAIL")) | G94: =G51 -> 1213.05 | I94: =IF(H94="","",IF(ABS(H94-G94)<=Setup!$C$6,"PASS","FAIL"))
A95: C2 | B95: Trip Lead Total | C95: Supervisor review | D95: =D53 -> 1202 | F95: =IF(E95="","",IF(ABS(E95-D95)<=Setup!$C$6,"PASS","FAIL")) | G95: =G53 -> 1275.05 | I95: =IF(H95="","",IF(ABS(H95-G95)<=Setup!$C$6,"PASS","FAIL"))
A96: C3 | B96: EWW Total | C96: Supervisor review (after entering EWW) | D96: =D58 -> 0 | F96: =IF(E96="","",IF(ABS(E96-D96)<=Setup!$C$6,"PASS","FAIL")) | G96: =G58 -> 260 | I96: =IF(H96="","",IF(ABS(H96-G96)<=Setup!$C$6,"PASS","FAIL"))
A97: C4 | B97: Grand Total (ODC + EWW) | C97: Supervisor review | D97: =D59 -> 1202 | F97: =IF(E97="","",IF(ABS(E97-D97)<=Setup!$C$6,"PASS","FAIL")) | G97: =G59 -> 1535.05 | I97: =IF(H97="","",IF(ABS(H97-G97)<=Setup!$C$6,"PASS","FAIL"))
A98: C5 | B98: Billable to Prime (ODC) | C98: Supervisor review | D98: =D75 -> 1324.38 | F98: =IF(E98="","",IF(ABS(E98-D98)<=Setup!$C$6,"PASS","FAIL")) | G98: =G75 -> 1406.73 | I98: =IF(H98="","",IF(ABS(H98-G98)<=Setup!$C$6,"PASS","FAIL"))
A99: C6 | B99: Grand Total to Prime | C99: Supervisor review | D99: =D76 -> 1324.38 | F99: =IF(E99="","",IF(ABS(E99-D99)<=Setup!$C$6,"PASS","FAIL")) | G99: =G76 -> 1666.73 | I99: =IF(H99="","",IF(ABS(H99-G99)<=Setup!$C$6,"PASS","FAIL"))
A100: C7.1 | B100: EWW Cost — Traveler 1 | C100: Supervisor review (live as you type) | D100: =D54 -> 0 | F100: =IF(E100="","",IF(ABS(E100-D100)<=Setup!$C$6,"PASS","FAIL")) | G100: =G54 -> 260 | I100: =IF(H100="","",IF(ABS(H100-G100)<=Setup!$C$6,"PASS","FAIL"))
A101: CL.lodging | B101: Billable column: Total Lodging Cost | C101: Supervisor review > Billable to Prime Breakdown | D101: =D61 -> 576.67 | F101: =IF(E101="","",IF(ABS(E101-D101)<=Setup!$C$6,"PASS","FAIL")) | G101: =G61 -> 659.02 | I101: =IF(H101="","",IF(ABS(H101-G101)<=Setup!$C$6,"PASS","FAIL"))
A102: CL.airfare | B102: Billable column: Airfare (avg) | C102: Supervisor review > Billable to Prime Breakdown | D102: =D62 -> 335.97 | F102: =IF(E102="","",IF(ABS(E102-D102)<=Setup!$C$6,"PASS","FAIL")) | G102: =G62 -> 335.97 | I102: =IF(H102="","",IF(ABS(H102-G102)<=Setup!$C$6,"PASS","FAIL"))
A103: CL.baggage | B103: Billable column: Baggage | C103: Supervisor review > Billable to Prime Breakdown | D103: =D63 -> 39.46 | F103: =IF(E103="","",IF(ABS(E103-D103)<=Setup!$C$6,"PASS","FAIL")) | G103: =G63 -> 39.46 | I103: =IF(H103="","",IF(ABS(H103-G103)<=Setup!$C$6,"PASS","FAIL"))
A104: CL.airportParking | B104: Billable column: Airport Parking | C104: Supervisor review > Billable to Prime Breakdown | D104: =D64 -> 60.88 | F104: =IF(E104="","",IF(ABS(E104-D104)<=Setup!$C$6,"PASS","FAIL")) | G104: =G64 -> 60.88 | I104: =IF(H104="","",IF(ABS(H104-G104)<=Setup!$C$6,"PASS","FAIL"))
A105: CL.rideshare | B105: Billable column: Rideshare Estimate | C105: Supervisor review > Billable to Prime Breakdown | D105: =D69 -> 69.9 | F105: =IF(E105="","",IF(ABS(E105-D105)<=Setup!$C$6,"PASS","FAIL")) | G105: =G69 -> 69.9 | I105: =IF(H105="","",IF(ABS(H105-G105)<=Setup!$C$6,"PASS","FAIL"))
A106: D1 | B106: Grand Total after approval | C106: My Estimates list (now includes EWW) | D106: =D59 -> 1202 | F106: =IF(E106="","",IF(ABS(E106-D106)<=Setup!$C$6,"PASS","FAIL")) | G106: =G59 -> 1535.05 | I106: =IF(H106="","",IF(ABS(H106-G106)<=Setup!$C$6,"PASS","FAIL"))
A107: D2 | B107: Grand Total (Prime queue) | C107: Prime > Travel Authorizations queue | D107: =D76 -> 1324.38 | F107: =IF(E107="","",IF(ABS(E107-D107)<=Setup!$C$6,"PASS","FAIL")) | G107: =G76 -> 1666.73 | I107: =IF(H107="","",IF(ABS(H107-G107)<=Setup!$C$6,"PASS","FAIL"))
A108: E1 | B108: Per Traveler Subtotal | C108: Prime review form | D108: =D84 -> 1254.48 | F108: =IF(E108="","",IF(ABS(E108-D108)<=Setup!$C$6,"PASS","FAIL")) | G108: =G84 -> 1336.83 | I108: =IF(H108="","",IF(ABS(H108-G108)<=Setup!$C$6,"PASS","FAIL"))
...

Sheet S4
A1: S4 — Long stay, 4 travelers, 2 with EWW
A2: Maximum multiplier effect: 4 travelers, 10 nights, two EWW travelers with different rates and hours. Exercises traveler add/remove, an actual-date change on the expense side, and a variance on rideshare and return shipping.
A3: Travel type: Fly + rideshare + shipping | Expected emails: 8 | Fee multiplier from Setup tab
A5: 1. INPUTS — type these exactly (blue)
A6: Ref | B6: Field / what to read | C6: Screen label / how it is calculated | D6: S4
B7: Event Name | C7: Add your initials at the end | D7: S4 Training Cohort Onsite - xx
B8: City | D8: San Diego
B9: State | C9: Pick from the list | D9: CA
B10: Contract | C10: Pick any contract; note which one | D10: (any)
B11: Leave Date | D11: 46357
B12: Return Date | D12: 46367
B13: Travelers | C13: Traveler 2-4: pick any roster employee | D13: 4
B14: GSA Lodging Rate (per night) | C14: Overwrite AFTER the lookup finishes | D14: 189
B15: Meals (M&IE) Rate (per day) | C15: Overwrite AFTER the lookup finishes | D15: 79
B16: Room Cost (subject to per diem limit) | C16: Per traveler, whole stay | D16: 1764
B17: Total Lodging Cost (incl. taxes & fees) | C17: Per traveler, whole stay | D17: 2119.62
B18: Lodging Fees | C18: Recorded only | D18: 120
B19: Lodging Taxes | C19: Recorded only | D19: 235.62
B20: Airfare (avg) | C20: Per traveler | D20: 512
B21: Baggage | C21: Per traveler | D21: 70
B22: Airport Parking | C22: Per traveler | D22: 96
B23: Shipping (to) | C23: Trip-level | D23: 224
B24: Shipping (back) | C24: Trip-level | D24: 190
... B30: Mileage (Personal Vehicle) | C30: Trip-level | D30: 0
B31: Entered by the SUPERVISOR at review (not on the submit form)
B32: Traveler 1 EWW Rate (per hour) | C32: Supervisor review > EWW Rate | D32: 55
B33: Traveler 1 EWW Hours | D33: 8
B34: Traveler 2 EWW Rate (per hour) | D34: 0
B35: Traveler 2 EWW Hours | D35: 0
B36: Traveler 3 EWW Rate (per hour) | D36: 48.75
B37: Traveler 3 EWW Hours | D37: 16
B38: Traveler 4 EWW Rate (per hour) | D38: 0
B39: Traveler 4 EWW Hours | D39: 0
B40: EWW already saved when submitted? (1 = yes) | C40: Only a resubmission after a Supervisor return carries EWW | D40: 0
A42: 2. EXPECTED MATH — live formulas (read these to follow the arithmetic)
A43: Ref | B43: Field / what to read | C43: Screen label / how it is calculated | D43: S4
B44: Nights | C44: Return Date - Leave Date (never below 0) | D44: =MAX(0,D12-D11) -> 10
B45: Full Days (1x) | C45: Nights - 1, minimum 0 | D45: =MAX(D44-1,0) -> 9
B46: Per Diem Meals Total (per traveler) | C46: 1.5 x M&IE + Full Days x M&IE | D46: =1.5*D15+D45*D15 -> 829.5
B47: Per-traveler costs (excl. meals) | C47: Total Lodging + Airfare + Airport Parking + Baggage | D47: =D17+D20+D22+D21 -> 2797.62
B48: Per Traveler Subtotal | C48: Per Diem + per-traveler costs | D48: =D46+D47 -> 3627.12
B49: Trip-level costs | C49: Rental + Gas + Parking + Tolls + Rideshare + Mileage + Shipping to + Shipping back | D49: =D25+D26+D27+D28+D29+D30+D23+D24 -> 554
B50: Trip Lead Total | C50: Per Traveler Subtotal x Travelers + trip-level costs | D50: =D48*D13+D49 -> 15062.48
B51: EWW Cost — Traveler 1 | C51: Rate x Hours (only if that traveler exists) | D51: =IF(1<=D13,D32*D33,0) -> 440
B52: EWW Cost — Traveler 2 | C52: Rate x Hours (only if that traveler exists) | D52: =IF(2<=D13,D34*D35,0) -> 0
B53: EWW Cost — Traveler 3 | C53: Rate x Hours (only if that traveler exists) | D53: =IF(3<=D13,D36*D37,0) -> 780
B54: EWW Cost — Traveler 4 | C54: Rate x Hours (only if that traveler exists) | D54: =IF(4<=D13,D38*D39,0) -> 0
B55: EWW Total | C55: Sum of the four EWW Costs | D55: =SUM(D51:D54) -> 1220
B56: Grand Total (ODC + EWW) | C56: Trip Lead Total + EWW Total | D56: =D50+D55 -> 16282.48
B57: Billable column, line by line (amount x multiplier, rounded to cents) | C57: Supervisor review "Billable to Prime" column, approved-email column, Prime form field
B58: Total Lodging Cost | C58: ROUND(Total Lodging Cost x multiplier, 2) | D58: =ROUND(D17*Setup!$C$5,2) -> 2389.66
B59: Airfare (avg) | C59: ROUND(Airfare (avg) x multiplier, 2) | D59: =ROUND(D20*Setup!$C$5,2) -> 577.23
B60: Baggage | C60: ROUND(Baggage x multiplier, 2) | D60: =ROUND(D21*Setup!$C$5,2) -> 78.92
B61: Airport Parking | C61: ROUND(Airport Parking x multiplier, 2) | D61: =ROUND(D22*Setup!$C$5,2) -> 108.23
B62: Rental Car | C62: ROUND(Rental Car x multiplier, 2) | D62: =ROUND(D25*Setup!$C$5,2) -> 0
B63: Gas | C63: ROUND(Gas x multiplier, 2) | D63: =ROUND(D26*Setup!$C$5,2) -> 0
B64: Parking | C64: ROUND(Parking x multiplier, 2) | D64: =ROUND(D27*Setup!$C$5,2) -> 0
B65: Tolls | C65: ROUND(Tolls x multiplier, 2) | D65: =ROUND(D28*Setup!$C$5,2) -> 0
B66: Rideshare Estimate | C66: ROUND(Rideshare Estimate x multiplier, 2) | D66: =ROUND(D29*Setup!$C$5,2) -> 157.84
B67: Mileage (Personal Vehicle) | C67: ROUND(Mileage (Personal Vehicle) x multiplier, 2) | D67: =ROUND(D30*Setup!$C$5,2) -> 0
B68: Shipping (to) | C68: ROUND(Shipping (to) x multiplier, 2) | D68: =ROUND(D23*Setup!$C$5,2) -> 252.54
B69: Shipping (back) | C69: ROUND(Shipping (back) x multiplier, 2) | D69: =ROUND(D24*Setup!$C$5,2) -> 214.21
B70: Marked-up ODC | C70: (4 rounded per-traveler lines) x Travelers + (8 rounded trip-level lines) | D70: =(D58+D59+D61+D60)*D13+D62+D63+D64+D65+D66+D67+D68+D69 -> 13240.75
B71: Per Diem Meals, all travelers (not marked up) | C71: Per Diem x Travelers | D71: =D46*D13 -> 3318
B72: Billable to Prime (ODC) | C72: Marked-up ODC + Per Diem all travelers | D72: =D70+D71 -> 16558.75
B73: Grand Total to Prime | C73: Billable to Prime (ODC) + EWW Total | D73: =D72+D55 -> 17778.75
B74: Markup added (information) | C74: Grand Total to Prime - Grand Total | D74: =D73-D56 -> 1496.27
B75: Grand Total on lists right after submit | C75: Trip Lead Total + EWW if EWW was already saved | D75: =D50+D40*D55 -> 15062.48
B76: Average ROOM cost per night | C76: Room Cost / Nights (0 if no nights) | D76: =IF(D44>0,D16/D44,0) -> 176.4
B77: Over the GSA limit? | C77: YES when average room cost per night > GSA Lodging Rate | D77: =IF(AND(D44>0,D76>D14),"YES","No") -> No
B78: Total lodging per night (NOT used for the limit) | C78: Total Lodging / Nights — shown to prove fees/taxes are excluded | D78: =IF(D44>0,D17/D44,0) -> 211.962
B79: Typing check: Room + Fees + Taxes - Total | C79: Should be $0.00; if not, one of the four inputs was mistyped | D79: =ROUND(D16+D18+D19-D17,2) -> 0
B80: Per Traveler Subtotal as the Prime sees it | C80: Per Diem (unmarked) + the 4 rounded per-traveler lines | D80: =D46+D58+D59+D61+D60 -> 3983.54
A82: 3. SCREEN CHECKPOINTS — compare each screen to Expected, type what you see in the yellow cell
A83: Ref | B83: Field / what to read | C83: Screen label / how it is calculated | D83: S4 Expected | E83: Actual (you) | F83: Result
A84: A1 | B84: Nights | C84: Employee form (live) | D84: =D44 -> 10 | F84: =IF(E84="","",IF(ABS(E84-D84)<=Setup!$C$6,"PASS","FAIL"))
A85: A2 | B85: Full Days (1x) | C85: Employee form (live) | D85: =D45 -> 9 | F85: =IF(E85="","",IF(ABS(E85-D85)<=Setup!$C$6,"PASS","FAIL"))
A86: A3 | B86: Per Diem Meals Total | C86: Employee form (live) | D86: =D46 -> 829.5 | F86: =IF(E86="","",IF(ABS(E86-D86)<=Setup!$C$6,"PASS","FAIL"))
A87: A4 | B87: Per Traveler Subtotal | C87: Employee form (live) | D87: =D48 -> 3627.12 | F87: =IF(E87="","",IF(ABS(E87-D87)<=Setup!$C$6,"PASS","FAIL"))
A88: A5 | B88: Trip Lead Total | C88: Employee form (live) | D88: =D50 -> 15062.48 | F88: =IF(E88="","",IF(ABS(E88-D88)<=Setup!$C$6,"PASS","FAIL"))
A89: B1 | B89: Grand Total right after submit | C89: My Estimates list AND Supervisor queue (before Supervisor enters EWW) | D89: =D75 -> 15062.48 | F89: =IF(E89="","",IF(ABS(E89-D89)<=Setup!$C$6,"PASS","FAIL"))
A90: C1 | B90: Per Traveler Subtotal | C90: Supervisor review | D90: =D48 -> 3627.12 | F90: =IF(E90="","",IF(ABS(E90-D90)<=Setup!$C$6,"PASS","FAIL"))
A91: C2 | B91: Trip Lead Total | C91: Supervisor review | D91: =D50 -> 15062.48 | F91: =IF(E91="","",IF(ABS(E91-D91)<=Setup!$C$6,"PASS","FAIL"))
A92: C3 | B92: EWW Total | C92: Supervisor review (after entering EWW) | D92: =D55 -> 1220 | F92: =IF(E92="","",IF(ABS(E92-D92)<=Setup!$C$6,"PASS","FAIL"))
A93: C4 | B93: Grand Total (ODC + EWW) | C93: Supervisor review | D93: =D56 -> 16282.48 | F93: =IF(E93="","",IF(ABS(E93-D93)<=Setup!$C$6,"PASS","FAIL"))
A94: C5 | B94: Billable to Prime (ODC) | C94: Supervisor review | D94: =D72 -> 16558.75 | F94: =IF(E94="","",IF(ABS(E94-D94)<=Setup!$C$6,"PASS","FAIL"))
A95: C6 | B95: Grand Total to Prime | C95: Supervisor review | D95: =D73 -> 17778.75 | F95: =IF(E95="","",IF(ABS(E95-D95)<=Setup!$C$6,"PASS","FAIL"))
A96: C7.1 | B96: EWW Cost — Traveler 1 | C96: Supervisor review (live as you type) | D96: =D51 -> 440 | F96: =IF(E96="","",IF(ABS(E96-D96)<=Setup!$C$6,"PASS","FAIL"))
A97: C7.3 | B97: EWW Cost — Traveler 3 | C97: Supervisor review (live as you type) | D97: =D53 -> 780 | F97: =IF(E97="","",IF(ABS(E97-D97)<=Setup!$C$6,"PASS","FAIL"))
A98: CL.lodging | B98: Billable column: Total Lodging Cost | C98: Supervisor review > Billable to Prime Breakdown | D98: =D58 -> 2389.66 | F98: =IF(E98="","",IF(ABS(E98-D98)<=Setup!$C$6,"PASS","FAIL"))
A99: CL.airfare | B99: Billable column: Airfare (avg) | C99: Supervisor review > Billable to Prime Breakdown | D99: =D59 -> 577.23 | F99: =IF(E99="","",IF(ABS(E99-D99)<=Setup!$C$6,"PASS","FAIL"))
A100: CL.baggage | B100: Billable column: Baggage | C100: Supervisor review > Billable to Prime Breakdown | D100: =D60 -> 78.92 | F100: =IF(E100="","",IF(ABS(E100-D100)<=Setup!$C$6,"PASS","FAIL"))
A101: CL.airportParking | B101: Billable column: Airport Parking | C101: Supervisor review > Billable to Prime Breakdown | D101: =D61 -> 108.23 | F101: =IF(E101="","",IF(ABS(E101-D101)<=Setup!$C$6,"PASS","FAIL"))
A102: CL.rideshare | B102: Billable column: Rideshare Estimate | C102: Supervisor review > Billable to Prime Breakdown | D102: =D66 -> 157.84 | F102: =IF(E102="","",IF(ABS(E102-D102)<=Setup!$C$6,"PASS","FAIL"))
A103: CL.shipTo | B103: Billable column: Shipping (to) | C103: Supervisor review > Billable to Prime Breakdown | D103: =D68 -> 252.54 | F103: =IF(E103="","",IF(ABS(E103-D103)<=Setup!$C$6,"PASS","FAIL"))
A104: CL.shipBack | B104: Billable column: Shipping (back) | C104: Supervisor review > Billable to Prime Breakdown | D104: =D69 -> 214.21 | F104: =IF(E104="","",IF(ABS(E104-D104)<=Setup!$C$6,"PASS","FAIL"))
A105: D1 | B105: Grand Total after approval | C105: My Estimates list (now includes EWW) | D105: =D56 -> 16282.48 | F105: =IF(E105="","",IF(ABS(E105-D105)<=Setup!$C$6,"PASS","FAIL"))
A106: D2 | B106: Grand Total (Prime queue) | C106: Prime > Travel Authorizations queue | D106: =D73 -> 17778.75 | F106: =IF(E106="","",IF(ABS(E106-D106)<=Setup!$C$6,"PASS","FAIL"))
A107: E1 | B107: Per Traveler Subtotal | C107: Prime review form | D107: =D80 -> 3983.54 | F107: =IF(E107="","",IF(ABS(E107-D107)<=Setup!$C$6,"PASS","FAIL"))
A108: E2 | B108: Trip Lead Total | C108: Prime review form | D108: =D72 -> 16558.75 | F108: =IF(E108="","",IF(ABS(E108-D108)<=Setup!$C$6,"PASS","FAIL"))
...

Sheet S5
A1: S5 — Edge dates: one night and same day
A2: GSA first/last-day rule at its boundaries. One night = two 75% days (1.5x M&IE, zero full days). Same day (0 nights) is an observation: record what the app produces and take it to the team (Watch W1 has the question written out).
A3: Travel type: Fly (1 night) / local (same day) | Expected emails: 9 | Fee multiplier from Setup tab
A5: 1. INPUTS — type these exactly (blue)
A6: Ref | B6: Field / what to read | C6: Screen label / how it is calculated | D6: S5a | G6: S5b
B7: Event Name | C7: Add your initials at the end | D7: S5a One Night Trip - xx | G7: S5b Same Day Trip - xx
B8: City | D8: Raleigh | G8: Charlotte
B9: State | C9: Pick from the list | D9: NC | G9: NC
B10: Contract | C10: Pick any contract; note which one | D10: (any) | G10: (any)
B11: Leave Date | D11: 46370 | G11: 46373
B12: Return Date | D12: 46371 | G12: 46373
B13: Travelers | C13: Traveler 2-4: pick any roster employee | D13: 1 | G13: 1
B14: GSA Lodging Rate (per night) | C14: Overwrite AFTER the lookup finishes | D14: 135 | G14: 130
B15: Meals (M&IE) Rate (per day) | C15: Overwrite AFTER the lookup finishes | D15: 64 | G15: 64
B16: Room Cost (subject to per diem limit) | C16: Per traveler, whole stay | D16: 128 | G16: 0
B17: Total Lodging Cost (incl. taxes & fees) | C17: Per traveler, whole stay | D17: 145.92 | G17: 0
B18: Lodging Fees | C18: Recorded only | D18: 0 | G18: 0
B19: Lodging Taxes | C19: Recorded only | D19: 17.92 | G19: 0
B20: Airfare (avg) | C20: Per traveler | D20: 244 | G20: 0
B21: Baggage | C21: Per traveler | D21: 0 | G21: 0
B22: Airport Parking | C22: Per traveler | D22: 0 | G22: 0
B23: Shipping (to) | C23: Trip-level | D23: 0 | G23: 0
B24: Shipping (back) | C24: Trip-level | D24: 0 | G24: 0
... B30: Mileage (Personal Vehicle) | C30: Trip-level | D30: 0 | G30: 0
B31: Entered by the SUPERVISOR at review (not on the submit form)
B32: Traveler 1 EWW Rate (per hour) | C32: Supervisor review > EWW Rate | D32: 40 | G32: 0
B33: Traveler 1 EWW Hours | D33: 6 | G33: 0
B34: Traveler 2 EWW Rate (per hour) | D34: 0 | G34: 0
B35: Traveler 2 EWW Hours | D35: 0 | G35: 0
B36: Traveler 3 EWW Rate (per hour) | D36: 0 | G36: 0
B37: Traveler 3 EWW Hours | D37: 0 | G37: 0
B38: Traveler 4 EWW Rate (per hour) | D38: 0 | G38: 0
B39: Traveler 4 EWW Hours | D39: 0 | G39: 0
B40: EWW already saved when submitted? (1 = yes) | C40: Only a resubmission after a Supervisor return carries EWW | D40: 0 | G40: 0
A42: 2. EXPECTED MATH — live formulas (read these to follow the arithmetic)
A43: Ref | B43: Field / what to read | C43: Screen label / how it is calculated | D43: S5a | G43: S5b
B44: Nights | C44: Return Date - Leave Date (never below 0) | D44: =MAX(0,D12-D11) -> 1 | G44: =MAX(0,G12-G11) -> 0
B45: Full Days (1x) | C45: Nights - 1, minimum 0 | D45: =MAX(D44-1,0) -> 0 | G45: =MAX(G44-1,0) -> 0
B46: Per Diem Meals Total (per traveler) | C46: 1.5 x M&IE + Full Days x M&IE | D46: =1.5*D15+D45*D15 -> 96 | G46: =1.5*G15+G45*G15 -> 96
B47: Per-traveler costs (excl. meals) | C47: Total Lodging + Airfare + Airport Parking + Baggage | D47: =D17+D20+D22+D21 -> 389.92 | G47: =G17+G20+G22+G21 -> 0
B48: Per Traveler Subtotal | C48: Per Diem + per-traveler costs | D48: =D46+D47 -> 485.92 | G48: =G46+G47 -> 96
B49: Trip-level costs | C49: Rental + Gas + Parking + Tolls + Rideshare + Mileage + Shipping to + Shipping back | D49: =D25+D26+D27+D28+D29+D30+D23+D24 -> 58 | G49: =G25+G26+G27+G28+G29+G30+G23+G24 -> 40
B50: Trip Lead Total | C50: Per Traveler Subtotal x Travelers + trip-level costs | D50: =D48*D13+D49 -> 543.92 | G50: =G48*G13+G49 -> 136
B51: EWW Cost — Traveler 1 | C51: Rate x Hours (only if that traveler exists) | D51: =IF(1<=D13,D32*D33,0) -> 240 | G51: =IF(1<=G13,G32*G33,0) -> 0
B52: EWW Cost — Traveler 2 | C52: Rate x Hours (only if that traveler exists) | D52: =IF(2<=D13,D34*D35,0) -> 0 | G52: =IF(2<=G13,G34*G35,0) -> 0
B53: EWW Cost — Traveler 3 | C53: Rate x Hours (only if that traveler exists) | D53: =IF(3<=D13,D36*D37,0) -> 0 | G53: =IF(3<=G13,G36*G37,0) -> 0
B54: EWW Cost — Traveler 4 | C54: Rate x Hours (only if that traveler exists) | D54: =IF(4<=D13,D38*D39,0) -> 0 | G54: =IF(4<=G13,G38*G39,0) -> 0
B55: EWW Total | C55: Sum of the four EWW Costs | D55: =SUM(D51:D54) -> 240 | G55: =SUM(G51:G54) -> 0
B56: Grand Total (ODC + EWW) | C56: Trip Lead Total + EWW Total | D56: =D50+D55 -> 783.92 | G56: =G50+G55 -> 136
B57: Billable column, line by line (amount x multiplier, rounded to cents) | C57: Supervisor review "Billable to Prime" column, approved-email column, Prime form field
B58: Total Lodging Cost | C58: ROUND(Total Lodging Cost x multiplier, 2) | D58: =ROUND(D17*Setup!$C$5,2) -> 164.51 | G58: =ROUND(G17*Setup!$C$5,2) -> 0
B59: Airfare (avg) | C59: ROUND(Airfare (avg) x multiplier, 2) | D59: =ROUND(D20*Setup!$C$5,2) -> 275.09 | G59: =ROUND(G20*Setup!$C$5,2) -> 0
B60: Baggage | C60: ROUND(Baggage x multiplier, 2) | D60: =ROUND(D21*Setup!$C$5,2) -> 0 | G60: =ROUND(G21*Setup!$C$5,2) -> 0
B61: Airport Parking | C61: ROUND(Airport Parking x multiplier, 2) | D61: =ROUND(D22*Setup!$C$5,2) -> 0 | G61: =ROUND(G22*Setup!$C$5,2) -> 0
B62: Rental Car | C62: ROUND(Rental Car x multiplier, 2) | D62: =ROUND(D25*Setup!$C$5,2) -> 0 | G62: =ROUND(G25*Setup!$C$5,2) -> 0
B63: Gas | C63: ROUND(Gas x multiplier, 2) | D63: =ROUND(D26*Setup!$C$5,2) -> 0 | G63: =ROUND(G26*Setup!$C$5,2) -> 0
B64: Parking | C64: ROUND(Parking x multiplier, 2) | D64: =ROUND(D27*Setup!$C$5,2) -> 0 | G64: =ROUND(G27*Setup!$C$5,2) -> 0
B65: Tolls | C65: ROUND(Tolls x multiplier, 2) | D65: =ROUND(D28*Setup!$C$5,2) -> 0 | G65: =ROUND(G28*Setup!$C$5,2) -> 0
B66: Rideshare Estimate | C66: ROUND(Rideshare Estimate x multiplier, 2) | D66: =ROUND(D29*Setup!$C$5,2) -> 65.39 | G66: =ROUND(G29*Setup!$C$5,2) -> 45.1
B67: Mileage (Personal Vehicle) | C67: ROUND(Mileage (Personal Vehicle) x multiplier, 2) | D67: =ROUND(D30*Setup!$C$5,2) -> 0 | G67: =ROUND(G30*Setup!$C$5,2) -> 0
B68: Shipping (to) | C68: ROUND(Shipping (to) x multiplier, 2) | D68: =ROUND(D23*Setup!$C$5,2) -> 0 | G68: =ROUND(G23*Setup!$C$5,2) -> 0
B69: Shipping (back) | C69: ROUND(Shipping (back) x multiplier, 2) | D69: =ROUND(D24*Setup!$C$5,2) -> 0 | G69: =ROUND(G24*Setup!$C$5,2) -> 0
B70: Marked-up ODC | C70: (4 rounded per-traveler lines) x Travelers + (8 rounded trip-level lines) | D70: =(D58+D59+D61+D60)*D13+D62+D63+D64+D65+D66+D67+D68+D69 -> 504.99 | G70: =(G58+G59+G61+G60)*G13+G62+G63+G64+G65+G66+G67+G68+G69 -> 45.1
B71: Per Diem Meals, all travelers (not marked up) | C71: Per Diem x Travelers | D71: =D46*D13 -> 96 | G71: =G46*G13 -> 96
B72: Billable to Prime (ODC) | C72: Marked-up ODC + Per Diem all travelers | D72: =D70+D71 -> 600.99 | G72: =G70+G71 -> 141.1
B73: Grand Total to Prime | C73: Billable to Prime (ODC) + EWW Total | D73: =D72+D55 -> 840.99 | G73: =G72+G55 -> 141.1
B74: Markup added (information) | C74: Grand Total to Prime - Grand Total | D74: =D73-D56 -> 57.07 | G74: =G73-G56 -> 5.1
B75: Grand Total on lists right after submit | C75: Trip Lead Total + EWW if EWW was already saved | D75: =D50+D40*D55 -> 543.92 | G75: =G50+G40*G55 -> 136
B76: Average ROOM cost per night | C76: Room Cost / Nights (0 if no nights) | D76: =IF(D44>0,D16/D44,0) -> 128 | G76: =IF(G44>0,G16/G44,0) -> 0
B77: Over the GSA limit? | C77: YES when average room cost per night > GSA Lodging Rate | D77: =IF(AND(D44>0,D76>D14),"YES","No") -> No | G77: =IF(AND(G44>0,G76>G14),"YES","No") -> No
B78: Total lodging per night (NOT used for the limit) | C78: Total Lodging / Nights — shown to prove fees/taxes are excluded | D78: =IF(D44>0,D17/D44,0) -> 145.92 | G78: =IF(G44>0,G17/G44,0) -> 0
B79: Typing check: Room + Fees + Taxes - Total | C79: Should be $0.00; if not, one of the four inputs was mistyped | D79: =ROUND(D16+D18+D19-D17,2) -> 0 | G79: =ROUND(G16+G18+G19-G17,2) -> 0
B80: Per Traveler Subtotal as the Prime sees it | C80: Per Diem (unmarked) + the 4 rounded per-traveler lines | D80: =D46+D58+D59+D61+D60 -> 535.6 | G80: =G46+G58+G59+G61+G60 -> 96
A82: 3. SCREEN CHECKPOINTS — compare each screen to Expected, type what you see in the yellow cell
A83: Ref | B83: Field / what to read | C83: Screen label / how it is calculated | D83: S5a Expected | E83: Actual (you) | F83: Result | G83: S5b Expected | H83: Actual (you) | I83: Result
A84: A1 | B84: Nights | C84: Employee form (live) | D84: =D44 -> 1 | F84: =IF(E84="","",IF(ABS(E84-D84)<=Setup!$C$6,"PASS","FAIL")) | G84: =G44 -> 0 | I84: =IF(H84="","",IF(ABS(H84-G84)<=Setup!$C$6,"PASS","FAIL"))
A85: A2 | B85: Full Days (1x) | C85: Employee form (live) | D85: =D45 -> 0 | F85: =IF(E85="","",IF(ABS(E85-D85)<=Setup!$C$6,"PASS","FAIL")) | G85: =G45 -> 0 | I85: =IF(H85="","",IF(ABS(H85-G85)<=Setup!$C$6,"PASS","FAIL"))
A86: A3 | B86: Per Diem Meals Total | C86: Employee form (live) | D86: =D46 -> 96 | F86: =IF(E86="","",IF(ABS(E86-D86)<=Setup!$C$6,"PASS","FAIL")) | G86: =G46 -> 96 | I86: =IF(H86="","",IF(ABS(H86-G86)<=Setup!$C$6,"PASS","FAIL"))
A87: A4 | B87: Per Traveler Subtotal | C87: Employee form (live) | D87: =D48 -> 485.92 | F87: =IF(E87="","",IF(ABS(E87-D87)<=Setup!$C$6,"PASS","FAIL")) | G87: =G48 -> 96 | I87: =IF(H87="","",IF(ABS(H87-G87)<=Setup!$C$6,"PASS","FAIL"))
A88: A5 | B88: Trip Lead Total | C88: Employee form (live) | D88: =D50 -> 543.92 | F88: =IF(E88="","",IF(ABS(E88-D88)<=Setup!$C$6,"PASS","FAIL")) | G88: =G50 -> 136 | I88: =IF(H88="","",IF(ABS(H88-G88)<=Setup!$C$6,"PASS","FAIL"))
A89: B1 | B89: Grand Total right after submit | C89: My Estimates list AND Supervisor queue (before Supervisor enters EWW) | D89: =D75 -> 543.92 | F89: =IF(E89="","",IF(ABS(E89-D89)<=Setup!$C$6,"PASS","FAIL")) | G89: =G75 -> 136 | I89: =IF(H89="","",IF(ABS(H89-G89)<=Setup!$C$6,"PASS","FAIL"))
A90: C1 | B90: Per Traveler Subtotal | C90: Supervisor review | D90: =D48 -> 485.92 | F90: =IF(E90="","",IF(ABS(E90-D90)<=Setup!$C$6,"PASS","FAIL")) | G90: =G48 -> 96 | I90: =IF(H90="","",IF(ABS(H90-G90)<=Setup!$C$6,"PASS","FAIL"))
A91: C2 | B91: Trip Lead Total | C91: Supervisor review | D91: =D50 -> 543.92 | F91: =IF(E91="","",IF(ABS(E91-D91)<=Setup!$C$6,"PASS","FAIL")) | G91: =G50 -> 136 | I91: =IF(H91="","",IF(ABS(H91-G91)<=Setup!$C$6,"PASS","FAIL"))
A92: C3 | B92: EWW Total | C92: Supervisor review (after entering EWW) | D92: =D55 -> 240 | F92: =IF(E92="","",IF(ABS(E92-D92)<=Setup!$C$6,"PASS","FAIL")) | G92: =G55 -> 0 | I92: =IF(H92="","",IF(ABS(H92-G92)<=Setup!$C$6,"PASS","FAIL"))
A93: C4 | B93: Grand Total (ODC + EWW) | C93: Supervisor review | D93: =D56 -> 783.92 | F93: =IF(E93="","",IF(ABS(E93-D93)<=Setup!$C$6,"PASS","FAIL")) | G93: =G56 -> 136 | I93: =IF(H93="","",IF(ABS(H93-G93)<=Setup!$C$6,"PASS","FAIL"))
A94: C5 | B94: Billable to Prime (ODC) | C94: Supervisor review | D94: =D72 -> 600.99 | F94: =IF(E94="","",IF(ABS(E94-D94)<=Setup!$C$6,"PASS","FAIL")) | G94: =G72 -> 141.1 | I94: =IF(H94="","",IF(ABS(H94-G94)<=Setup!$C$6,"PASS","FAIL"))
A95: C6 | B95: Grand Total to Prime | C95: Supervisor review | D95: =D73 -> 840.99 | F95: =IF(E95="","",IF(ABS(E95-D95)<=Setup!$C$6,"PASS","FAIL")) | G95: =G73 -> 141.1 | I95: =IF(H95="","",IF(ABS(H95-G95)<=Setup!$C$6,"PASS","FAIL"))
A96: C7.1 | B96: EWW Cost — Traveler 1 | C96: Supervisor review (live as you type) | D96: =D51 -> 240 | F96: =IF(E96="","",IF(ABS(E96-D96)<=Setup!$C$6,"PASS","FAIL")) | G96: =G51 -> 0 | I96: =IF(H96="","",IF(ABS(H96-G96)<=Setup!$C$6,"PASS","FAIL"))
A97: CL.lodging | B97: Billable column: Total Lodging Cost | C97: Supervisor review > Billable to Prime Breakdown | D97: =D58 -> 164.51 | F97: =IF(E97="","",IF(ABS(E97-D97)<=Setup!$C$6,"PASS","FAIL")) | G97: =G58 -> 0 | I97: =IF(H97="","",IF(ABS(H97-G97)<=Setup!$C$6,"PASS","FAIL"))
A98: CL.airfare | B98: Billable column: Airfare (avg) | C98: Supervisor review > Billable to Prime Breakdown | D98: =D59 -> 275.09 | F98: =IF(E98="","",IF(ABS(E98-D98)<=Setup!$C$6,"PASS","FAIL")) | G98: =G59 -> 0 | I98: =IF(H98="","",IF(ABS(H98-G98)<=Setup!$C$6,"PASS","FAIL"))
A99: CL.rideshare | B99: Billable column: Rideshare Estimate | C99: Supervisor review > Billable to Prime Breakdown | D99: =D66 -> 65.39 | F99: =IF(E99="","",IF(ABS(E99-D99)<=Setup!$C$6,"PASS","FAIL")) | G99: =G66 -> 45.1 | I99: =IF(H99="","",IF(ABS(H99-G99)<=Setup!$C$6,"PASS","FAIL"))
A100: D1 | B100: Grand Total after approval | C100: My Estimates list (now includes EWW) | D100: =D56 -> 783.92 | F100: =IF(E100="","",IF(ABS(E100-D100)<=Setup!$C$6,"PASS","FAIL")) | G100: =G56 -> 136 | I100: =IF(H100="","",IF(ABS(H100-G100)<=Setup!$C$6,"PASS","FAIL"))
A101: D2 | B101: Grand Total (Prime queue) | C101: Prime > Travel Authorizations queue | D101: =D73 -> 840.99 | F101: =IF(E101="","",IF(ABS(E101-D101)<=Setup!$C$6,"PASS","FAIL")) | G101: =G73 -> 141.1 | I101: =IF(H101="","",IF(ABS(H101-G101)<=Setup!$C$6,"PASS","FAIL"))
A102: E1 | B102: Per Traveler Subtotal | C102: Prime review form | D102: =D80 -> 535.6 | F102: =IF(E102="","",IF(ABS(E102-D102)<=Setup!$C$6,"PASS","FAIL")) | G102: =G80 -> 96 | I102: =IF(H102="","",IF(ABS(H102-G102)<=Setup!$C$6,"PASS","FAIL"))
A103: E2 | B103: Trip Lead Total | C103: Prime review form | D103: =D72 -> 600.99 | F103: =IF(E103="","",IF(ABS(E103-D103)<=Setup!$C$6,"PASS","FAIL")) | G103: =G72 -> 141.1 | I103: =IF(H103="","",IF(ABS(H103-G103)<=Setup!$C$6,"PASS","FAIL"))
A104: E3 | B104: EWW Total | C104: Prime review form | D104: =D55 -> 240 | F104: =IF(E104="","",IF(ABS(E104-D104)<=Setup!$C$6,"PASS","FAIL")) | G104: =G55 -> 0 | I104: =IF(H104="","",IF(ABS(H104-G104)<=Setup!$C$6,"PASS","FAIL"))
A105: E4 | B105: Grand Total (must equal D2 exactly) | C105: Prime review form | D105: =D73 -> 840.99 | F105: =IF(E105="","",IF(ABS(E105-D105)<=Setup!$C$6,"PASS","FAIL")) | G105: =G73 -> 141.1 | I105: =IF(H105="","",IF(ABS(H105-G105)<=Setup!$C$6,"PASS","FAIL"))
A106: F1 | B106: Average room cost per night | C106: Employee form warning text / math only | D106: =D76 -> 128 | F106: =IF(E106="","",IF(ABS(E106-D106)<=Setup!$C$6,"PASS","FAIL")) | G106: =G76 -> 0 | I106: =IF(H106="","",IF(ABS(H106-G106)<=Setup!$C$6,"PASS","FAIL"))
A107: F2 | B107: Red over-limit warning shown? (type YES or No) | C107: Employee form | D107: =D77 -> No | F107: =IF(E107="","",IF(UPPER(E107)=UPPER(D107),"PASS","FAIL")) | G107: =G77 -> No | I107: =IF(H107="","",IF(UPPER(H107)=UPPER(G107),"PASS","FAIL"))
A108: F3 | B108: Total lodging per night (NOT used for the limit) | C108: Information only | D108: =D78 -> 145.92 | F108: info | G108: =G78 -> 0 | I108: info
...

Sheet S6
A1: S6 — Validation rules + Supervisor return and resubmit
A2: Every blocking rule on the estimate form, then a Return round-trip: the Supervisor enters EWW and returns the estimate, the employee sees the note, corrects airfare and resubmits, and the EWW survives.
A3: Travel type: Fly, 2 travelers | Expected emails: 8 | Fee multiplier from Setup tab
A5: 1. INPUTS — type these exactly (blue)
A6: Ref | B6: Field / what to read | C6: Screen label / how it is calculated | D6: S6 v1 | G6: S6 v2
B7: Event Name | C7: Add your initials at the end | D7: S6 Return And Resubmit - xx | G7: S6 Return And Resubmit - xx
B8: City | D8: Houston | G8: Houston
B9: State | C9: Pick from the list | D9: TX | G9: TX
B10: Contract | C10: Pick any contract; note which one | D10: (any) | G10: (any)
B11: Leave Date | D11: 46363 | G11: 46363
B12: Return Date | D12: 46366 | G12: 46366
B13: Travelers | C13: Traveler 2-4: pick any roster employee | D13: 2 | G13: 2
B14: GSA Lodging Rate (per night) | C14: Overwrite AFTER the lookup finishes | D14: 142 | G14: 142
B15: Meals (M&IE) Rate (per day) | C15: Overwrite AFTER the lookup finishes | D15: 71 | G15: 71
B16: Room Cost (subject to per diem limit) | C16: Per traveler, whole stay | D16: 396 | G16: 396
B17: Total Lodging Cost (incl. taxes & fees) | C17: Per traveler, whole stay | D17: 477.46 | G17: 477.46
B18: Lodging Fees | C18: Recorded only | D18: 28 | G18: 28
B19: Lodging Taxes | C19: Recorded only | D19: 53.46 | G19: 53.46
B20: Airfare (avg) | C20: Per traveler | D20: 640 | G20: 512
B21: Baggage | C21: Per traveler | D21: 35 | G21: 35
B22: Airport Parking | C22: Per traveler | D22: 48 | G22: 48
B23: Shipping (to) | C23: Trip-level | D23: 0 | G23: 0
B24: Shipping (back) | C24: Trip-level | D24: 0 | G24: 0
... B30: Mileage (Personal Vehicle) | C30: Trip-level | D30: 0 | G30: 0
B31: Entered by the SUPERVISOR at review (not on the submit form)
B32: Traveler 1 EWW Rate (per hour) | C32: Supervisor review > EWW Rate | D32: 45 | G32: 45
B33: Traveler 1 EWW Hours | D33: 10 | G33: 10
B34: Traveler 2 EWW Rate (per hour) | D34: 0 | G34: 0
B35: Traveler 2 EWW Hours | D35: 0 | G35: 0
B36: Traveler 3 EWW Rate (per hour) | D36: 0 | G36: 0
B37: Traveler 3 EWW Hours | D37: 0 | G37: 0
B38: Traveler 4 EWW Rate (per hour) | D38: 0 | G38: 0
B39: Traveler 4 EWW Hours | D39: 0 | G39: 0
B40: EWW already saved when submitted? (1 = yes) | C40: Only a resubmission after a Supervisor return carries EWW | D40: 0 | G40: 1
A42: 2. EXPECTED MATH — live formulas (read these to follow the arithmetic)
A43: Ref | B43: Field / what to read | C43: Screen label / how it is calculated | D43: S6 v1 | G43: S6 v2
B44: Nights | C44: Return Date - Leave Date (never below 0) | D44: =MAX(0,D12-D11) -> 3 | G44: =MAX(0,G12-G11) -> 3
B45: Full Days (1x) | C45: Nights - 1, minimum 0 | D45: =MAX(D44-1,0) -> 2 | G45: =MAX(G44-1,0) -> 2
B46: Per Diem Meals Total (per traveler) | C46: 1.5 x M&IE + Full Days x M&IE | D46: =1.5*D15+D45*D15 -> 248.5 | G46: =1.5*G15+G45*G15 -> 248.5
B47: Per-traveler costs (excl. meals) | C47: Total Lodging + Airfare + Airport Parking + Baggage | D47: =D17+D20+D22+D21 -> 1200.46 | G47: =G17+G20+G22+G21 -> 1072.46
B48: Per Traveler Subtotal | C48: Per Diem + per-traveler costs | D48: =D46+D47 -> 1448.96 | G48: =G46+G47 -> 1320.96
B49: Trip-level costs | C49: Rental + Gas + Parking + Tolls + Rideshare + Mileage + Shipping to + Shipping back | D49: =D25+D26+D27+D28+D29+D30+D23+D24 -> 96 | G49: =G25+G26+G27+G28+G29+G30+G23+G24 -> 96
B50: Trip Lead Total | C50: Per Traveler Subtotal x Travelers + trip-level costs | D50: =D48*D13+D49 -> 2993.92 | G50: =G48*G13+G49 -> 2737.92
B51: EWW Cost — Traveler 1 | C51: Rate x Hours (only if that traveler exists) | D51: =IF(1<=D13,D32*D33,0) -> 450 | G51: =IF(1<=G13,G32*G33,0) -> 450
B52: EWW Cost — Traveler 2 | C52: Rate x Hours (only if that traveler exists) | D52: =IF(2<=D13,D34*D35,0) -> 0 | G52: =IF(2<=G13,G34*G35,0) -> 0
B53: EWW Cost — Traveler 3 | C53: Rate x Hours (only if that traveler exists) | D53: =IF(3<=D13,D36*D37,0) -> 0 | G53: =IF(3<=G13,G36*G37,0) -> 0
B54: EWW Cost — Traveler 4 | C54: Rate x Hours (only if that traveler exists) | D54: =IF(4<=D13,D38*D39,0) -> 0 | G54: =IF(4<=G13,G38*G39,0) -> 0
B55: EWW Total | C55: Sum of the four EWW Costs | D55: =SUM(D51:D54) -> 450 | G55: =SUM(G51:G54) -> 450
B56: Grand Total (ODC + EWW) | C56: Trip Lead Total + EWW Total | D56: =D50+D55 -> 3443.92 | G56: =G50+G55 -> 3187.92
B57: Billable column, line by line (amount x multiplier, rounded to cents) | C57: Supervisor review "Billable to Prime" column, approved-email column, Prime form field
B58: Total Lodging Cost | C58: ROUND(Total Lodging Cost x multiplier, 2) | D58: =ROUND(D17*Setup!$C$5,2) -> 538.29 | G58: =ROUND(G17*Setup!$C$5,2) -> 538.29
B59: Airfare (avg) | C59: ROUND(Airfare (avg) x multiplier, 2) | D59: =ROUND(D20*Setup!$C$5,2) -> 721.54 | G59: =ROUND(G20*Setup!$C$5,2) -> 577.23
B60: Baggage | C60: ROUND(Baggage x multiplier, 2) | D60: =ROUND(D21*Setup!$C$5,2) -> 39.46 | G60: =ROUND(G21*Setup!$C$5,2) -> 39.46
B61: Airport Parking | C61: ROUND(Airport Parking x multiplier, 2) | D61: =ROUND(D22*Setup!$C$5,2) -> 54.12 | G61: =ROUND(G22*Setup!$C$5,2) -> 54.12
B62: Rental Car | C62: ROUND(Rental Car x multiplier, 2) | D62: =ROUND(D25*Setup!$C$5,2) -> 0 | G62: =ROUND(G25*Setup!$C$5,2) -> 0
B63: Gas | C63: ROUND(Gas x multiplier, 2) | D63: =ROUND(D26*Setup!$C$5,2) -> 0 | G63: =ROUND(G26*Setup!$C$5,2) -> 0
B64: Parking | C64: ROUND(Parking x multiplier, 2) | D64: =ROUND(D27*Setup!$C$5,2) -> 0 | G64: =ROUND(G27*Setup!$C$5,2) -> 0
B65: Tolls | C65: ROUND(Tolls x multiplier, 2) | D65: =ROUND(D28*Setup!$C$5,2) -> 0 | G65: =ROUND(G28*Setup!$C$5,2) -> 0
B66: Rideshare Estimate | C66: ROUND(Rideshare Estimate x multiplier, 2) | D66: =ROUND(D29*Setup!$C$5,2) -> 108.23 | G66: =ROUND(G29*Setup!$C$5,2) -> 108.23
B67: Mileage (Personal Vehicle) | C67: ROUND(Mileage (Personal Vehicle) x multiplier, 2) | D67: =ROUND(D30*Setup!$C$5,2) -> 0 | G67: =ROUND(G30*Setup!$C$5,2) -> 0
B68: Shipping (to) | C68: ROUND(Shipping (to) x multiplier, 2) | D68: =ROUND(D23*Setup!$C$5,2) -> 0 | G68: =ROUND(G23*Setup!$C$5,2) -> 0
B69: Shipping (back) | C69: ROUND(Shipping (back) x multiplier, 2) | D69: =ROUND(D24*Setup!$C$5,2) -> 0 | G69: =ROUND(G24*Setup!$C$5,2) -> 0
B70: Marked-up ODC | C70: (4 rounded per-traveler lines) x Travelers + (8 rounded trip-level lines) | D70: =(D58+D59+D61+D60)*D13+D62+D63+D64+D65+D66+D67+D68+D69 -> 2815.05 | G70: =(G58+G59+G61+G60)*G13+G62+G63+G64+G65+G66+G67+G68+G69 -> 2526.43
B71: Per Diem Meals, all travelers (not marked up) | C71: Per Diem x Travelers | D71: =D46*D13 -> 497 | G71: =G46*G13 -> 497
B72: Billable to Prime (ODC) | C72: Marked-up ODC + Per Diem all travelers | D72: =D70+D71 -> 3312.05 | G72: =G70+G71 -> 3023.43
B73: Grand Total to Prime | C73: Billable to Prime (ODC) + EWW Total | D73: =D72+D55 -> 3762.05 | G73: =G72+G55 -> 3473.43
B74: Markup added (information) | C74: Grand Total to Prime - Grand Total | D74: =D73-D56 -> 318.13 | G74: =G73-G56 -> 285.51
B75: Grand Total on lists right after submit | C75: Trip Lead Total + EWW if EWW was already saved | D75: =D50+D40*D55 -> 2993.92 | G75: =G50+G40*G55 -> 3187.92
B76: Average ROOM cost per night | C76: Room Cost / Nights (0 if no nights) | D76: =IF(D44>0,D16/D44,0) -> 132 | G76: =IF(G44>0,G16/G44,0) -> 132
B77: Over the GSA limit? | C77: YES when average room cost per night > GSA Lodging Rate | D77: =IF(AND(D44>0,D76>D14),"YES","No") -> No | G77: =IF(AND(G44>0,G76>G14),"YES","No") -> No
B78: Total lodging per night (NOT used for the limit) | C78: Total Lodging / Nights — shown to prove fees/taxes are excluded | D78: =IF(D44>0,D17/D44,0) -> 159.15333 | G78: =IF(G44>0,G17/G44,0) -> 159.15333
B79: Typing check: Room + Fees + Taxes - Total | C79: Should be $0.00; if not, one of the four inputs was mistyped | D79: =ROUND(D16+D18+D19-D17,2) -> 0 | G79: =ROUND(G16+G18+G19-G17,2) -> 0
B80: Per Traveler Subtotal as the Prime sees it | C80: Per Diem (unmarked) + the 4 rounded per-traveler lines | D80: =D46+D58+D59+D61+D60 -> 1601.91 | G80: =G46+G58+G59+G61+G60 -> 1457.6
A82: 3. SCREEN CHECKPOINTS — compare each screen to Expected, type what you see in the yellow cell
A83: Ref | B83: Field / what to read | C83: Screen label / how it is calculated | D83: S6 v1 Expected | E83: Actual (you) | F83: Result | G83: S6 v2 Expected | H83: Actual (you) | I83: Result
A84: A1 | B84: Nights | C84: Employee form (live) | D84: =D44 -> 3 | F84: =IF(E84="","",IF(ABS(E84-D84)<=Setup!$C$6,"PASS","FAIL")) | G84: =G44 -> 3 | I84: =IF(H84="","",IF(ABS(H84-G84)<=Setup!$C$6,"PASS","FAIL"))
A85: A2 | B85: Full Days (1x) | C85: Employee form (live) | D85: =D45 -> 2 | F85: =IF(E85="","",IF(ABS(E85-D85)<=Setup!$C$6,"PASS","FAIL")) | G85: =G45 -> 2 | I85: =IF(H85="","",IF(ABS(H85-G85)<=Setup!$C$6,"PASS","FAIL"))
A86: A3 | B86: Per Diem Meals Total | C86: Employee form (live) | D86: =D46 -> 248.5 | F86: =IF(E86="","",IF(ABS(E86-D86)<=Setup!$C$6,"PASS","FAIL")) | G86: =G46 -> 248.5 | I86: =IF(H86="","",IF(ABS(H86-G86)<=Setup!$C$6,"PASS","FAIL"))
A87: A4 | B87: Per Traveler Subtotal | C87: Employee form (live) | D87: =D48 -> 1448.96 | F87: =IF(E87="","",IF(ABS(E87-D87)<=Setup!$C$6,"PASS","FAIL")) | G87: =G48 -> 1320.96 | I87: =IF(H87="","",IF(ABS(H87-G87)<=Setup!$C$6,"PASS","FAIL"))
A88: A5 | B88: Trip Lead Total | C88: Employee form (live) | D88: =D50 -> 2993.92 | F88: =IF(E88="","",IF(ABS(E88-D88)<=Setup!$C$6,"PASS","FAIL")) | G88: =G50 -> 2737.92 | I88: =IF(H88="","",IF(ABS(H88-G88)<=Setup!$C$6,"PASS","FAIL"))
A89: B1 | B89: Grand Total right after submit | C89: My Estimates list AND Supervisor queue (before Supervisor enters EWW) | D89: =D75 -> 2993.92 | F89: =IF(E89="","",IF(ABS(E89-D89)<=Setup!$C$6,"PASS","FAIL")) | G89: =G75 -> 3187.92 | I89: =IF(H89="","",IF(ABS(H89-G89)<=Setup!$C$6,"PASS","FAIL"))
A90: C1 | B90: Per Traveler Subtotal | C90: Supervisor review | D90: =D48 -> 1448.96 | F90: =IF(E90="","",IF(ABS(E90-D90)<=Setup!$C$6,"PASS","FAIL")) | G90: =G48 -> 1320.96 | I90: =IF(H90="","",IF(ABS(H90-G90)<=Setup!$C$6,"PASS","FAIL"))
A91: C2 | B91: Trip Lead Total | C91: Supervisor review | D91: =D50 -> 2993.92 | F91: =IF(E91="","",IF(ABS(E91-D91)<=Setup!$C$6,"PASS","FAIL")) | G91: =G50 -> 2737.92 | I91: =IF(H91="","",IF(ABS(H91-G91)<=Setup!$C$6,"PASS","FAIL"))
A92: C3 | B92: EWW Total | C92: Supervisor review (after entering EWW) | D92: =D55 -> 450 | F92: =IF(E92="","",IF(ABS(E92-D92)<=Setup!$C$6,"PASS","FAIL")) | G92: =G55 -> 450 | I92: =IF(H92="","",IF(ABS(H92-G92)<=Setup!$C$6,"PASS","FAIL"))
A93: C4 | B93: Grand Total (ODC + EWW) | C93: Supervisor review | D93: =D56 -> 3443.92 | F93: =IF(E93="","",IF(ABS(E93-D93)<=Setup!$C$6,"PASS","FAIL")) | G93: =G56 -> 3187.92 | I93: =IF(H93="","",IF(ABS(H93-G93)<=Setup!$C$6,"PASS","FAIL"))
A94: C5 | B94: Billable to Prime (ODC) | C94: Supervisor review | D94: =D72 -> 3312.05 | F94: =IF(E94="","",IF(ABS(E94-D94)<=Setup!$C$6,"PASS","FAIL")) | G94: =G72 -> 3023.43 | I94: =IF(H94="","",IF(ABS(H94-G94)<=Setup!$C$6,"PASS","FAIL"))
A95: C6 | B95: Grand Total to Prime | C95: Supervisor review | D95: =D73 -> 3762.05 | F95: =IF(E95="","",IF(ABS(E95-D95)<=Setup!$C$6,"PASS","FAIL")) | G95: =G73 -> 3473.43 | I95: =IF(H95="","",IF(ABS(H95-G95)<=Setup!$C$6,"PASS","FAIL"))
A96: C7.1 | B96: EWW Cost — Traveler 1 | C96: Supervisor review (live as you type) | D96: =D51 -> 450 | F96: =IF(E96="","",IF(ABS(E96-D96)<=Setup!$C$6,"PASS","FAIL")) | G96: =G51 -> 450 | I96: =IF(H96="","",IF(ABS(H96-G96)<=Setup!$C$6,"PASS","FAIL"))
A97: CL.lodging | B97: Billable column: Total Lodging Cost | C97: Supervisor review > Billable to Prime Breakdown | D97: =D58 -> 538.29 | F97: =IF(E97="","",IF(ABS(E97-D97)<=Setup!$C$6,"PASS","FAIL")) | G97: =G58 -> 538.29 | I97: =IF(H97="","",IF(ABS(H97-G97)<=Setup!$C$6,"PASS","FAIL"))
A98: CL.airfare | B98: Billable column: Airfare (avg) | C98: Supervisor review > Billable to Prime Breakdown | D98: =D59 -> 721.54 | F98: =IF(E98="","",IF(ABS(E98-D98)<=Setup!$C$6,"PASS","FAIL")) | G98: =G59 -> 577.23 | I98: =IF(H98="","",IF(ABS(H98-G98)<=Setup!$C$6,"PASS","FAIL"))
A99: CL.baggage | B99: Billable column: Baggage | C99: Supervisor review > Billable to Prime Breakdown | D99: =D60 -> 39.46 | F99: =IF(E99="","",IF(ABS(E99-D99)<=Setup!$C$6,"PASS","FAIL")) | G99: =G60 -> 39.46 | I99: =IF(H99="","",IF(ABS(H99-G99)<=Setup!$C$6,"PASS","FAIL"))
A100: CL.airportParking | B100: Billable column: Airport Parking | C100: Supervisor review > Billable to Prime Breakdown | D100: =D61 -> 54.12 | F100: =IF(E100="","",IF(ABS(E100-D100)<=Setup!$C$6,"PASS","FAIL")) | G100: =G61 -> 54.12 | I100: =IF(H100="","",IF(ABS(H100-G100)<=Setup!$C$6,"PASS","FAIL"))
A101: CL.rideshare | B101: Billable column: Rideshare Estimate | C101: Supervisor review > Billable to Prime Breakdown | D101: =D66 -> 108.23 | F101: =IF(E101="","",IF(ABS(E101-D101)<=Setup!$C$6,"PASS","FAIL")) | G101: =G66 -> 108.23 | I101: =IF(H101="","",IF(ABS(H101-G101)<=Setup!$C$6,"PASS","FAIL"))
A102: D1 | B102: Grand Total after approval | C102: My Estimates list (now includes EWW) | D102: =D56 -> 3443.92 | F102: =IF(E102="","",IF(ABS(E102-D102)<=Setup!$C$6,"PASS","FAIL")) | G102: =G56 -> 3187.92 | I102: =IF(H102="","",IF(ABS(H102-G102)<=Setup!$C$6,"PASS","FAIL"))
A103: D2 | B103: Grand Total (Prime queue) | C103: Prime > Travel Authorizations queue | D103: =D73 -> 3762.05 | F103: =IF(E103="","",IF(ABS(E103-D103)<=Setup!$C$6,"PASS","FAIL")) | G103: =G73 -> 3473.43 | I103: =IF(H103="","",IF(ABS(H103-G103)<=Setup!$C$6,"PASS","FAIL"))
A104: E1 | B104: Per Traveler Subtotal | C104: Prime review form | D104: =D80 -> 1601.91 | F104: =IF(E104="","",IF(ABS(E104-D104)<=Setup!$C$6,"PASS","FAIL")) | G104: =G80 -> 1457.6 | I104: =IF(H104="","",IF(ABS(H104-G104)<=Setup!$C$6,"PASS","FAIL"))
A105: E2 | B105: Trip Lead Total | C105: Prime review form | D105: =D72 -> 3312.05 | F105: =IF(E105="","",IF(ABS(E105-D105)<=Setup!$C$6,"PASS","FAIL")) | G105: =G72 -> 3023.43 | I105: =IF(H105="","",IF(ABS(H105-G105)<=Setup!$C$6,"PASS","FAIL"))
A106: E3 | B106: EWW Total | C106: Prime review form | D106: =D55 -> 450 | F106: =IF(E106="","",IF(ABS(E106-D106)<=Setup!$C$6,"PASS","FAIL")) | G106: =G55 -> 450 | I106: =IF(H106="","",IF(ABS(H106-G106)<=Setup!$C$6,"PASS","FAIL"))
A107: E4 | B107: Grand Total (must equal D2 exactly) | C107: Prime review form | D107: =D73 -> 3762.05 | F107: =IF(E107="","",IF(ABS(E107-D107)<=Setup!$C$6,"PASS","FAIL")) | G107: =G73 -> 3473.43 | I107: =IF(H107="","",IF(ABS(H107-G107)<=Setup!$C$6,"PASS","FAIL"))
A108: F1 | B108: Average room cost per night | C108: Employee form warning text / math only | D108: =D76 -> 132 | F108: =IF(E108="","",IF(ABS(E108-D108)<=Setup!$C$6,"PASS","FAIL")) | G108: =G76 -> 132 | I108: =IF(H108="","",IF(ABS(H108-G108)<=Setup!$C$6,"PASS","FAIL"))
...

Sheet S7
A1: S7 — Deny, return and cancel paths
A2: Every way an estimate can end other than paid: Supervisor deny, Prime return then deny, and employee cancel from draft and submitted. Denied requests are stored read-only. A returned request keeps its tracking number through re-approval. Math is light here; the focus is status, notes, tracking number and emails.
A3: Travel type: Fly, 1 traveler (light data) | Expected emails: 17 | Fee multiplier from Setup tab
A5: 1. INPUTS — type these exactly (blue)
A6: Ref | B6: Field / what to read | C6: Screen label / how it is calculated | D6: S7a | G6: S7b | J6: S7c-1 | M6: S7c-2
B7: Event Name | C7: Add your initials at the end | D7: S7a Supervisor Deny - xx | G7: S7b Prime Return Then Deny - xx | J7: S7c Cancel From Draft - xx | M7: S7c Cancel After Submit - xx
B8: City | D8: Detroit | G8: Denver | J8: Boise | M8: Omaha
B9: State | C9: Pick from the list | D9: MI | G9: CO | J9: ID | M9: NE
B10: Contract | C10: Pick any contract; note which one | D10: (any) | G10: (any) | J10: (any) | M10: (any)
B11: Leave Date | D11: 46358 | G11: 46358 | J11: 46358 | M11: 46358
B12: Return Date | D12: 46360 | G12: 46360 | J12: 46360 | M12: 46360
B13: Travelers | C13: Traveler 2-4: pick any roster employee | D13: 1 | G13: 1 | J13: 1 | M13: 1
B14: GSA Lodging Rate (per night) | C14: Overwrite AFTER the lookup finishes | D14: 120 | G14: 120 | J14: 120 | M14: 120
B15: Meals (M&IE) Rate (per day) | C15: Overwrite AFTER the lookup finishes | D15: 59 | G15: 59 | J15: 59 | M15: 59
B16: Room Cost (subject to per diem limit) | C16: Per traveler, whole stay | D16: 224 | G16: 224 | J16: 224 | M16: 224
B17: Total Lodging Cost (incl. taxes & fees) | C17: Per traveler, whole stay | D17: 248.64 | G17: 248.64 | J17: 248.64 | M17: 248.64
B18: Lodging Fees | C18: Recorded only | D18: 0 | G18: 0 | J18: 0 | M18: 0
B19: Lodging Taxes | C19: Recorded only | D19: 24.64 | G19: 24.64 | J19: 24.64 | M19: 24.64
B20: Airfare (avg) | C20: Per traveler | D20: 300 | G20: 326 | J20: 276 | M20: 290
B21: Baggage | C21: Per traveler | D21: 0 | G21: 0 | J21: 0 | M21: 0
B22: Airport Parking | C22: Per traveler | D22: 0 | G22: 0 | J22: 0 | M22: 0
B23: Shipping (to) | C23: Trip-level | D23: 0 | G23: 0 | J23: 0 | M23: 0
B24: Shipping (back) | C24: Trip-level | D24: 0 | G24: 0 | J24: 0 | M24: 0
... B30: Mileage (Personal Vehicle) | C30: Trip-level | D30: 0 | G30: 0 | J30: 0 | M30: 0
B31: Entered by the SUPERVISOR at review (not on the submit form)
B32: Traveler 1 EWW Rate (per hour) | C32: Supervisor review > EWW Rate | D32: 0 | G32: 0 | J32: 0 | M32: 0
B33: Traveler 1 EWW Hours | D33: 0 | G33: 0 | J33: 0 | M33: 0
B34: Traveler 2 EWW Rate (per hour) | D34: 0 | G34: 0 | J34: 0 | M34: 0
B35: Traveler 2 EWW Hours | D35: 0 | G35: 0 | J35: 0 | M35: 0
B36: Traveler 3 EWW Rate (per hour) | D36: 0 | G36: 0 | J36: 0 | M36: 0
B37: Traveler 3 EWW Hours | D37: 0 | G37: 0 | J37: 0 | M37: 0
B38: Traveler 4 EWW Rate (per hour) | D38: 0 | G38: 0 | J38: 0 | M38: 0
B39: Traveler 4 EWW Hours | D39: 0 | G39: 0 | J39: 0 | M39: 0
B40: EWW already saved when submitted? (1 = yes) | C40: Only a resubmission after a Supervisor return carries EWW | D40: 0 | G40: 0 | J40: 0 | M40: 0
A42: 2. EXPECTED MATH — live formulas (read these to follow the arithmetic)
A43: Ref | B43: Field / what to read | C43: Screen label / how it is calculated | D43: S7a | G43: S7b | J43: S7c-1 | M43: S7c-2
B44: Nights | C44: Return Date - Leave Date (never below 0) | D44: =MAX(0,D12-D11) -> 2 | G44: =MAX(0,G12-G11) -> 2 | J44: =MAX(0,J12-J11) -> 2 | M44: =MAX(0,M12-M11) -> 2
B45: Full Days (1x) | C45: Nights - 1, minimum 0 | D45: =MAX(D44-1,0) -> 1 | G45: =MAX(G44-1,0) -> 1 | J45: =MAX(J44-1,0) -> 1 | M45: =MAX(M44-1,0) -> 1
B46: Per Diem Meals Total (per traveler) | C46: 1.5 x M&IE + Full Days x M&IE | D46: =1.5*D15+D45*D15 -> 147.5 | G46: =1.5*G15+G45*G15 -> 147.5 | J46: =1.5*J15+J45*J15 -> 147.5 | M46: =1.5*M15+M45*M15 -> 147.5
B47: Per-traveler costs (excl. meals) | C47: Total Lodging + Airfare + Airport Parking + Baggage | D47: =D17+D20+D22+D21 -> 548.64 | G47: =G17+G20+G22+G21 -> 574.64 | J47: =J17+J20+J22+J21 -> 524.64 | M47: =M17+M20+M22+M21 -> 538.64
B48: Per Traveler Subtotal | C48: Per Diem + per-traveler costs | D48: =D46+D47 -> 696.14 | G48: =G46+G47 -> 722.14 | J48: =J46+J47 -> 672.14 | M48: =M46+M47 -> 686.14
B49: Trip-level costs | C49: Rental + Gas + Parking + Tolls + Rideshare + Mileage + Shipping to + Shipping back | D49: =D25+D26+D27+D28+D29+D30+D23+D24 -> 0 | G49: =G25+G26+G27+G28+G29+G30+G23+G24 -> 0 | J49: =J25+J26+J27+J28+J29+J30+J23+J24 -> 0 | M49: =M25+M26+M27+M28+M29+M30+M23+M24 -> 0
B50: Trip Lead Total | C50: Per Traveler Subtotal x Travelers + trip-level costs | D50: =D48*D13+D49 -> 696.14 | G50: =G48*G13+G49 -> 722.14 | J50: =J48*J13+J49 -> 672.14 | M50: =M48*M13+M49 -> 686.14
B51: EWW Cost — Traveler 1 | C51: Rate x Hours (only if that traveler exists) | D51: =IF(1<=D13,D32*D33,0) -> 0 | G51: =IF(1<=G13,G32*G33,0) -> 0 | J51: =IF(1<=J13,J32*J33,0) -> 0 | M51: =IF(1<=M13,M32*M33,0) -> 0
B52: EWW Cost — Traveler 2 | C52: Rate x Hours (only if that traveler exists) | D52: =IF(2<=D13,D34*D35,0) -> 0 | G52: =IF(2<=G13,G34*G35,0) -> 0 | J52: =IF(2<=J13,J34*J35,0) -> 0 | M52: =IF(2<=M13,M34*M35,0) -> 0
B53: EWW Cost — Traveler 3 | C53: Rate x Hours (only if that traveler exists) | D53: =IF(3<=D13,D36*D37,0) -> 0 | G53: =IF(3<=G13,G36*G37,0) -> 0 | J53: =IF(3<=J13,J36*J37,0) -> 0 | M53: =IF(3<=M13,M36*M37,0) -> 0
B54: EWW Cost — Traveler 4 | C54: Rate x Hours (only if that traveler exists) | D54: =IF(4<=D13,D38*D39,0) -> 0 | G54: =IF(4<=G13,G38*G39,0) -> 0 | J54: =IF(4<=J13,J38*J39,0) -> 0 | M54: =IF(4<=M13,M38*M39,0) -> 0
B55: EWW Total | C55: Sum of the four EWW Costs | D55: =SUM(D51:D54) -> 0 | G55: =SUM(G51:G54) -> 0 | J55: =SUM(J51:J54) -> 0 | M55: =SUM(M51:M54) -> 0
B56: Grand Total (ODC + EWW) | C56: Trip Lead Total + EWW Total | D56: =D50+D55 -> 696.14 | G56: =G50+G55 -> 722.14 | J56: =J50+J55 -> 672.14 | M56: =M50+M55 -> 686.14
B57: Billable column, line by line (amount x multiplier, rounded to cents) | C57: Supervisor review "Billable to Prime" column, approved-email column, Prime form field
B58: Total Lodging Cost | C58: ROUND(Total Lodging Cost x multiplier, 2) | D58: =ROUND(D17*Setup!$C$5,2) -> 280.32 | G58: =ROUND(G17*Setup!$C$5,2) -> 280.32 | J58: =ROUND(J17*Setup!$C$5,2) -> 280.32 | M58: =ROUND(M17*Setup!$C$5,2) -> 280.32
B59: Airfare (avg) | C59: ROUND(Airfare (avg) x multiplier, 2) | D59: =ROUND(D20*Setup!$C$5,2) -> 338.22 | G59: =ROUND(G20*Setup!$C$5,2) -> 367.53 | J59: =ROUND(J20*Setup!$C$5,2) -> 311.16 | M59: =ROUND(M20*Setup!$C$5,2) -> 326.95
B60: Baggage | C60: ROUND(Baggage x multiplier, 2) | D60: =ROUND(D21*Setup!$C$5,2) -> 0 | G60: =ROUND(G21*Setup!$C$5,2) -> 0 | J60: =ROUND(J21*Setup!$C$5,2) -> 0 | M60: =ROUND(M21*Setup!$C$5,2) -> 0
B61: Airport Parking | C61: ROUND(Airport Parking x multiplier, 2) | D61: =ROUND(D22*Setup!$C$5,2) -> 0 | G61: =ROUND(G22*Setup!$C$5,2) -> 0 | J61: =ROUND(J22*Setup!$C$5,2) -> 0 | M61: =ROUND(M22*Setup!$C$5,2) -> 0
B62: Rental Car | C62: ROUND(Rental Car x multiplier, 2) | D62: =ROUND(D25*Setup!$C$5,2) -> 0 | G62: =ROUND(G25*Setup!$C$5,2) -> 0 | J62: =ROUND(J25*Setup!$C$5,2) -> 0 | M62: =ROUND(M25*Setup!$C$5,2) -> 0
B63: Gas | C63: ROUND(Gas x multiplier, 2) | D63: =ROUND(D26*Setup!$C$5,2) -> 0 | G63: =ROUND(G26*Setup!$C$5,2) -> 0 | J63: =ROUND(J26*Setup!$C$5,2) -> 0 | M63: =ROUND(M26*Setup!$C$5,2) -> 0
B64: Parking | C64: ROUND(Parking x multiplier, 2) | D64: =ROUND(D27*Setup!$C$5,2) -> 0 | G64: =ROUND(G27*Setup!$C$5,2) -> 0 | J64: =ROUND(J27*Setup!$C$5,2) -> 0 | M64: =ROUND(M27*Setup!$C$5,2) -> 0
B65: Tolls | C65: ROUND(Tolls x multiplier, 2) | D65: =ROUND(D28*Setup!$C$5,2) -> 0 | G65: =ROUND(G28*Setup!$C$5,2) -> 0 | J65: =ROUND(J28*Setup!$C$5,2) -> 0 | M65: =ROUND(M28*Setup!$C$5,2) -> 0
B66: Rideshare Estimate | C66: ROUND(Rideshare Estimate x multiplier, 2) | D66: =ROUND(D29*Setup!$C$5,2) -> 0 | G66: =ROUND(G29*Setup!$C$5,2) -> 0 | J66: =ROUND(J29*Setup!$C$5,2) -> 0 | M66: =ROUND(M29*Setup!$C$5,2) -> 0
B67: Mileage (Personal Vehicle) | C67: ROUND(Mileage (Personal Vehicle) x multiplier, 2) | D67: =ROUND(D30*Setup!$C$5,2) -> 0 | G67: =ROUND(G30*Setup!$C$5,2) -> 0 | J67: =ROUND(J30*Setup!$C$5,2) -> 0 | M67: =ROUND(M30*Setup!$C$5,2) -> 0
B68: Shipping (to) | C68: ROUND(Shipping (to) x multiplier, 2) | D68: =ROUND(D23*Setup!$C$5,2) -> 0 | G68: =ROUND(G23*Setup!$C$5,2) -> 0 | J68: =ROUND(J23*Setup!$C$5,2) -> 0 | M68: =ROUND(M23*Setup!$C$5,2) -> 0
B69: Shipping (back) | C69: ROUND(Shipping (back) x multiplier, 2) | D69: =ROUND(D24*Setup!$C$5,2) -> 0 | G69: =ROUND(G24*Setup!$C$5,2) -> 0 | J69: =ROUND(J24*Setup!$C$5,2) -> 0 | M69: =ROUND(M24*Setup!$C$5,2) -> 0
B70: Marked-up ODC | C70: (4 rounded per-traveler lines) x Travelers + (8 rounded trip-level lines) | D70: =(D58+D59+D61+D60)*D13+D62+D63+D64+D65+D66+D67+D68+D69 -> 618.54 | G70: =(G58+G59+G61+G60)*G13+G62+G63+G64+G65+G66+G67+G68+G69 -> 647.85 | J70: =(J58+J59+J61+J60)*J13+J62+J63+J64+J65+J66+J67+J68+J69 -> 591.48 | M70: =(M58+M59+M61+M60)*M13+M62+M63+M64+M65+M66+M67+M68+M69 -> 607.27
B71: Per Diem Meals, all travelers (not marked up) | C71: Per Diem x Travelers | D71: =D46*D13 -> 147.5 | G71: =G46*G13 -> 147.5 | J71: =J46*J13 -> 147.5 | M71: =M46*M13 -> 147.5
B72: Billable to Prime (ODC) | C72: Marked-up ODC + Per Diem all travelers | D72: =D70+D71 -> 766.04 | G72: =G70+G71 -> 795.35 | J72: =J70+J71 -> 738.98 | M72: =M70+M71 -> 754.77
B73: Grand Total to Prime | C73: Billable to Prime (ODC) + EWW Total | D73: =D72+D55 -> 766.04 | G73: =G72+G55 -> 795.35 | J73: =J72+J55 -> 738.98 | M73: =M72+M55 -> 754.77
B74: Markup added (information) | C74: Grand Total to Prime - Grand Total | D74: =D73-D56 -> 69.9 | G74: =G73-G56 -> 73.21 | J74: =J73-J56 -> 66.84 | M74: =M73-M56 -> 68.63
B75: Grand Total on lists right after submit | C75: Trip Lead Total + EWW if EWW was already saved | D75: =D50+D40*D55 -> 696.14 | G75: =G50+G40*G55 -> 722.14 | J75: =J50+J40*J55 -> 672.14 | M75: =M50+M40*M55 -> 686.14
B76: Average ROOM cost per night | C76: Room Cost / Nights (0 if no nights) | D76: =IF(D44>0,D16/D44,0) -> 112 | G76: =IF(G44>0,G16/G44,0) -> 112 | J76: =IF(J44>0,J16/J44,0) -> 112 | M76: =IF(M44>0,M16/M44,0) -> 112
B77: Over the GSA limit? | C77: YES when average room cost per night > GSA Lodging Rate | D77: =IF(AND(D44>0,D76>D14),"YES","No") -> No | G77: =IF(AND(G44>0,G76>G14),"YES","No") -> No | J77: =IF(AND(J44>0,J76>J14),"YES","No") -> No | M77: =IF(AND(M44>0,M76>M14),"YES","No") -> No
B78: Total lodging per night (NOT used for the limit) | C78: Total Lodging / Nights — shown to prove fees/taxes are excluded | D78: =IF(D44>0,D17/D44,0) -> 124.32 | G78: =IF(G44>0,G17/G44,0) -> 124.32 | J78: =IF(J44>0,J17/J44,0) -> 124.32 | M78: =IF(M44>0,M17/M44,0) -> 124.32
B79: Typing check: Room + Fees + Taxes - Total | C79: Should be $0.00; if not, one of the four inputs was mistyped | D79: =ROUND(D16+D18+D19-D17,2) -> 0 | G79: =ROUND(G16+G18+G19-G17,2) -> 0 | J79: =ROUND(J16+J18+J19-J17,2) -> 0 | M79: =ROUND(M16+M18+M19-M17,2) -> 0
B80: Per Traveler Subtotal as the Prime sees it | C80: Per Diem (unmarked) + the 4 rounded per-traveler lines | D80: =D46+D58+D59+D61+D60 -> 766.04 | G80: =G46+G58+G59+G61+G60 -> 795.35 | J80: =J46+J58+J59+J61+J60 -> 738.98 | M80: =M46+M58+M59+M61+M60 -> 754.77
A82: 3. SCREEN CHECKPOINTS — compare each screen to Expected, type what you see in the yellow cell
A83: Ref | B83: Field / what to read | C83: Screen label / how it is calculated | D83: S7a Expected | E83: Actual (you) | F83: Result | G83: S7b Expected | H83: Actual (you) | I83: Result | J83: S7c-1 Expected | K83: Actual (you) | L83: Result | M83: S7c-2 Expected | N83: Actual (you) | O83: Result
A84: A1 | B84: Nights | C84: Employee form (live) | D84: =D44 -> 2 | F84: =IF(E84="","",IF(ABS(E84-D84)<=Setup!$C$6,"PASS","FAIL")) | G84: =G44 -> 2 | I84: =IF(H84="","",IF(ABS(H84-G84)<=Setup!$C$6,"PASS","FAIL")) | J84: =J44 -> 2 | L84: =IF(K84="","",IF(ABS(K84-J84)<=Setup!$C$6,"PASS","FAIL")) | M84: =M44 -> 2 | O84: =IF(N84="","",IF(ABS(N84-M84)<=Setup!$C$6,"PASS","FAIL"))
A85: A3 | B85: Per Diem Meals Total | C85: Employee form (live) | D85: =D46 -> 147.5 | F85: =IF(E85="","",IF(ABS(E85-D85)<=Setup!$C$6,"PASS","FAIL")) | G85: =G46 -> 147.5 | I85: =IF(H85="","",IF(ABS(H85-G85)<=Setup!$C$6,"PASS","FAIL")) | J85: =J46 -> 147.5 | L85: =IF(K85="","",IF(ABS(K85-J85)<=Setup!$C$6,"PASS","FAIL")) | M85: =M46 -> 147.5 | O85: =IF(N85="","",IF(ABS(N85-M85)<=Setup!$C$6,"PASS","FAIL"))
A86: A5 | B86: Trip Lead Total | C86: Employee form (live) | D86: =D50 -> 696.14 | F86: =IF(E86="","",IF(ABS(E86-D86)<=Setup!$C$6,"PASS","FAIL")) | G86: =G50 -> 722.14 | I86: =IF(H86="","",IF(ABS(H86-G86)<=Setup!$C$6,"PASS","FAIL")) | J86: =J50 -> 672.14 | L86: =IF(K86="","",IF(ABS(K86-J86)<=Setup!$C$6,"PASS","FAIL")) | M86: =M50 -> 686.14 | O86: =IF(N86="","",IF(ABS(N86-M86)<=Setup!$C$6,"PASS","FAIL"))
A87: B1 | B87: Grand Total right after submit | C87: My Estimates list AND Supervisor queue (before Supervisor enters EWW) | D87: =D75 -> 696.14 | F87: =IF(E87="","",IF(ABS(E87-D87)<=Setup!$C$6,"PASS","FAIL")) | G87: =G75 -> 722.14 | I87: =IF(H87="","",IF(ABS(H87-G87)<=Setup!$C$6,"PASS","FAIL")) | J87: =J75 -> 672.14 | L87: =IF(K87="","",IF(ABS(K87-J87)<=Setup!$C$6,"PASS","FAIL")) | M87: =M75 -> 686.14 | O87: =IF(N87="","",IF(ABS(N87-M87)<=Setup!$C$6,"PASS","FAIL"))
A88: C3 | B88: EWW Total | C88: Supervisor review (after entering EWW) | D88: =D55 -> 0 | F88: =IF(E88="","",IF(ABS(E88-D88)<=Setup!$C$6,"PASS","FAIL")) | G88: =G55 -> 0 | I88: =IF(H88="","",IF(ABS(H88-G88)<=Setup!$C$6,"PASS","FAIL")) | J88: =J55 -> 0 | L88: =IF(K88="","",IF(ABS(K88-J88)<=Setup!$C$6,"PASS","FAIL")) | M88: =M55 -> 0 | O88: =IF(N88="","",IF(ABS(N88-M88)<=Setup!$C$6,"PASS","FAIL"))
A89: C5 | B89: Billable to Prime (ODC) | C89: Supervisor review | D89: =D72 -> 766.04 | F89: =IF(E89="","",IF(ABS(E89-D89)<=Setup!$C$6,"PASS","FAIL")) | G89: =G72 -> 795.35 | I89: =IF(H89="","",IF(ABS(H89-G89)<=Setup!$C$6,"PASS","FAIL")) | J89: =J72 -> 738.98 | L89: =IF(K89="","",IF(ABS(K89-J89)<=Setup!$C$6,"PASS","FAIL")) | M89: =M72 -> 754.77 | O89: =IF(N89="","",IF(ABS(N89-M89)<=Setup!$C$6,"PASS","FAIL"))
A90: C6 | B90: Grand Total to Prime | C90: Supervisor review | D90: =D73 -> 766.04 | F90: =IF(E90="","",IF(ABS(E90-D90)<=Setup!$C$6,"PASS","FAIL")) | G90: =G73 -> 795.35 | I90: =IF(H90="","",IF(ABS(H90-G90)<=Setup!$C$6,"PASS","FAIL")) | J90: =J73 -> 738.98 | L90: =IF(K90="","",IF(ABS(K90-J90)<=Setup!$C$6,"PASS","FAIL")) | M90: =M73 -> 754.77 | O90: =IF(N90="","",IF(ABS(N90-M90)<=Setup!$C$6,"PASS","FAIL"))
A91: D2 | B91: Grand Total (Prime queue) | C91: Prime > Travel Authorizations queue | D91: =D73 -> 766.04 | F91: =IF(E91="","",IF(ABS(E91-D91)<=Setup!$C$6,"PASS","FAIL")) | G91: =G73 -> 795.35 | I91: =IF(H91="","",IF(ABS(H91-G91)<=Setup!$C$6,"PASS","FAIL")) | J91: =J73 -> 738.98 | L91: =IF(K91="","",IF(ABS(K91-J91)<=Setup!$C$6,"PASS","FAIL")) | M91: =M73 -> 754.77 | O91: =IF(N91="","",IF(ABS(N91-M91)<=Setup!$C$6,"PASS","FAIL"))
A92: E4 | B92: Grand Total (must equal D2 exactly) | C92: Prime review form | D92: =D73 -> 766.04 | F92: =IF(E92="","",IF(ABS(E92-D92)<=Setup!$C$6,"PASS","FAIL")) | G92: =G73 -> 795.35 | I92: =IF(H92="","",IF(ABS(H92-G92)<=Setup!$C$6,"PASS","FAIL")) | J92: =J73 -> 738.98 | L92: =IF(K92="","",IF(ABS(K92-J92)<=Setup!$C$6,"PASS","FAIL")) | M92: =M73 -> 754.77 | O92: =IF(N92="","",IF(ABS(N92-M92)<=Setup!$C$6,"PASS","FAIL"))
A93: F1 | B93: Average room cost per night | C93: Employee form warning text / math only | D93: =D76 -> 112 | F93: =IF(E93="","",IF(ABS(E93-D93)<=Setup!$C$6,"PASS","FAIL")) | G93: =G76 -> 112 | I93: =IF(H93="","",IF(ABS(H93-G93)<=Setup!$C$6,"PASS","FAIL")) | J93: =J76 -> 112 | L93: =IF(K93="","",IF(ABS(K93-J93)<=Setup!$C$6,"PASS","FAIL")) | M93: =M76 -> 112 | O93: =IF(N93="","",IF(ABS(N93-M93)<=Setup!$C$6,"PASS","FAIL"))
A94: F2 | B94: Red over-limit warning shown? (type YES or No) | C94: Employee form | D94: =D77 -> No | F94: =IF(E94="","",IF(UPPER(E94)=UPPER(D94),"PASS","FAIL")) | G94: =G77 -> No | I94: =IF(H94="","",IF(UPPER(H94)=UPPER(G94),"PASS","FAIL")) | J94: =J77 -> No | L94: =IF(K94="","",IF(UPPER(K94)=UPPER(J94),"PASS","FAIL")) | M94: =M77 -> No | O94: =IF(N94="","",IF(UPPER(N94)=UPPER(M94),"PASS","FAIL"))
B95: Tip: for rows that do not apply to your step yet, leave the yellow cell blank.

Sheet S8
A1: S8 — Expense return and resubmit, expense deny
A2: The expense-side rejection paths. Two minimal authorized estimates: S8a's expense report is returned, corrected and resubmitted, then approved; S8b's is denied and stored read-only.
A3: Travel type: Fly, 1 traveler (light data) | Expected emails: 19 | Fee multiplier from Setup tab
A5: 1. INPUTS — type these exactly (blue)
A6: Ref | B6: Field / what to read | C6: Screen label / how it is calculated | D6: S8a | G6: S8b
B7: Event Name | C7: Add your initials at the end | D7: S8a Expense Return - xx | G7: S8b Expense Deny - xx
B8: City | D8: Phoenix | G8: Tucson
B9: State | C9: Pick from the list | D9: AZ | G9: AZ
B10: Contract | C10: Pick any contract; note which one | D10: (any) | G10: (any)
B11: Leave Date | D11: 46365 | G11: 46365
B12: Return Date | D12: 46367 | G12: 46367
B13: Travelers | C13: Traveler 2-4: pick any roster employee | D13: 1 | G13: 1
B14: GSA Lodging Rate (per night) | C14: Overwrite AFTER the lookup finishes | D14: 125 | G14: 125
B15: Meals (M&IE) Rate (per day) | C15: Overwrite AFTER the lookup finishes | D15: 61 | G15: 61
B16: Room Cost (subject to per diem limit) | C16: Per traveler, whole stay | D16: 236 | G16: 236
B17: Total Lodging Cost (incl. taxes & fees) | C17: Per traveler, whole stay | D17: 261.96 | G17: 261.96
B18: Lodging Fees | C18: Recorded only | D18: 0 | G18: 0
B19: Lodging Taxes | C19: Recorded only | D19: 25.96 | G19: 25.96
B20: Airfare (avg) | C20: Per traveler | D20: 280 | G20: 305
B21: Baggage | C21: Per traveler | D21: 0 | G21: 0
B22: Airport Parking | C22: Per traveler | D22: 0 | G22: 0
B23: Shipping (to) | C23: Trip-level | D23: 0 | G23: 0
B24: Shipping (back) | C24: Trip-level | D24: 0 | G24: 0
... B30: Mileage (Personal Vehicle) | C30: Trip-level | D30: 0 | G30: 0
B31: Entered by the SUPERVISOR at review (not on the submit form)
B32: Traveler 1 EWW Rate (per hour) | C32: Supervisor review > EWW Rate | D32: 0 | G32: 0
B33: Traveler 1 EWW Hours | D33: 0 | G33: 0
B34: Traveler 2 EWW Rate (per hour) | D34: 0 | G34: 0
B35: Traveler 2 EWW Hours | D35: 0 | G35: 0
B36: Traveler 3 EWW Rate (per hour) | D36: 0 | G36: 0
B37: Traveler 3 EWW Hours | D37: 0 | G37: 0
B38: Traveler 4 EWW Rate (per hour) | D38: 0 | G38: 0
B39: Traveler 4 EWW Hours | D39: 0 | G39: 0
B40: EWW already saved when submitted? (1 = yes) | C40: Only a resubmission after a Supervisor return carries EWW | D40: 0 | G40: 0
A42: 2. EXPECTED MATH — live formulas (read these to follow the arithmetic)
A43: Ref | B43: Field / what to read | C43: Screen label / how it is calculated | D43: S8a | G43: S8b
B44: Nights | C44: Return Date - Leave Date (never below 0) | D44: =MAX(0,D12-D11) -> 2 | G44: =MAX(0,G12-G11) -> 2
B45: Full Days (1x) | C45: Nights - 1, minimum 0 | D45: =MAX(D44-1,0) -> 1 | G45: =MAX(G44-1,0) -> 1
B46: Per Diem Meals Total (per traveler) | C46: 1.5 x M&IE + Full Days x M&IE | D46: =1.5*D15+D45*D15 -> 152.5 | G46: =1.5*G15+G45*G15 -> 152.5
B47: Per-traveler costs (excl. meals) | C47: Total Lodging + Airfare + Airport Parking + Baggage | D47: =D17+D20+D22+D21 -> 541.96 | G47: =G17+G20+G22+G21 -> 566.96
B48: Per Traveler Subtotal | C48: Per Diem + per-traveler costs | D48: =D46+D47 -> 694.46 | G48: =G46+G47 -> 719.46
B49: Trip-level costs | C49: Rental + Gas + Parking + Tolls + Rideshare + Mileage + Shipping to + Shipping back | D49: =D25+D26+D27+D28+D29+D30+D23+D24 -> 0 | G49: =G25+G26+G27+G28+G29+G30+G23+G24 -> 0
B50: Trip Lead Total | C50: Per Traveler Subtotal x Travelers + trip-level costs | D50: =D48*D13+D49 -> 694.46 | G50: =G48*G13+G49 -> 719.46
B51: EWW Cost — Traveler 1 | C51: Rate x Hours (only if that traveler exists) | D51: =IF(1<=D13,D32*D33,0) -> 0 | G51: =IF(1<=G13,G32*G33,0) -> 0
B52: EWW Cost — Traveler 2 | C52: Rate x Hours (only if that traveler exists) | D52: =IF(2<=D13,D34*D35,0) -> 0 | G52: =IF(2<=G13,G34*G35,0) -> 0
B53: EWW Cost — Traveler 3 | C53: Rate x Hours (only if that traveler exists) | D53: =IF(3<=D13,D36*D37,0) -> 0 | G53: =IF(3<=G13,G36*G37,0) -> 0
B54: EWW Cost — Traveler 4 | C54: Rate x Hours (only if that traveler exists) | D54: =IF(4<=D13,D38*D39,0) -> 0 | G54: =IF(4<=G13,G38*G39,0) -> 0
B55: EWW Total | C55: Sum of the four EWW Costs | D55: =SUM(D51:D54) -> 0 | G55: =SUM(G51:G54) -> 0
B56: Grand Total (ODC + EWW) | C56: Trip Lead Total + EWW Total | D56: =D50+D55 -> 694.46 | G56: =G50+G55 -> 719.46
B57: Billable column, line by line (amount x multiplier, rounded to cents) | C57: Supervisor review "Billable to Prime" column, approved-email column, Prime form field
B58: Total Lodging Cost | C58: ROUND(Total Lodging Cost x multiplier, 2) | D58: =ROUND(D17*Setup!$C$5,2) -> 295.33 | G58: =ROUND(G17*Setup!$C$5,2) -> 295.33
B59: Airfare (avg) | C59: ROUND(Airfare (avg) x multiplier, 2) | D59: =ROUND(D20*Setup!$C$5,2) -> 315.67 | G59: =ROUND(G20*Setup!$C$5,2) -> 343.86
B60: Baggage | C60: ROUND(Baggage x multiplier, 2) | D60: =ROUND(D21*Setup!$C$5,2) -> 0 | G60: =ROUND(G21*Setup!$C$5,2) -> 0
B61: Airport Parking | C61: ROUND(Airport Parking x multiplier, 2) | D61: =ROUND(D22*Setup!$C$5,2) -> 0 | G61: =ROUND(G22*Setup!$C$5,2) -> 0
B62: Rental Car | C62: ROUND(Rental Car x multiplier, 2) | D62: =ROUND(D25*Setup!$C$5,2) -> 0 | G62: =ROUND(G25*Setup!$C$5,2) -> 0
B63: Gas | C63: ROUND(Gas x multiplier, 2) | D63: =ROUND(D26*Setup!$C$5,2) -> 0 | G63: =ROUND(G26*Setup!$C$5,2) -> 0
B64: Parking | C64: ROUND(Parking x multiplier, 2) | D64: =ROUND(D27*Setup!$C$5,2) -> 0 | G64: =ROUND(G27*Setup!$C$5,2) -> 0
B65: Tolls | C65: ROUND(Tolls x multiplier, 2) | D65: =ROUND(D28*Setup!$C$5,2) -> 0 | G65: =ROUND(G28*Setup!$C$5,2) -> 0
B66: Rideshare Estimate | C66: ROUND(Rideshare Estimate x multiplier, 2) | D66: =ROUND(D29*Setup!$C$5,2) -> 0 | G66: =ROUND(G29*Setup!$C$5,2) -> 0
B67: Mileage (Personal Vehicle) | C67: ROUND(Mileage (Personal Vehicle) x multiplier, 2) | D67: =ROUND(D30*Setup!$C$5,2) -> 0 | G67: =ROUND(G30*Setup!$C$5,2) -> 0
B68: Shipping (to) | C68: ROUND(Shipping (to) x multiplier, 2) | D68: =ROUND(D23*Setup!$C$5,2) -> 0 | G68: =ROUND(G23*Setup!$C$5,2) -> 0
B69: Shipping (back) | C69: ROUND(Shipping (back) x multiplier, 2) | D69: =ROUND(D24*Setup!$C$5,2) -> 0 | G69: =ROUND(G24*Setup!$C$5,2) -> 0
B70: Marked-up ODC | C70: (4 rounded per-traveler lines) x Travelers + (8 rounded trip-level lines) | D70: =(D58+D59+D61+D60)*D13+D62+D63+D64+D65+D66+D67+D68+D69 -> 611 | G70: =(G58+G59+G61+G60)*G13+G62+G63+G64+G65+G66+G67+G68+G69 -> 639.19
B71: Per Diem Meals, all travelers (not marked up) | C71: Per Diem x Travelers | D71: =D46*D13 -> 152.5 | G71: =G46*G13 -> 152.5
B72: Billable to Prime (ODC) | C72: Marked-up ODC + Per Diem all travelers | D72: =D70+D71 -> 763.5 | G72: =G70+G71 -> 791.69
B73: Grand Total to Prime | C73: Billable to Prime (ODC) + EWW Total | D73: =D72+D55 -> 763.5 | G73: =G72+G55 -> 791.69
B74: Markup added (information) | C74: Grand Total to Prime - Grand Total | D74: =D73-D56 -> 69.04 | G74: =G73-G56 -> 72.23
B75: Grand Total on lists right after submit | C75: Trip Lead Total + EWW if EWW was already saved | D75: =D50+D40*D55 -> 694.46 | G75: =G50+G40*G55 -> 719.46
B76: Average ROOM cost per night | C76: Room Cost / Nights (0 if no nights) | D76: =IF(D44>0,D16/D44,0) -> 118 | G76: =IF(G44>0,G16/G44,0) -> 118
B77: Over the GSA limit? | C77: YES when average room cost per night > GSA Lodging Rate | D77: =IF(AND(D44>0,D76>D14),"YES","No") -> No | G77: =IF(AND(G44>0,G76>G14),"YES","No") -> No
B78: Total lodging per night (NOT used for the limit) | C78: Total Lodging / Nights — shown to prove fees/taxes are excluded | D78: =IF(D44>0,D17/D44,0) -> 130.98 | G78: =IF(G44>0,G17/G44,0) -> 130.98
B79: Typing check: Room + Fees + Taxes - Total | C79: Should be $0.00; if not, one of the four inputs was mistyped | D79: =ROUND(D16+D18+D19-D17,2) -> 0 | G79: =ROUND(G16+G18+G19-G17,2) -> 0
B80: Per Traveler Subtotal as the Prime sees it | C80: Per Diem (unmarked) + the 4 rounded per-traveler lines | D80: =D46+D58+D59+D61+D60 -> 763.5 | G80: =G46+G58+G59+G61+G60 -> 791.69
A82: 3. SCREEN CHECKPOINTS — compare each screen to Expected, type what you see in the yellow cell
A83: Ref | B83: Field / what to read | C83: Screen label / how it is calculated | D83: S8a Expected | E83: Actual (you) | F83: Result | G83: S8b Expected | H83: Actual (you) | I83: Result
A84: A1 | B84: Nights | C84: Employee form (live) | D84: =D44 -> 2 | F84: =IF(E84="","",IF(ABS(E84-D84)<=Setup!$C$6,"PASS","FAIL")) | G84: =G44 -> 2 | I84: =IF(H84="","",IF(ABS(H84-G84)<=Setup!$C$6,"PASS","FAIL"))
A85: A3 | B85: Per Diem Meals Total | C85: Employee form (live) | D85: =D46 -> 152.5 | F85: =IF(E85="","",IF(ABS(E85-D85)<=Setup!$C$6,"PASS","FAIL")) | G85: =G46 -> 152.5 | I85: =IF(H85="","",IF(ABS(H85-G85)<=Setup!$C$6,"PASS","FAIL"))
A86: A5 | B86: Trip Lead Total | C86: Employee form (live) | D86: =D50 -> 694.46 | F86: =IF(E86="","",IF(ABS(E86-D86)<=Setup!$C$6,"PASS","FAIL")) | G86: =G50 -> 719.46 | I86: =IF(H86="","",IF(ABS(H86-G86)<=Setup!$C$6,"PASS","FAIL"))
A87: B1 | B87: Grand Total right after submit | C87: My Estimates list AND Supervisor queue (before Supervisor enters EWW) | D87: =D75 -> 694.46 | F87: =IF(E87="","",IF(ABS(E87-D87)<=Setup!$C$6,"PASS","FAIL")) | G87: =G75 -> 719.46 | I87: =IF(H87="","",IF(ABS(H87-G87)<=Setup!$C$6,"PASS","FAIL"))
A88: C3 | B88: EWW Total | C88: Supervisor review (after entering EWW) | D88: =D55 -> 0 | F88: =IF(E88="","",IF(ABS(E88-D88)<=Setup!$C$6,"PASS","FAIL")) | G88: =G55 -> 0 | I88: =IF(H88="","",IF(ABS(H88-G88)<=Setup!$C$6,"PASS","FAIL"))
A89: C5 | B89: Billable to Prime (ODC) | C89: Supervisor review | D89: =D72 -> 763.5 | F89: =IF(E89="","",IF(ABS(E89-D89)<=Setup!$C$6,"PASS","FAIL")) | G89: =G72 -> 791.69 | I89: =IF(H89="","",IF(ABS(H89-G89)<=Setup!$C$6,"PASS","FAIL"))
A90: C6 | B90: Grand Total to Prime | C90: Supervisor review | D90: =D73 -> 763.5 | F90: =IF(E90="","",IF(ABS(E90-D90)<=Setup!$C$6,"PASS","FAIL")) | G90: =G73 -> 791.69 | I90: =IF(H90="","",IF(ABS(H90-G90)<=Setup!$C$6,"PASS","FAIL"))
A91: D2 | B91: Grand Total (Prime queue) | C91: Prime > Travel Authorizations queue | D91: =D73 -> 763.5 | F91: =IF(E91="","",IF(ABS(E91-D91)<=Setup!$C$6,"PASS","FAIL")) | G91: =G73 -> 791.69 | I91: =IF(H91="","",IF(ABS(H91-G91)<=Setup!$C$6,"PASS","FAIL"))
A92: E4 | B92: Grand Total (must equal D2 exactly) | C92: Prime review form | D92: =D73 -> 763.5 | F92: =IF(E92="","",IF(ABS(E92-D92)<=Setup!$C$6,"PASS","FAIL")) | G92: =G73 -> 791.69 | I92: =IF(H92="","",IF(ABS(H92-G92)<=Setup!$C$6,"PASS","FAIL"))
A93: F1 | B93: Average room cost per night | C93: Employee form warning text / math only | D93: =D76 -> 118 | F93: =IF(E93="","",IF(ABS(E93-D93)<=Setup!$C$6,"PASS","FAIL")) | G93: =G76 -> 118 | I93: =IF(H93="","",IF(ABS(H93-G93)<=Setup!$C$6,"PASS","FAIL"))
A94: F2 | B94: Red over-limit warning shown? (type YES or No) | C94: Employee form | D94: =D77 -> No | F94: =IF(E94="","",IF(UPPER(E94)=UPPER(D94),"PASS","FAIL")) | G94: =G77 -> No | I94: =IF(H94="","",IF(UPPER(H94)=UPPER(G94),"PASS","FAIL"))
B95: Tip: for rows that do not apply to your step yet, leave the yellow cell blank.
A97: 4.1 EXPENSE REPORT — S8a expense (linked to estimate S8a)
A98: Ref | B98: Field | C98: Notes / formula | D98: Expected / typed | E98: Actual (you) | F98: Result
B99: Actual Leave Date | C99: Prefilled from the estimate; type this if different | D99: 46365
B100: Actual Return Date | D100: 46367
B101: Number of Travelers | C101: Prefilled from the estimate | D101: 1
B102: Meals (M&IE) Rate (per day) | C102: Prefilled from the estimate | D102: 61
A104: Ref | B104: Category | C104: Where it appears on the form | D104: Estimated | E104: Actual (type) | F104: Over by $ | G104: Over by % | H104: Over 10%? | I104: Added (no estimate)? | J104: Note box required? | K104: Note box shown? Y/N (you) | L104: Result | M104: Receipt attached? Y/N (you)
A105: X-C1 | B105: Lodging (actual total) | C105: =IF(D105>0,"Main Actual Costs grid",IF(E105>0,"Additional Expenses section","Not shown on the form")) -> Main Actual Costs grid | D105: =D17 -> 261.96 | E105: 261.96 | F105: =E105-D105 -> 0 | G105: =IF(D105>0,(E105-D105)/D105,0) -> 0 | H105: =IF(AND(D105>0,E105>D105*1.1),"Y","N") -> N | I105: =IF(AND(D105=0,E105>0),"Y","N") -> N | J105: =IF(OR(H105="Y",I105="Y"),"Y","N") -> N | L105: =IF(LEFT(C105,3)="Not","n/a",IF(K105="","",IF(UPPER(K105)=J105,"PASS","FAIL")))
A106: X-C2 | B106: Airfare (avg) | C106: =IF(D106>0,"Main Actual Costs grid",IF(E106>0,"Additional Expenses section","Not shown on the form")) -> Main Actual Costs grid | D106: =D20 -> 280 | E106: 280 | F106: =E106-D106 -> 0 | G106: =IF(D106>0,(E106-D106)/D106,0) -> 0 | H106: =IF(AND(D106>0,E106>D106*1.1),"Y","N") -> N | I106: =IF(AND(D106=0,E106>0),"Y","N") -> N | J106: =IF(OR(H106="Y",I106="Y"),"Y","N") -> N | L106: =IF(LEFT(C106,3)="Not","n/a",IF(K106="","",IF(UPPER(K106)=J106,"PASS","FAIL")))
A107: X-C3 | B107: Baggage | C107: =IF(D107>0,"Main Actual Costs grid",IF(E107>0,"Additional Expenses section","Not shown on the form")) -> Not shown on the form | D107: =D21 -> 0 | E107: 0 | F107: =E107-D107 -> 0 | G107: =IF(D107>0,(E107-D107)/D107,0) -> 0 | H107: =IF(AND(D107>0,E107>D107*1.1),"Y","N") -> N | I107: =IF(AND(D107=0,E107>0),"Y","N") -> N | J107: =IF(OR(H107="Y",I107="Y"),"Y","N") -> N | L107: =IF(LEFT(C107,3)="Not","n/a",IF(K107="","",IF(UPPER(K107)=J107,"PASS","FAIL"))) -> n/a
A108: X-C4 | B108: Airport Parking | C108: =IF(D108>0,"Main Actual Costs grid",IF(E108>0,"Additional Expenses section","Not shown on the form")) -> Not shown on the form | D108: =D22 -> 0 | E108: 0 | F108: =E108-D108 -> 0 | G108: =IF(D108>0,(E108-D108)/D108,0) -> 0 | H108: =IF(AND(D108>0,E108>D108*1.1),"Y","N") -> N | I108: =IF(AND(D108=0,E108>0),"Y","N") -> N | J108: =IF(OR(H108="Y",I108="Y"),"Y","N") -> N | L108: =IF(LEFT(C108,3)="Not","n/a",IF(K108="","",IF(UPPER(K108)=J108,"PASS","FAIL"))) -> n/a
A109: X-C5 | B109: Rental Car | C109: =IF(D109>0,"Main Actual Costs grid",IF(E109>0,"Additional Expenses section","Not shown on the form")) -> Not shown on the form | D109: =D25 -> 0 | E109: 0 | F109: =E109-D109 -> 0 | G109: =IF(D109>0,(E109-D109)/D109,0) -> 0 | H109: =IF(AND(D109>0,E109>D109*1.1),"Y","N") -> N | I109: =IF(AND(D109=0,E109>0),"Y","N") -> N | J109: =IF(OR(H109="Y",I109="Y"),"Y","N") -> N | L109: =IF(LEFT(C109,3)="Not","n/a",IF(K109="","",IF(UPPER(K109)=J109,"PASS","FAIL"))) -> n/a
A110: X-C6 | B110: Gas | C110: =IF(D110>0,"Main Actual Costs grid",IF(E110>0,"Additional Expenses section","Not shown on the form")) -> Not shown on the form | D110: =D26 -> 0 | E110: 0 | F110: =E110-D110 -> 0 | G110: =IF(D110>0,(E110-D110)/D110,0) -> 0 | H110: =IF(AND(D110>0,E110>D110*1.1),"Y","N") -> N | I110: =IF(AND(D110=0,E110>0),"Y","N") -> N | J110: =IF(OR(H110="Y",I110="Y"),"Y","N") -> N | L110: =IF(LEFT(C110,3)="Not","n/a",IF(K110="","",IF(UPPER(K110)=J110,"PASS","FAIL"))) -> n/a
...

Sheet Emails
A1: Email log — expected vs received
A2: All emails land in the one signed-in inbox. Log each as it arrives. Short notices carry no trip name, so match them by the time of your action.
A4: Scenario | B4: Expected | C4: Received | D4: Unexpected extras (you) | E4: Status
A5: S1 | B5: =COUNTIF($B$17:$B$102,A5) -> 8 | C5: =COUNTIFS($B$17:$B$102,A5,$L$17:$L$102,"Y") -> 0 | E5: =IF(C5=0,"",IF(AND(C5=B5,D5=0),"OK","CHECK"))
A6: S2 | B6: =COUNTIF($B$17:$B$102,A6) -> 8 | C6: =COUNTIFS($B$17:$B$102,A6,$L$17:$L$102,"Y") -> 0 | E6: =IF(C6=0,"",IF(AND(C6=B6,D6=0),"OK","CHECK"))
A7: S3 | B7: =COUNTIF($B$17:$B$102,A7) -> 9 | C7: =COUNTIFS($B$17:$B$102,A7,$L$17:$L$102,"Y") -> 0 | E7: =IF(C7=0,"",IF(AND(C7=B7,D7=0),"OK","CHECK"))
A8: S4 | B8: =COUNTIF($B$17:$B$102,A8) -> 8 | C8: =COUNTIFS($B$17:$B$102,A8,$L$17:$L$102,"Y") -> 0 | E8: =IF(C8=0,"",IF(AND(C8=B8,D8=0),"OK","CHECK"))
A9: S5 | B9: =COUNTIF($B$17:$B$102,A9) -> 9 | C9: =COUNTIFS($B$17:$B$102,A9,$L$17:$L$102,"Y") -> 0 | E9: =IF(C9=0,"",IF(AND(C9=B9,D9=0),"OK","CHECK"))
A10: S6 | B10: =COUNTIF($B$17:$B$102,A10) -> 8 | C10: =COUNTIFS($B$17:$B$102,A10,$L$17:$L$102,"Y") -> 0 | E10: =IF(C10=0,"",IF(AND(C10=B10,D10=0),"OK","CHECK"))
A11: S7 | B11: =COUNTIF($B$17:$B$102,A11) -> 17 | C11: =COUNTIFS($B$17:$B$102,A11,$L$17:$L$102,"Y") -> 0 | E11: =IF(C11=0,"",IF(AND(C11=B11,D11=0),"OK","CHECK"))
A12: S8 | B12: =COUNTIF($B$17:$B$102,A12) -> 19 | C12: =COUNTIFS($B$17:$B$102,A12,$L$17:$L$102,"Y") -> 0 | E12: =IF(C12=0,"",IF(AND(C12=B12,D12=0),"OK","CHECK"))
A13: Total | B13: =SUM(B5:B12) -> 86 | C13: =SUM(C5:C12) -> 0 | D13: =SUM(D5:D12) -> 0
A14: Note: expense-report actions are expected to send NO email (Watch W3). Count any that arrive as "Unexpected extras".
A16: Email ID | B16: Scenario | C16: Step | D16: Estimate | E16: Expected subject | F16: Template | G16: Check 1 | H16: Expected 1 | I16: Check 2 | J16: Expected 2 | K16: Also verify | L16: Received? Y/N | M16: Time received | N16: Subject OK? Y/N | O16: Figures OK? Y/N | P16: Tracking # seen | Q16: Notes
A17: S1-E1 | B17: S1 | C17: 6 | D17: S1 | E17: Travel estimate submitted — Columbia, SC | F17: Submitter copy (Requested column only) | G17: Trip Lead Total | H17: ='S1'!D50 -> 894.7 | I17: Grand Total | J17: ='S1'!D75 -> 894.7 | K17: Heading "Columbia, SC — S1 Regional Workshop", 3 nights. Requested column only; no Billable column. No Tracking # yet (none is issued until the first approval). EWW table lists 1 traveler(s) at $0.00.
A18: S1-E2 | B18: S1 | C18: 6 | D18: S1 | E18: Action needed: review as Supervisor — Columbia, SC | F18: Supervisor nudge (same body as submitter copy) | G18: Trip Lead Total | H18: ='S1'!D50 -> 894.7 | I18: Grand Total | J18: ='S1'!D75 -> 894.7 | K18: Heading "Columbia, SC — S1 Regional Workshop", 3 nights. Requested column only; no Billable column. No Tracking # yet (none is issued until the first approval). EWW table lists 1 traveler(s) at $0.00.
A19: S1-E3 | B19: S1 | C19: 9 | D19: S1 | E19: Travel estimate approved — Columbia, SC — <Tracking #> | F19: Supervisor record (Requested + Billable to Prime columns) | G19: Billable to Prime (ODC) | H19: ='S1'!D72 -> 978.37 | I19: Grand Total to Prime | J19: ='S1'!D73 -> 978.37 | K19: Tracking # (SLIN code, hyphen, 5 digits) in the subject and the body. SLIN code in the heading. Requested AND Billable to Prime columns. Totals rows: Trip Lead, EWW, Grand, Billable to Prime (ODC), Grand Total to Prime. Check EWW table.
A20: S1-E4 | B20: S1 | C20: 9 | D20: S1 | E20: Action needed: Prime authorization — Columbia, SC — <Tracking #> | F20: Prime copy (single marked-up Total column) | G20: Trip Lead Total (marked up) | H20: ='S1'!D72 -> 978.37 | I20: Grand Total (marked up) | J20: ='S1'!D73 -> 978.37 | K20: Tracking # (SLIN code, hyphen, 5 digits) in the subject and the body. Single "Total" column (marked up). Must NOT contain: Requested, Billable to Prime, the Fees/Taxes note, internal Trip Lead.
A21: S1-E5 | B21: S1 | C21: 11 | D21: S1 | E21: Travel authorized — Columbia, SC — <Tracking #> | F21: Notice: Prime authorized the trip | K21: Short notice that names the trip and carries the Tracking # in the subject and the body.
A22: S1-E6 | B22: S1 | C22: 17 | D22: S1 | E22: Expense report submitted — Columbia, SC — <Tracking #> | F22: Expense submitter copy (actual vs estimated) | G22: Actual Grand Total | H22: ='S1'!D144 -> 896 | I22: Variance vs. Estimate | J22: ='S1'!D146 -> 1.3 | K22: Tracking # (SLIN code, hyphen, 5 digits) in the subject and the body. It must be the SAME number as the estimate. Heading shows actual dates and travelers. Table of Estimated / Actual / Difference per category; Explanations section lists the variance and added-category notes; Totals include the read-only EWW Total.
A23: S1-E7 | B23: S1 | C23: 17 | D23: S1 | E23: Action needed: review expense report as Supervisor — Columbia, SC — <Tracking #> | F23: Expense Supervisor nudge (same body) | G23: Actual Grand Total | H23: ='S1'!D144 -> 896 | I23: Variance vs. Estimate | J23: ='S1'!D146 -> 1.3 | K23: Tracking # (SLIN code, hyphen, 5 digits) in the subject and the body. It must be the SAME number as the estimate. Heading shows actual dates and travelers. Table of Estimated / Actual / Difference per category; Explanations section lists the variance and added-category notes; Totals include the read-only EWW Total.
A24: S1-E8 | B24: S1 | C24: 19 | D24: S1 | E24: Expense report approved — Columbia, SC — <Tracking #> | F24: Expense approved (reimbursement finalized) | G24: Actual Grand Total | H24: ='S1'!D144 -> 896 | I24: Variance vs. Estimate | J24: ='S1'!D146 -> 1.3 | K24: Tracking # (SLIN code, hyphen, 5 digits) in the subject and the body. It must be the SAME number as the estimate. Heading shows actual dates and travelers. Table of Estimated / Actual / Difference per category; Explanations section lists the variance and added-category notes; Totals include the read-only EWW Total.
A25: S2-E1 | B25: S2 | C25: 4 | D25: S2 | E25: Travel estimate submitted — Austin, TX | F25: Submitter copy (Requested column only) | G25: Trip Lead Total | H25: ='S2'!D50 -> 2890.1 | I25: Grand Total | J25: ='S2'!D75 -> 2890.1 | K25: Heading "Austin, TX — S2 Customer Site Visit", 3 nights. Requested column only; no Billable column. No Tracking # yet (none is issued until the first approval). EWW table lists 2 traveler(s) at $0.00.
A26: S2-E2 | B26: S2 | C26: 4 | D26: S2 | E26: Action needed: review as Supervisor — Austin, TX | F26: Supervisor nudge (same body as submitter copy) | G26: Trip Lead Total | H26: ='S2'!D50 -> 2890.1 | I26: Grand Total | J26: ='S2'!D75 -> 2890.1 | K26: Heading "Austin, TX — S2 Customer Site Visit", 3 nights. Requested column only; no Billable column. No Tracking # yet (none is issued until the first approval). EWW table lists 2 traveler(s) at $0.00.
A27: S2-E3 | B27: S2 | C27: 7 | D27: S2 | E27: Travel estimate approved — Austin, TX — <Tracking #> | F27: Supervisor record (Requested + Billable to Prime columns) | G27: Billable to Prime (ODC) | H27: ='S2'!D72 -> 3192.31 | I27: Grand Total to Prime | J27: ='S2'!D73 -> 3942.31 | K27: Tracking # (SLIN code, hyphen, 5 digits) in the subject and the body. SLIN code in the heading. Requested AND Billable to Prime columns. Totals rows: Trip Lead, EWW, Grand, Billable to Prime (ODC), Grand Total to Prime. Check EWW table.
A28: S2-E4 | B28: S2 | C28: 7 | D28: S2 | E28: Action needed: Prime authorization — Austin, TX — <Tracking #> | F28: Prime copy (single marked-up Total column) | G28: Trip Lead Total (marked up) | H28: ='S2'!D72 -> 3192.31 | I28: Grand Total (marked up) | J28: ='S2'!D73 -> 3942.31 | K28: Tracking # (SLIN code, hyphen, 5 digits) in the subject and the body. Single "Total" column (marked up). Must NOT contain: Requested, Billable to Prime, the Fees/Taxes note, internal Trip Lead.
A29: S2-E5 | B29: S2 | C29: 8 | D29: S2 | E29: Travel authorized — Austin, TX — <Tracking #> | F29: Notice: Prime authorized the trip | K29: Short notice that names the trip and carries the Tracking # in the subject and the body.
A30: S2-E6 | B30: S2 | C30: 15 | D30: S2 | E30: Expense report submitted — Austin, TX — <Tracking #> | F30: Expense submitter copy (actual vs estimated) | G30: Actual Grand Total | H30: ='S2'!D154 -> 3978.5 | I30: Variance vs. Estimate | J30: ='S2'!D156 -> 338.4 | K30: Tracking # (SLIN code, hyphen, 5 digits) in the subject and the body. It must be the SAME number as the estimate. Heading shows actual dates and travelers. Table of Estimated / Actual / Difference per category; Explanations section lists the variance and added-category notes; Totals include the read-only EWW Total.
A31: S2-E7 | B31: S2 | C31: 15 | D31: S2 | E31: Action needed: review expense report as Supervisor — Austin, TX — <Tracking #> | F31: Expense Supervisor nudge (same body) | G31: Actual Grand Total | H31: ='S2'!D154 -> 3978.5 | I31: Variance vs. Estimate | J31: ='S2'!D156 -> 338.4 | K31: Tracking # (SLIN code, hyphen, 5 digits) in the subject and the body. It must be the SAME number as the estimate. Heading shows actual dates and travelers. Table of Estimated / Actual / Difference per category; Explanations section lists the variance and added-category notes; Totals include the read-only EWW Total.
A32: S2-E8 | B32: S2 | C32: 17 | D32: S2 | E32: Expense report approved — Austin, TX — <Tracking #> | F32: Expense approved (reimbursement finalized) | G32: Actual Grand Total | H32: ='S2'!D154 -> 3978.5 | I32: Variance vs. Estimate | J32: ='S2'!D156 -> 338.4 | K32: Tracking # (SLIN code, hyphen, 5 digits) in the subject and the body. It must be the SAME number as the estimate. Heading shows actual dates and travelers. Table of Estimated / Actual / Difference per category; Explanations section lists the variance and added-category notes; Totals include the read-only EWW Total.
A33: S3-E1 | B33: S3 | C33: 3 | D33: S3a | E33: Travel estimate submitted — Nashville, TN | F33: Submitter copy (Requested column only) | G33: Trip Lead Total | H33: ='S3'!D53 -> 1202 | I33: Grand Total | J33: ='S3'!D78 -> 1202 | K33: Heading "Nashville, TN — S3a Fees-Taxes Excluded", 3 nights. Requested column only; no Billable column. No Tracking # yet (none is issued until the first approval). EWW table lists 1 traveler(s) at $0.00.
A34: S3-E2 | B34: S3 | C34: 3 | D34: S3a | E34: Action needed: review as Supervisor — Nashville, TN | F34: Supervisor nudge (same body as submitter copy) | G34: Trip Lead Total | H34: ='S3'!D53 -> 1202 | I34: Grand Total | J34: ='S3'!D78 -> 1202 | K34: Heading "Nashville, TN — S3a Fees-Taxes Excluded", 3 nights. Requested column only; no Billable column. No Tracking # yet (none is issued until the first approval). EWW table lists 1 traveler(s) at $0.00.
A35: S3-E3 | B35: S3 | C35: 4 | D35: S3a | E35: Travel estimate approved — Nashville, TN — <Tracking #> | F35: Supervisor record (Requested + Billable to Prime columns) | G35: Billable to Prime (ODC) | H35: ='S3'!D75 -> 1324.38 | I35: Grand Total to Prime | J35: ='S3'!D76 -> 1324.38 | K35: Tracking # (SLIN code, hyphen, 5 digits) in the subject and the body. SLIN code in the heading. Requested AND Billable to Prime columns. Totals rows: Trip Lead, EWW, Grand, Billable to Prime (ODC), Grand Total to Prime. Check EWW table.
A36: S3-E4 | B36: S3 | C36: 4 | D36: S3a | E36: Action needed: Prime authorization — Nashville, TN — <Tracking #> | F36: Prime copy (single marked-up Total column) | G36: Trip Lead Total (marked up) | H36: ='S3'!D75 -> 1324.38 | I36: Grand Total (marked up) | J36: ='S3'!D76 -> 1324.38 | K36: Tracking # (SLIN code, hyphen, 5 digits) in the subject and the body. Single "Total" column (marked up). Must NOT contain: Requested, Billable to Prime, the Fees/Taxes note, internal Trip Lead.
A37: S3-E5 | B37: S3 | C37: 10 | D37: S3b | E37: Travel estimate submitted — Memphis, TN | F37: Submitter copy (Requested column only) | G37: Trip Lead Total | H37: ='S3'!G53 -> 1275.05 | I37: Grand Total | J37: ='S3'!G78 -> 1275.05 | K37: Heading "Memphis, TN — S3b Over Limit With Quotes", 3 nights. Requested column only; no Billable column. No Tracking # yet (none is issued until the first approval). EWW table lists 1 traveler(s) at $0.00.
A38: S3-E6 | B38: S3 | C38: 10 | D38: S3b | E38: Action needed: review as Supervisor — Memphis, TN | F38: Supervisor nudge (same body as submitter copy) | G38: Trip Lead Total | H38: ='S3'!G53 -> 1275.05 | I38: Grand Total | J38: ='S3'!G78 -> 1275.05 | K38: Heading "Memphis, TN — S3b Over Limit With Quotes", 3 nights. Requested column only; no Billable column. No Tracking # yet (none is issued until the first approval). EWW table lists 1 traveler(s) at $0.00.
A39: S3-E7 | B39: S3 | C39: 12 | D39: S3b | E39: Travel estimate approved — Memphis, TN — <Tracking #> | F39: Supervisor record (Requested + Billable to Prime columns) | G39: Billable to Prime (ODC) | H39: ='S3'!G75 -> 1406.73 | I39: Grand Total to Prime | J39: ='S3'!G76 -> 1666.73 | K39: Tracking # (SLIN code, hyphen, 5 digits) in the subject and the body. SLIN code in the heading. Requested AND Billable to Prime columns. Totals rows: Trip Lead, EWW, Grand, Billable to Prime (ODC), Grand Total to Prime. Check EWW table.
A40: S3-E8 | B40: S3 | C40: 12 | D40: S3b | E40: Action needed: Prime authorization — Memphis, TN — <Tracking #> | F40: Prime copy (single marked-up Total column) | G40: Trip Lead Total (marked up) | H40: ='S3'!G75 -> 1406.73 | I40: Grand Total (marked up) | J40: ='S3'!G76 -> 1666.73 | K40: Tracking # (SLIN code, hyphen, 5 digits) in the subject and the body. Single "Total" column (marked up). Must NOT contain: Requested, Billable to Prime, the Fees/Taxes note, internal Trip Lead.
A41: S3-E9 | B41: S3 | C41: 13 | D41: S3b | E41: Travel authorized — Memphis, TN — <Tracking #> | F41: Notice: Prime authorized the trip | K41: Short notice that names the trip and carries the Tracking # in the subject and the body.
A42: S4-E1 | B42: S4 | C42: 4 | D42: S4 | E42: Travel estimate submitted — San Diego, CA | F42: Submitter copy (Requested column only) | G42: Trip Lead Total | H42: ='S4'!D50 -> 15062.48 | I42: Grand Total | J42: ='S4'!D75 -> 15062.48 | K42: Heading "San Diego, CA — S4 Training Cohort Onsite", 10 nights. Requested column only; no Billable column. No Tracking # yet (none is issued until the first approval). EWW table lists 4 traveler(s) at $0.00.
A43: S4-E2 | B43: S4 | C43: 4 | D43: S4 | E43: Action needed: review as Supervisor — San Diego, CA | F43: Supervisor nudge (same body as submitter copy) | G43: Trip Lead Total | H43: ='S4'!D50 -> 15062.48 | I43: Grand Total | J43: ='S4'!D75 -> 15062.48 | K43: Heading "San Diego, CA — S4 Training Cohort Onsite", 10 nights. Requested column only; no Billable column. No Tracking # yet (none is issued until the first approval). EWW table lists 4 traveler(s) at $0.00.
A44: S4-E3 | B44: S4 | C44: 6 | D44: S4 | E44: Travel estimate approved — San Diego, CA — <Tracking #> | F44: Supervisor record (Requested + Billable to Prime columns) | G44: Billable to Prime (ODC) | H44: ='S4'!D72 -> 16558.75 | I44: Grand Total to Prime | J44: ='S4'!D73 -> 17778.75 | K44: Tracking # (SLIN code, hyphen, 5 digits) in the subject and the body. SLIN code in the heading. Requested AND Billable to Prime columns. Totals rows: Trip Lead, EWW, Grand, Billable to Prime (ODC), Grand Total to Prime. Check EWW table.
A45: S4-E4 | B45: S4 | C45: 6 | D45: S4 | E45: Action needed: Prime authorization — San Diego, CA — <Tracking #> | F45: Prime copy (single marked-up Total column) | G45: Trip Lead Total (marked up) | H45: ='S4'!D72 -> 16558.75 | I45: Grand Total (marked up) | J45: ='S4'!D73 -> 17778.75 | K45: Tracking # (SLIN code, hyphen, 5 digits) in the subject and the body. Single "Total" column (marked up). Must NOT contain: Requested, Billable to Prime, the Fees/Taxes note, internal Trip Lead.
A46: S4-E5 | B46: S4 | C46: 7 | D46: S4 | E46: Travel authorized — San Diego, CA — <Tracking #> | F46: Notice: Prime authorized the trip | K46: Short notice that names the trip and carries the Tracking # in the subject and the body.
A47: S4-E6 | B47: S4 | C47: 10 | D47: S4 | E47: Expense report submitted — San Diego, CA — <Tracking #> | F47: Expense submitter copy (actual vs estimated) | G47: Actual Grand Total | H47: ='S4'!D152 -> 16507.5 | I47: Variance vs. Estimate | J47: ='S4'!D154 -> 225.02 | K47: Tracking # (SLIN code, hyphen, 5 digits) in the subject and the body. It must be the SAME number as the estimate. Heading shows actual dates and travelers. Table of Estimated / Actual / Difference per category; Explanations section lists the variance and added-category notes; Totals include the read-only EWW Total.
A48: S4-E7 | B48: S4 | C48: 10 | D48: S4 | E48: Action needed: review expense report as Supervisor — San Diego, CA — <Tracking #> | F48: Expense Supervisor nudge (same body) | G48: Actual Grand Total | H48: ='S4'!D152 -> 16507.5 | I48: Variance vs. Estimate | J48: ='S4'!D154 -> 225.02 | K48: Tracking # (SLIN code, hyphen, 5 digits) in the subject and the body. It must be the SAME number as the estimate. Heading shows actual dates and travelers. Table of Estimated / Actual / Difference per category; Explanations section lists the variance and added-category notes; Totals include the read-only EWW Total.
A49: S4-E8 | B49: S4 | C49: 11 | D49: S4 | E49: Expense report approved — San Diego, CA — <Tracking #> | F49: Expense approved (reimbursement finalized) | G49: Actual Grand Total | H49: ='S4'!D152 -> 16507.5 | I49: Variance vs. Estimate | J49: ='S4'!D154 -> 225.02 | K49: Tracking # (SLIN code, hyphen, 5 digits) in the subject and the body. It must be the SAME number as the estimate. Heading shows actual dates and travelers. Table of Estimated / Actual / Difference per category; Explanations section lists the variance and added-category notes; Totals include the read-only EWW Total.
A50: S5-E1 | B50: S5 | C50: 3 | D50: S5a | E50: Travel estimate submitted — Raleigh, NC | F50: Submitter copy (Requested column only) | G50: Trip Lead Total | H50: ='S5'!D50 -> 543.92 | I50: Grand Total | J50: ='S5'!D75 -> 543.92 | K50: Heading "Raleigh, NC — S5a One Night Trip", 1 nights. Requested column only; no Billable column. No Tracking # yet (none is issued until the first approval). EWW table lists 1 traveler(s) at $0.00.
A51: S5-E2 | B51: S5 | C51: 3 | D51: S5a | E51: Action needed: review as Supervisor — Raleigh, NC | F51: Supervisor nudge (same body as submitter copy) | G51: Trip Lead Total | H51: ='S5'!D50 -> 543.92 | I51: Grand Total | J51: ='S5'!D75 -> 543.92 | K51: Heading "Raleigh, NC — S5a One Night Trip", 1 nights. Requested column only; no Billable column. No Tracking # yet (none is issued until the first approval). EWW table lists 1 traveler(s) at $0.00.
A52: S5-E3 | B52: S5 | C52: 4 | D52: S5a | E52: Travel estimate approved — Raleigh, NC — <Tracking #> | F52: Supervisor record (Requested + Billable to Prime columns) | G52: Billable to Prime (ODC) | H52: ='S5'!D72 -> 600.99 | I52: Grand Total to Prime | J52: ='S5'!D73 -> 840.99 | K52: Tracking # (SLIN code, hyphen, 5 digits) in the subject and the body. SLIN code in the heading. Requested AND Billable to Prime columns. Totals rows: Trip Lead, EWW, Grand, Billable to Prime (ODC), Grand Total to Prime. Check EWW table.
A53: S5-E4 | B53: S5 | C53: 4 | D53: S5a | E53: Action needed: Prime authorization — Raleigh, NC — <Tracking #> | F53: Prime copy (single marked-up Total column) | G53: Trip Lead Total (marked up) | H53: ='S5'!D72 -> 600.99 | I53: Grand Total (marked up) | J53: ='S5'!D73 -> 840.99 | K53: Tracking # (SLIN code, hyphen, 5 digits) in the subject and the body. Single "Total" column (marked up). Must NOT contain: Requested, Billable to Prime, the Fees/Taxes note, internal Trip Lead.
A54: S5-E5 | B54: S5 | C54: 5 | D54: S5a | E54: Travel authorized — Raleigh, NC — <Tracking #> | F54: Notice: Prime authorized the trip | K54: Short notice that names the trip and carries the Tracking # in the subject and the body.
A55: S5-E6 | B55: S5 | C55: 7 | D55: S5b | E55: Travel estimate submitted — Charlotte, NC | F55: Submitter copy (Requested column only) | G55: Trip Lead Total | H55: ='S5'!G50 -> 136 | I55: Grand Total | J55: ='S5'!G75 -> 136 | K55: Heading "Charlotte, NC — S5b Same Day Trip", 0 nights. Requested column only; no Billable column. No Tracking # yet (none is issued until the first approval). EWW table lists 1 traveler(s) at $0.00.
A56: S5-E7 | B56: S5 | C56: 7 | D56: S5b | E56: Action needed: review as Supervisor — Charlotte, NC | F56: Supervisor nudge (same body as submitter copy) | G56: Trip Lead Total | H56: ='S5'!G50 -> 136 | I56: Grand Total | J56: ='S5'!G75 -> 136 | K56: Heading "Charlotte, NC — S5b Same Day Trip", 0 nights. Requested column only; no Billable column. No Tracking # yet (none is issued until the first approval). EWW table lists 1 traveler(s) at $0.00.
A57: S5-E8 | B57: S5 | C57: 8 | D57: S5b | E57: Travel estimate approved — Charlotte, NC — <Tracking #> | F57: Supervisor record (Requested + Billable to Prime columns) | G57: Billable to Prime (ODC) | H57: ='S5'!G72 -> 141.1 | I57: Grand Total to Prime | J57: ='S5'!G73 -> 141.1 | K57: Tracking # (SLIN code, hyphen, 5 digits) in the subject and the body. SLIN code in the heading. Requested AND Billable to Prime columns. Totals rows: Trip Lead, EWW, Grand, Billable to Prime (ODC), Grand Total to Prime. Check EWW table.
A58: S5-E9 | B58: S5 | C58: 8 | D58: S5b | E58: Action needed: Prime authorization — Charlotte, NC — <Tracking #> | F58: Prime copy (single marked-up Total column) | G58: Trip Lead Total (marked up) | H58: ='S5'!G72 -> 141.1 | I58: Grand Total (marked up) | J58: ='S5'!G73 -> 141.1 | K58: Tracking # (SLIN code, hyphen, 5 digits) in the subject and the body. Single "Total" column (marked up). Must NOT contain: Requested, Billable to Prime, the Fees/Taxes note, internal Trip Lead.
A59: S6-E1 | B59: S6 | C59: 9 | D59: S6 v1 | E59: Travel estimate submitted — Houston, TX | F59: Submitter copy (Requested column only) | G59: Trip Lead Total | H59: ='S6'!D50 -> 2993.92 | I59: Grand Total | J59: ='S6'!D75 -> 2993.92 | K59: Heading "Houston, TX — S6 Return And Resubmit", 3 nights. Requested column only; no Billable column. No Tracking # yet (none is issued until the first approval). EWW table lists 2 traveler(s) at $0.00.
A60: S6-E2 | B60: S6 | C60: 9 | D60: S6 v1 | E60: Action needed: review as Supervisor — Houston, TX | F60: Supervisor nudge (same body as submitter copy) | G60: Trip Lead Total | H60: ='S6'!D50 -> 2993.92 | I60: Grand Total | J60: ='S6'!D75 -> 2993.92 | K60: Heading "Houston, TX — S6 Return And Resubmit", 3 nights. Requested column only; no Billable column. No Tracking # yet (none is issued until the first approval). EWW table lists 2 traveler(s) at $0.00.
A61: S6-E3 | B61: S6 | C61: 11 | D61: S6 v1 | E61: Travel estimate returned — Houston, TX | F61: Notice: Supervisor returned the estimate | G61: Note text must read | H61: Airfare is higher than comparable fares - please recheck fare class | K61: Short notice that names the trip. No Tracking # yet: none is issued before the first approval. The note text appears in the body.
A62: S6-E4 | B62: S6 | C62: 13 | D62: S6 v2 | E62: Travel estimate submitted — Houston, TX | F62: Submitter copy (Requested column only) | G62: Trip Lead Total | H62: ='S6'!G50 -> 2737.92 | I62: Grand Total | J62: ='S6'!G75 -> 3187.92 | K62: Heading "Houston, TX — S6 Return And Resubmit", 3 nights. Requested column only; no Billable column. No Tracking # yet (none is issued until the first approval). EWW table lists 2 traveler(s) with the saved EWW.
A63: S6-E5 | B63: S6 | C63: 13 | D63: S6 v2 | E63: Action needed: review as Supervisor — Houston, TX | F63: Supervisor nudge (same body as submitter copy) | G63: Trip Lead Total | H63: ='S6'!G50 -> 2737.92 | I63: Grand Total | J63: ='S6'!G75 -> 3187.92 | K63: Heading "Houston, TX — S6 Return And Resubmit", 3 nights. Requested column only; no Billable column. No Tracking # yet (none is issued until the first approval). EWW table lists 2 traveler(s) with the saved EWW.
A64: S6-E6 | B64: S6 | C64: 14 | D64: S6 v2 | E64: Travel estimate approved — Houston, TX — <Tracking #> | F64: Supervisor record (Requested + Billable to Prime columns) | G64: Billable to Prime (ODC) | H64: ='S6'!G72 -> 3023.43 | I64: Grand Total to Prime | J64: ='S6'!G73 -> 3473.43 | K64: Tracking # (SLIN code, hyphen, 5 digits) in the subject and the body. SLIN code in the heading. Requested AND Billable to Prime columns. Totals rows: Trip Lead, EWW, Grand, Billable to Prime (ODC), Grand Total to Prime. Check EWW table.
A65: S6-E7 | B65: S6 | C65: 14 | D65: S6 v2 | E65: Action needed: Prime authorization — Houston, TX — <Tracking #> | F65: Prime copy (single marked-up Total column) | G65: Trip Lead Total (marked up) | H65: ='S6'!G72 -> 3023.43 | I65: Grand Total (marked up) | J65: ='S6'!G73 -> 3473.43 | K65: Tracking # (SLIN code, hyphen, 5 digits) in the subject and the body. Single "Total" column (marked up). Must NOT contain: Requested, Billable to Prime, the Fees/Taxes note, internal Trip Lead.
A66: S6-E8 | B66: S6 | C66: 15 | D66: S6 v2 | E66: Travel authorized — Houston, TX — <Tracking #> | F66: Notice: Prime authorized the trip | K66: Short notice that names the trip and carries the Tracking # in the subject and the body.
A67: S7-E1 | B67: S7 | C67: 1 | D67: S7a | E67: Travel estimate submitted — Detroit, MI | F67: Submitter copy (Requested column only) | G67: Trip Lead Total | H67: ='S7'!D50 -> 696.14 | I67: Grand Total | J67: ='S7'!D75 -> 696.14 | K67: Heading "Detroit, MI — S7a Supervisor Deny", 2 nights. Requested column only; no Billable column. No Tracking # yet (none is issued until the first approval). EWW table lists 1 traveler(s) at $0.00.
A68: S7-E2 | B68: S7 | C68: 1 | D68: S7a | E68: Action needed: review as Supervisor — Detroit, MI | F68: Supervisor nudge (same body as submitter copy) | G68: Trip Lead Total | H68: ='S7'!D50 -> 696.14 | I68: Grand Total | J68: ='S7'!D75 -> 696.14 | K68: Heading "Detroit, MI — S7a Supervisor Deny", 2 nights. Requested column only; no Billable column. No Tracking # yet (none is issued until the first approval). EWW table lists 1 traveler(s) at $0.00.
A69: S7-E3 | B69: S7 | C69: 2 | D69: S7a | E69: Travel estimate denied — Detroit, MI | F69: Notice: Supervisor denied the estimate | G69: Note text must read | H69: Not funded this quarter | K69: Short notice that names the trip. No Tracking # yet: none is issued before the first approval. The note text appears in the body.
A70: S7-E4 | B70: S7 | C70: 4 | D70: S7b | E70: Travel estimate submitted — Denver, CO | F70: Submitter copy (Requested column only) | G70: Trip Lead Total | H70: ='S7'!G50 -> 722.14 | I70: Grand Total | J70: ='S7'!G75 -> 722.14 | K70: Heading "Denver, CO — S7b Prime Return Then Deny", 2 nights. Requested column only; no Billable column. No Tracking # yet (none is issued until the first approval). EWW table lists 1 traveler(s) at $0.00.
A71: S7-E5 | B71: S7 | C71: 4 | D71: S7b | E71: Action needed: review as Supervisor — Denver, CO | F71: Supervisor nudge (same body as submitter copy) | G71: Trip Lead Total | H71: ='S7'!G50 -> 722.14 | I71: Grand Total | J71: ='S7'!G75 -> 722.14 | K71: Heading "Denver, CO — S7b Prime Return Then Deny", 2 nights. Requested column only; no Billable column. No Tracking # yet (none is issued until the first approval). EWW table lists 1 traveler(s) at $0.00.
A72: S7-E6 | B72: S7 | C72: 5 | D72: S7b | E72: Travel estimate approved — Denver, CO — <Tracking #> | F72: Supervisor record (Requested + Billable to Prime columns) | G72: Billable to Prime (ODC) | H72: ='S7'!G72 -> 795.35 | I72: Grand Total to Prime | J72: ='S7'!G73 -> 795.35 | K72: Tracking # (SLIN code, hyphen, 5 digits) in the subject and the body. SLIN code in the heading. Requested AND Billable to Prime columns. Totals rows: Trip Lead, EWW, Grand, Billable to Prime (ODC), Grand Total to Prime. Check EWW table.
A73: S7-E7 | B73: S7 | C73: 5 | D73: S7b | E73: Action needed: Prime authorization — Denver, CO — <Tracking #> | F73: Prime copy (single marked-up Total column) | G73: Trip Lead Total (marked up) | H73: ='S7'!G72 -> 795.35 | I73: Grand Total (marked up) | J73: ='S7'!G73 -> 795.35 | K73: Tracking # (SLIN code, hyphen, 5 digits) in the subject and the body. Single "Total" column (marked up). Must NOT contain: Requested, Billable to Prime, the Fees/Taxes note, internal Trip Lead.
A74: S7-E8 | B74: S7 | C74: 6 | D74: S7b | E74: Travel authorization returned — Denver, CO — <Tracking #> | F74: Notice: Prime returned the authorization | G74: Note text must read | H74: Please add the customer PO to the event name | K74: Short notice that names the trip and carries the Tracking # in the subject and the body. The note text appears in the body.
A75: S7-E9 | B75: S7 | C75: 7 | D75: S7b | E75: Travel estimate submitted — Denver, CO — <Tracking #> | F75: Submitter copy (Requested column only) | G75: Trip Lead Total | H75: ='S7'!G50 -> 722.14 | I75: Grand Total | J75: ='S7'!G75 -> 722.14 | K75: Heading "Denver, CO — S7b Prime Return Then Deny", 2 nights. Requested column only; no Billable column. Resubmission after a Prime return: Tracking # (SLIN code, hyphen, 5 digits) in the subject and the body. Same number as the original approval. EWW table lists 1 traveler(s) at $0.00.
A76: S7-E10 | B76: S7 | C76: 7 | D76: S7b | E76: Action needed: review as Supervisor — Denver, CO — <Tracking #> | F76: Supervisor nudge (same body as submitter copy) | G76: Trip Lead Total | H76: ='S7'!G50 -> 722.14 | I76: Grand Total | J76: ='S7'!G75 -> 722.14 | K76: Heading "Denver, CO — S7b Prime Return Then Deny", 2 nights. Requested column only; no Billable column. Resubmission after a Prime return: Tracking # (SLIN code, hyphen, 5 digits) in the subject and the body. Same number as the original approval. EWW table lists 1 traveler(s) at $0.00.
A77: S7-E11 | B77: S7 | C77: 8 | D77: S7b | E77: Travel estimate approved — Denver, CO — <Tracking #> | F77: Supervisor record (Requested + Billable to Prime columns) | G77: Billable to Prime (ODC) | H77: ='S7'!G72 -> 795.35 | I77: Grand Total to Prime | J77: ='S7'!G73 -> 795.35 | K77: Tracking # (SLIN code, hyphen, 5 digits) in the subject and the body. SLIN code in the heading. Requested AND Billable to Prime columns. Totals rows: Trip Lead, EWW, Grand, Billable to Prime (ODC), Grand Total to Prime. Check EWW table. Re-approval: the number must be unchanged.
A78: S7-E12 | B78: S7 | C78: 8 | D78: S7b | E78: Action needed: Prime authorization — Denver, CO — <Tracking #> | F78: Prime copy (single marked-up Total column) | G78: Trip Lead Total (marked up) | H78: ='S7'!G72 -> 795.35 | I78: Grand Total (marked up) | J78: ='S7'!G73 -> 795.35 | K78: Tracking # (SLIN code, hyphen, 5 digits) in the subject and the body. Single "Total" column (marked up). Must NOT contain: Requested, Billable to Prime, the Fees/Taxes note, internal Trip Lead. Re-approval: the number must be unchanged.
A79: S7-E13 | B79: S7 | C79: 9 | D79: S7b | E79: Travel authorization denied — Denver, CO — <Tracking #> | F79: Notice: Prime denied the authorization | G79: Note text must read | H79: Budget exhausted | K79: Short notice that names the trip and carries the Tracking # in the subject and the body. The note text appears in the body.
A80: S7-E14 | B80: S7 | C80: 11 | D80: S7c-1 | E80: Travel estimate cancelled — Boise, ID | F80: Notice: employee cancelled the request | K80: Short notice that names the trip. No Tracking # yet: none is issued before the first approval.
A81: S7-E15 | B81: S7 | C81: 12 | D81: S7c-2 | E81: Travel estimate submitted — Omaha, NE | F81: Submitter copy (Requested column only) | G81: Trip Lead Total | H81: ='S7'!M50 -> 686.14 | I81: Grand Total | J81: ='S7'!M75 -> 686.14 | K81: Heading "Omaha, NE — S7c Cancel After Submit", 2 nights. Requested column only; no Billable column. No Tracking # yet (none is issued until the first approval). EWW table lists 1 traveler(s) at $0.00.
A82: S7-E16 | B82: S7 | C82: 12 | D82: S7c-2 | E82: Action needed: review as Supervisor — Omaha, NE | F82: Supervisor nudge (same body as submitter copy) | G82: Trip Lead Total | H82: ='S7'!M50 -> 686.14 | I82: Grand Total | J82: ='S7'!M75 -> 686.14 | K82: Heading "Omaha, NE — S7c Cancel After Submit", 2 nights. Requested column only; no Billable column. No Tracking # yet (none is issued until the first approval). EWW table lists 1 traveler(s) at $0.00.
A83: S7-E17 | B83: S7 | C83: 12 | D83: S7c-2 | E83: Travel estimate cancelled — Omaha, NE | F83: Notice: employee cancelled the request | K83: Short notice that names the trip. No Tracking # yet: none is issued before the first approval.
A84: S8-E1 | B84: S8 | C84: 1 | D84: S8a | E84: Travel estimate submitted — Phoenix, AZ | F84: Submitter copy (Requested column only) | G84: Trip Lead Total | H84: ='S8'!D50 -> 694.46 | I84: Grand Total | J84: ='S8'!D75 -> 694.46 | K84: Heading "Phoenix, AZ — S8a Expense Return", 2 nights. Requested column only; no Billable column. No Tracking # yet (none is issued until the first approval). EWW table lists 1 traveler(s) at $0.00.
A85: S8-E2 | B85: S8 | C85: 1 | D85: S8a | E85: Action needed: review as Supervisor — Phoenix, AZ | F85: Supervisor nudge (same body as submitter copy) | G85: Trip Lead Total | H85: ='S8'!D50 -> 694.46 | I85: Grand Total | J85: ='S8'!D75 -> 694.46 | K85: Heading "Phoenix, AZ — S8a Expense Return", 2 nights. Requested column only; no Billable column. No Tracking # yet (none is issued until the first approval). EWW table lists 1 traveler(s) at $0.00.
A86: S8-E3 | B86: S8 | C86: 2 | D86: S8a | E86: Travel estimate approved — Phoenix, AZ — <Tracking #> | F86: Supervisor record (Requested + Billable to Prime columns) | G86: Billable to Prime (ODC) | H86: ='S8'!D72 -> 763.5 | I86: Grand Total to Prime | J86: ='S8'!D73 -> 763.5 | K86: Tracking # (SLIN code, hyphen, 5 digits) in the subject and the body. SLIN code in the heading. Requested AND Billable to Prime columns. Totals rows: Trip Lead, EWW, Grand, Billable to Prime (ODC), Grand Total to Prime. Check EWW table.
A87: S8-E4 | B87: S8 | C87: 2 | D87: S8a | E87: Action needed: Prime authorization — Phoenix, AZ — <Tracking #> | F87: Prime copy (single marked-up Total column) | G87: Trip Lead Total (marked up) | H87: ='S8'!D72 -> 763.5 | I87: Grand Total (marked up) | J87: ='S8'!D73 -> 763.5 | K87: Tracking # (SLIN code, hyphen, 5 digits) in the subject and the body. Single "Total" column (marked up). Must NOT contain: Requested, Billable to Prime, the Fees/Taxes note, internal Trip Lead.
A88: S8-E5 | B88: S8 | C88: 3 | D88: S8a | E88: Travel authorized — Phoenix, AZ — <Tracking #> | F88: Notice: Prime authorized the trip | K88: Short notice that names the trip and carries the Tracking # in the subject and the body.
A89: S8-E6 | B89: S8 | C89: 4 | D89: S8b | E89: Travel estimate submitted — Tucson, AZ | F89: Submitter copy (Requested column only) | G89: Trip Lead Total | H89: ='S8'!G50 -> 719.46 | I89: Grand Total | J89: ='S8'!G75 -> 719.46 | K89: Heading "Tucson, AZ — S8b Expense Deny", 2 nights. Requested column only; no Billable column. No Tracking # yet (none is issued until the first approval). EWW table lists 1 traveler(s) at $0.00.
A90: S8-E7 | B90: S8 | C90: 4 | D90: S8b | E90: Action needed: review as Supervisor — Tucson, AZ | F90: Supervisor nudge (same body as submitter copy) | G90: Trip Lead Total | H90: ='S8'!G50 -> 719.46 | I90: Grand Total | J90: ='S8'!G75 -> 719.46 | K90: Heading "Tucson, AZ — S8b Expense Deny", 2 nights. Requested column only; no Billable column. No Tracking # yet (none is issued until the first approval). EWW table lists 1 traveler(s) at $0.00.
A91: S8-E8 | B91: S8 | C91: 5 | D91: S8b | E91: Travel estimate approved — Tucson, AZ — <Tracking #> | F91: Supervisor record (Requested + Billable to Prime columns) | G91: Billable to Prime (ODC) | H91: ='S8'!G72 -> 791.69 | I91: Grand Total to Prime | J91: ='S8'!G73 -> 791.69 | K91: Tracking # (SLIN code, hyphen, 5 digits) in the subject and the body. SLIN code in the heading. Requested AND Billable to Prime columns. Totals rows: Trip Lead, EWW, Grand, Billable to Prime (ODC), Grand Total to Prime. Check EWW table.
A92: S8-E9 | B92: S8 | C92: 5 | D92: S8b | E92: Action needed: Prime authorization — Tucson, AZ — <Tracking #> | F92: Prime copy (single marked-up Total column) | G92: Trip Lead Total (marked up) | H92: ='S8'!G72 -> 791.69 | I92: Grand Total (marked up) | J92: ='S8'!G73 -> 791.69 | K92: Tracking # (SLIN code, hyphen, 5 digits) in the subject and the body. Single "Total" column (marked up). Must NOT contain: Requested, Billable to Prime, the Fees/Taxes note, internal Trip Lead.
A93: S8-E10 | B93: S8 | C93: 6 | D93: S8b | E93: Travel authorized — Tucson, AZ — <Tracking #> | F93: Notice: Prime authorized the trip | K93: Short notice that names the trip and carries the Tracking # in the subject and the body.
A94: S8-E11 | B94: S8 | C94: 7 | D94: S8a | E94: Expense report submitted — Phoenix, AZ — <Tracking #> | F94: Expense submitter copy (actual vs estimated) | G94: Actual Grand Total | H94: ='S8'!D129 -> 694.46 | I94: Variance vs. Estimate | J94: ='S8'!D131 -> 0 | K94: Tracking # (SLIN code, hyphen, 5 digits) in the subject and the body. It must be the SAME number as the estimate. Heading shows actual dates and travelers. Table of Estimated / Actual / Difference per category; Explanations section lists the variance and added-category notes; Totals include the read-only EWW Total.
A95: S8-E12 | B95: S8 | C95: 7 | D95: S8a | E95: Action needed: review expense report as Supervisor — Phoenix, AZ — <Tracking #> | F95: Expense Supervisor nudge (same body) | G95: Actual Grand Total | H95: ='S8'!D129 -> 694.46 | I95: Variance vs. Estimate | J95: ='S8'!D131 -> 0 | K95: Tracking # (SLIN code, hyphen, 5 digits) in the subject and the body. It must be the SAME number as the estimate. Heading shows actual dates and travelers. Table of Estimated / Actual / Difference per category; Explanations section lists the variance and added-category notes; Totals include the read-only EWW Total.
A96: S8-E13 | B96: S8 | C96: 8 | D96: S8a | E96: Expense report returned — Phoenix, AZ — <Tracking #> | F96: Notice: Supervisor returned the expense report | G96: Note text must read | H96: Lodging receipt is unreadable - please re-upload | K96: Short notice that names the trip and carries the Tracking # in the subject and the body. The note text appears in the body.
A97: S8-E14 | B97: S8 | C97: 9 | D97: S8a | E97: Expense report submitted — Phoenix, AZ — <Tracking #> | F97: Expense submitter copy (actual vs estimated) | G97: Actual Grand Total | H97: ='S8'!D129 -> 694.46 | I97: Variance vs. Estimate | J97: ='S8'!D131 -> 0 | K97: Tracking # (SLIN code, hyphen, 5 digits) in the subject and the body. It must be the SAME number as the estimate. Heading shows actual dates and travelers. Table of Estimated / Actual / Difference per category; Explanations section lists the variance and added-category notes; Totals include the read-only EWW Total.
A98: S8-E15 | B98: S8 | C98: 9 | D98: S8a | E98: Action needed: review expense report as Supervisor — Phoenix, AZ — <Tracking #> | F98: Expense Supervisor nudge (same body) | G98: Actual Grand Total | H98: ='S8'!D129 -> 694.46 | I98: Variance vs. Estimate | J98: ='S8'!D131 -> 0 | K98: Tracking # (SLIN code, hyphen, 5 digits) in the subject and the body. It must be the SAME number as the estimate. Heading shows actual dates and travelers. Table of Estimated / Actual / Difference per category; Explanations section lists the variance and added-category notes; Totals include the read-only EWW Total.
A99: S8-E16 | B99: S8 | C99: 10 | D99: S8a | E99: Expense report approved — Phoenix, AZ — <Tracking #> | F99: Expense approved (reimbursement finalized) | G99: Actual Grand Total | H99: ='S8'!D129 -> 694.46 | I99: Variance vs. Estimate | J99: ='S8'!D131 -> 0 | K99: Tracking # (SLIN code, hyphen, 5 digits) in the subject and the body. It must be the SAME number as the estimate. Heading shows actual dates and travelers. Table of Estimated / Actual / Difference per category; Explanations section lists the variance and added-category notes; Totals include the read-only EWW Total.
A100: S8-E17 | B100: S8 | C100: 11 | D100: S8b | E100: Expense report submitted — Tucson, AZ — <Tracking #> | F100: Expense submitter copy (actual vs estimated) | G100: Actual Grand Total | H100: ='S8'!D169 -> 744.46 | I100: Variance vs. Estimate | J100: ='S8'!D171 -> 25 | K100: Tracking # (SLIN code, hyphen, 5 digits) in the subject and the body. It must be the SAME number as the estimate. Heading shows actual dates and travelers. Table of Estimated / Actual / Difference per category; Explanations section lists the variance and added-category notes; Totals include the read-only EWW Total.
A101: S8-E18 | B101: S8 | C101: 11 | D101: S8b | E101: Action needed: review expense report as Supervisor — Tucson, AZ — <Tracking #> | F101: Expense Supervisor nudge (same body) | G101: Actual Grand Total | H101: ='S8'!D169 -> 744.46 | I101: Variance vs. Estimate | J101: ='S8'!D171 -> 25 | K101: Tracking # (SLIN code, hyphen, 5 digits) in the subject and the body. It must be the SAME number as the estimate. Heading shows actual dates and travelers. Table of Estimated / Actual / Difference per category; Explanations section lists the variance and added-category notes; Totals include the read-only EWW Total.
A102: S8-E19 | B102: S8 | C102: 12 | D102: S8b | E102: Expense report denied — Tucson, AZ — <Tracking #> | F102: Notice: Supervisor denied the expense report | G102: Note text must read | H102: Duplicate of another claim | K102: Short notice that names the trip and carries the Tracking # in the subject and the body. The note text appears in the body.

Sheet Controls
A1: Control coverage matrix
A2: A dot means a step in that scenario uses the control. Built from the Steps tab, so it always matches what you actually run.
C3: Controls total / covered / gaps | D3: =COUNTA(A6:A92)&" controls | "&COUNTIF(N6:N92,"Covered")&" covered | "&COUNTIF(N6:N92,"GAP")&" gaps" -> 87 controls | 87 covered | 0 gaps
A5: ID | B5: Area | C5: Control | D5: What to verify | E5: S1 | F5: S2 | G5: S3 | H5: S4 | I5: S5 | J5: S6 | K5: S7 | L5: S8 | M5: Scenarios | N5: Status
A6: E01 | B6: Estimate form | C6: Event Name | D6: Free text. Persists through draft/reopen. Appears in emails and lists. | E6: ● | F6: ● | G6: ● | H6: ● | I6: ● | J6: ● | K6: ● | L6: ● | M6: =COUNTIF(E6:L6,"●") -> 8 | N6: =IF(M6=0,"GAP","Covered") -> Covered
A7: E02 | B7: Estimate form | C7: City | D7: Free text. Leaving the field triggers the GSA lookup when State is also set. | E7: ● | F7: ● | G7: ● | H7: ● | I7: ● | J7: ● | K7: ● | L7: ● | M7: =COUNTIF(E7:L7,"●") -> 8 | N7: =IF(M7=0,"GAP","Covered") -> Covered
A8: E03 | B8: Estimate form | C8: State | D8: Type-ahead for 50 states + DC; stores the 2-letter code. | E8: ● | F8: ● | G8: ● | H8: ● | I8: ● | J8: ● | K8: ● | L8: ● | M8: =COUNTIF(E8:L8,"●") -> 8 | N8: =IF(M8=0,"GAP","Covered") -> Covered
A9: E04 | B9: Estimate form | C9: Contract | D9: Dropdown. Required to submit. | E9: ● | F9: ● | G9: ● | H9: ● | I9: ● | J9: ● | K9: ● | L9: ● | M9: =COUNTIF(E9:L9,"●") -> 8 | N9: =IF(M9=0,"GAP","Covered") -> Covered
A10: E05 | B10: Estimate form | C10: Leave Date | D10: Date picker. Recalculates Nights and Per Diem. Triggers GSA lookup. | E10: ● | F10: ● | G10: ● | H10: ● | I10: ● | J10: ● | K10: ● | L10: ● | M10: =COUNTIF(E10:L10,"●") -> 8 | N10: =IF(M10=0,"GAP","Covered") -> Covered
A11: E06 | B11: Estimate form | C11: Return Date | D11: Date picker. Must be on/after Leave Date to submit. | E11: ● | F11: ● | G11: ● | H11: ● | I11: ● | J11: ● | K11: ● | L11: ● | M11: =COUNTIF(E11:L11,"●") -> 8 | N11: =IF(M11=0,"GAP","Covered") -> Covered
A12: E07 | B12: Estimate form | C12: Travelers (1-4) | D12: Dropdown. Adds or removes traveler rows. Multiplies per-traveler costs. | E12: ● | F12: ● | H12: ● | J12: ● | M12: =COUNTIF(E12:L12,"●") -> 4 | N12: =IF(M12=0,"GAP","Covered") -> Covered
A13: E08 | B13: Estimate form | C13: Traveler 2-4 picker | D13: Roster dropdown. Excludes already-chosen people. Required before submit. | F13: ● | H13: ● | J13: ● | M13: =COUNTIF(E13:L13,"●") -> 3 | N13: =IF(M13=0,"GAP","Covered") -> Covered
A14: E09 | B14: Estimate form | C14: Remove traveler (x) | D14: Removes a slot, renumbers, Travelers count follows. | H14: ● | M14: =COUNTIF(E14:L14,"●") -> 1 | N14: =IF(M14=0,"GAP","Covered") -> Covered
A15: E10 | B15: Estimate form | C15: Refresh GSA Rates button | D15: Re-runs lookup and overwrites rate fields. | G15: ● | M15: =COUNTIF(E15:L15,"●") -> 1 | N15: =IF(M15=0,"GAP","Covered") -> Covered
A16: E11 | B16: Estimate form | C16: GSA Lodging Rate | D16: Currency field. Drives the lodging limit check. | E16: ● | F16: ● | G16: ● | H16: ● | I16: ● | J16: ● | K16: ● | L16: ● | M16: =COUNTIF(E16:L16,"●") -> 8 | N16: =IF(M16=0,"GAP","Covered") -> Covered
A17: E12 | B17: Estimate form | C17: Meals (M&IE) Rate | D17: Currency field. Drives per diem meals. | E17: ● | F17: ● | G17: ● | H17: ● | I17: ● | J17: ● | K17: ● | L17: ● | M17: =COUNTIF(E17:L17,"●") -> 8 | N17: =IF(M17=0,"GAP","Covered") -> Covered
A18: E13 | B18: Estimate form | C18: Room Cost | D18: Currency field. Only this (not fees/taxes) counts toward the limit. | E18: ● | F18: ● | G18: ● | H18: ● | I18: ● | J18: ● | K18: ● | L18: ● | M18: =COUNTIF(E18:L18,"●") -> 8 | N18: =IF(M18=0,"GAP","Covered") -> Covered
A19: E14 | B19: Estimate form | C19: Total Lodging Cost | D19: Currency field. Flows into the per-traveler subtotal and the markup. | E19: ● | F19: ● | G19: ● | H19: ● | I19: ● | J19: ● | K19: ● | L19: ● | M19: =COUNTIF(E19:L19,"●") -> 8 | N19: =IF(M19=0,"GAP","Covered") -> Covered
A20: E15 | B20: Estimate form | C20: Lodging Fees | D20: Currency field. Recorded only; not added again. | E20: ● | F20: ● | G20: ● | H20: ● | I20: ● | J20: ● | K20: ● | L20: ● | M20: =COUNTIF(E20:L20,"●") -> 8 | N20: =IF(M20=0,"GAP","Covered") -> Covered
A21: E16 | B21: Estimate form | C21: Lodging Taxes | D21: Currency field. Recorded only; not added again. | E21: ● | F21: ● | G21: ● | H21: ● | I21: ● | J21: ● | K21: ● | L21: ● | M21: =COUNTIF(E21:L21,"●") -> 8 | N21: =IF(M21=0,"GAP","Covered") -> Covered
A22: E17 | B22: Estimate form | C22: Upload Comparison Quotes (modal) | D22: Upload up to 3 files. Button counts n of 3. Creates a draft silently. | G22: ● | M22: =COUNTIF(E22:L22,"●") -> 1 | N22: =IF(M22=0,"GAP","Covered") -> Covered
A23: E18 | B23: Estimate form | C23: Quote nightly rate field | D23: Number per quote. Modal shows the average. All 3 needed to submit. | G23: ● | M23: =COUNTIF(E23:L23,"●") -> 1 | N23: =IF(M23=0,"GAP","Covered") -> Covered
A24: E19 | B24: Estimate form | C24: Airfare (avg) | D24: Currency field. Per traveler. | F24: ● | G24: ● | H24: ● | I24: ● | J24: ● | K24: ● | L24: ● | M24: =COUNTIF(E24:L24,"●") -> 7 | N24: =IF(M24=0,"GAP","Covered") -> Covered
A25: E20 | B25: Estimate form | C25: Baggage | D25: Currency field. Per traveler. | G25: ● | H25: ● | J25: ● | M25: =COUNTIF(E25:L25,"●") -> 3 | N25: =IF(M25=0,"GAP","Covered") -> Covered
A26: E21 | B26: Estimate form | C26: Airport Parking | D26: Currency field. Per traveler. | F26: ● | G26: ● | H26: ● | J26: ● | M26: =COUNTIF(E26:L26,"●") -> 4 | N26: =IF(M26=0,"GAP","Covered") -> Covered
A27: E22 | B27: Estimate form | C27: Shipping (to) | D27: Currency field. Trip-level. | F27: ● | H27: ● | M27: =COUNTIF(E27:L27,"●") -> 2 | N27: =IF(M27=0,"GAP","Covered") -> Covered
A28: E23 | B28: Estimate form | C28: Shipping (back) | D28: Currency field. Trip-level. | F28: ● | H28: ● | M28: =COUNTIF(E28:L28,"●") -> 2 | N28: =IF(M28=0,"GAP","Covered") -> Covered
A29: E24 | B29: Estimate form | C29: Rental Car | D29: Currency field. Trip-level. | F29: ● | M29: =COUNTIF(E29:L29,"●") -> 1 | N29: =IF(M29=0,"GAP","Covered") -> Covered
A30: E25 | B30: Estimate form | C30: Gas | D30: Currency field. Trip-level. | E30: ● | F30: ● | M30: =COUNTIF(E30:L30,"●") -> 2 | N30: =IF(M30=0,"GAP","Covered") -> Covered
A31: E26 | B31: Estimate form | C31: Parking | D31: Currency field. Trip-level. | E31: ● | F31: ● | M31: =COUNTIF(E31:L31,"●") -> 2 | N31: =IF(M31=0,"GAP","Covered") -> Covered
A32: E27 | B32: Estimate form | C32: Tolls | D32: Currency field. Trip-level. | E32: ● | M32: =COUNTIF(E32:L32,"●") -> 1 | N32: =IF(M32=0,"GAP","Covered") -> Covered
A33: E28 | B33: Estimate form | C33: Rideshare Estimate | D33: Currency field. Trip-level. | G33: ● | H33: ● | I33: ● | J33: ● | M33: =COUNTIF(E33:L33,"●") -> 4 | N33: =IF(M33=0,"GAP","Covered") -> Covered
A34: E29 | B34: Estimate form | C34: Mileage (Personal Vehicle) | D34: Currency field. Trip-level. | E34: ● | M34: =COUNTIF(E34:L34,"●") -> 1 | N34: =IF(M34=0,"GAP","Covered") -> Covered
A35: E30 | B35: Estimate form | C35: Save as Draft button | D35: Saves without validation. Toast "Draft saved." No email. | E35: ● | K35: ● | M35: =COUNTIF(E35:L35,"●") -> 2 | N35: =IF(M35=0,"GAP","Covered") -> Covered
A36: E31 | B36: Estimate form | C36: Submit Estimate button | D36: Validates, saves, sends 2 emails, toast. | E36: ● | F36: ● | G36: ● | H36: ● | I36: ● | J36: ● | K36: ● | L36: ● | M36: =COUNTIF(E36:L36,"●") -> 8 | N36: =IF(M36=0,"GAP","Covered") -> Covered
A37: E32 | B37: Estimate form | C37: Cancel button (form) | D37: Leaves the form without saving. | J37: ● | M37: =COUNTIF(E37:L37,"●") -> 1 | N37: =IF(M37=0,"GAP","Covered") -> Covered
A38: E33 | B38: Estimate form | C38: Currency input behavior | D38: Clears on click, formats $X.XX on Tab, live-updates totals. | E38: ● | F38: ● | G38: ● | H38: ● | J38: ● | M38: =COUNTIF(E38:L38,"●") -> 5 | N38: =IF(M38=0,"GAP","Covered") -> Covered
A39: E34 | B39: Estimate form | C39: Over-limit warning box | D39: Appears only when average ROOM cost per night exceeds the GSA rate. | G39: ● | J39: ● | M39: =COUNTIF(E39:L39,"●") -> 2 | N39: =IF(M39=0,"GAP","Covered") -> Covered
A40: E35 | B40: Estimate form | C40: Unsaved-changes prompt | D40: Browser confirms before leaving with edits. | J40: ● | M40: =COUNTIF(E40:L40,"●") -> 1 | N40: =IF(M40=0,"GAP","Covered") -> Covered
A41: L01 | B41: My Estimates list | C41: Row button (Edit Draft / Edit & Resubmit / View) | D41: Edit Draft for drafts, Edit & Resubmit for RETURNED only, View for everything else (including denied). | E41: ● | J41: ● | K41: ● | M41: =COUNTIF(E41:L41,"●") -> 3 | N41: =IF(M41=0,"GAP","Covered") -> Covered
A42: L02 | B42: My Estimates list | C42: Cancel (red x) + confirmation | D42: Shown for open requests only: not paid, cancelled or denied. Confirm prompt. Sends a cancellation email. | E42: ● | K42: ● | M42: =COUNTIF(E42:L42,"●") -> 2 | N42: =IF(M42=0,"GAP","Covered") -> Covered
A43: L03 | B43: My Estimates list | C43: Pending vs Paid / Cancelled cards | D43: Rows land in the right card by status. | E43: ● | K43: ● | M43: =COUNTIF(E43:L43,"●") -> 2 | N43: =IF(M43=0,"GAP","Covered") -> Covered
A44: L04 | B44: My Estimates list | C44: Return/Deny note banner | D44: Red banner with the approver's note (editable form when returned, read-only detail when denied). | J44: ● | K44: ● | M44: =COUNTIF(E44:L44,"●") -> 2 | N44: =IF(M44=0,"GAP","Covered") -> Covered
A45: S01 | B45: Supervisor estimate review | C45: Approvals > Estimates queue + Review | D45: Lists submitted estimates with Grand Total. | E45: ● | F45: ● | G45: ● | H45: ● | I45: ● | J45: ● | K45: ● | L45: ● | M45: =COUNTIF(E45:L45,"●") -> 8 | N45: =IF(M45=0,"GAP","Covered") -> Covered
A46: S02 | B46: Supervisor estimate review | C46: EWW Rate (per traveler) | D46: Currency field per traveler (payroll-verified). Updates EWW cost live. | E46: ● | F46: ● | G46: ● | H46: ● | I46: ● | J46: ● | M46: =COUNTIF(E46:L46,"●") -> 6 | N46: =IF(M46=0,"GAP","Covered") -> Covered
A47: S03 | B47: Supervisor estimate review | C47: EWW Hours (per traveler) | D47: Number field per traveler. | E47: ● | F47: ● | G47: ● | H47: ● | I47: ● | J47: ● | M47: =COUNTIF(E47:L47,"●") -> 6 | N47: =IF(M47=0,"GAP","Covered") -> Covered
A48: S04 | B48: Supervisor estimate review | C48: Billing: Contract | D48: Dropdown. Resets Task Order and SLIN. | E48: ● | F48: ● | G48: ● | H48: ● | I48: ● | J48: ● | K48: ● | L48: ● | M48: =COUNTIF(E48:L48,"●") -> 8 | N48: =IF(M48=0,"GAP","Covered") -> Covered
A49: S05 | B49: Supervisor estimate review | C49: Billing: Task Order | D49: Filtered by Contract. Resets SLIN. | E49: ● | F49: ● | G49: ● | H49: ● | I49: ● | J49: ● | K49: ● | L49: ● | M49: =COUNTIF(E49:L49,"●") -> 8 | N49: =IF(M49=0,"GAP","Covered") -> Covered
A50: S06 | B50: Supervisor estimate review | C50: Billing: SLIN | D50: Filtered by Task Order. Required to approve. Becomes the first half of the tracking number. | E50: ● | F50: ● | G50: ● | H50: ● | I50: ● | J50: ● | K50: ● | L50: ● | M50: =COUNTIF(E50:L50,"●") -> 8 | N50: =IF(M50=0,"GAP","Covered") -> Covered
A51: S07 | B51: Supervisor estimate review | C51: Note box | D51: Required for Return/Deny; hidden until needed. | J51: ● | K51: ● | M51: =COUNTIF(E51:L51,"●") -> 2 | N51: =IF(M51=0,"GAP","Covered") -> Covered
A52: S08 | B52: Supervisor estimate review | C52: Approve button | D52: First approval issues the tracking number (SLIN-00001). Sends 2 emails. | E52: ● | F52: ● | G52: ● | H52: ● | I52: ● | J52: ● | K52: ● | L52: ● | M52: =COUNTIF(E52:L52,"●") -> 8 | N52: =IF(M52=0,"GAP","Covered") -> Covered
A53: S09 | B53: Supervisor estimate review | C53: Return button | D53: Needs a note. Keeps EWW. Sends 1 email. | J53: ● | M53: =COUNTIF(E53:L53,"●") -> 1 | N53: =IF(M53=0,"GAP","Covered") -> Covered
A54: S10 | B54: Supervisor estimate review | C54: Deny button | D54: Needs a note. Stores the request as denied. Sends 1 email. | K54: ● | M54: =COUNTIF(E54:L54,"●") -> 1 | N54: =IF(M54=0,"GAP","Covered") -> Covered
A55: S11 | B55: Supervisor estimate review | C55: Close button | D55: Closes the review without a decision. | E55: ● | M55: =COUNTIF(E55:L55,"●") -> 1 | N55: =IF(M55=0,"GAP","Covered") -> Covered
A56: S12 | B56: Supervisor estimate review | C56: Read-only mirrored form | D56: All submitter fields locked; EWW fields editable. | E56: ● | F56: ● | G56: ● | M56: =COUNTIF(E56:L56,"●") -> 3 | N56: =IF(M56=0,"GAP","Covered") -> Covered
A57: P01 | B57: Prime authorization | C57: Travel Authorizations queue + Review | D57: Lists Supervisor-approved estimates with tracking # and billable total. | E57: ● | F57: ● | G57: ● | H57: ● | I57: ● | J57: ● | K57: ● | L57: ● | M57: =COUNTIF(E57:L57,"●") -> 8 | N57: =IF(M57=0,"GAP","Covered") -> Covered
A58: P02 | B58: Prime authorization | C58: Authorize Travel button | D58: Moves to approved. Sends 1 email with trip and tracking number. | E58: ● | F58: ● | G58: ● | H58: ● | I58: ● | J58: ● | L58: ● | M58: =COUNTIF(E58:L58,"●") -> 7 | N58: =IF(M58=0,"GAP","Covered") -> Covered
A59: P03 | B59: Prime authorization | C59: Return button | D59: Needs a note. Sends 1 email. | K59: ● | M59: =COUNTIF(E59:L59,"●") -> 1 | N59: =IF(M59=0,"GAP","Covered") -> Covered
A60: P04 | B60: Prime authorization | C60: Deny button | D60: Needs a note. Stores the request as denied. Sends 1 email. | K60: ● | M60: =COUNTIF(E60:L60,"●") -> 1 | N60: =IF(M60=0,"GAP","Covered") -> Covered
A61: P05 | B61: Prime authorization | C61: Note box | D61: Required for Return/Deny. | K61: ● | M61: =COUNTIF(E61:L61,"●") -> 1 | N61: =IF(M61=0,"GAP","Covered") -> Covered
A62: P06 | B62: Prime authorization | C62: Close button | D62: Closes the review. | K62: ● | M62: =COUNTIF(E62:L62,"●") -> 1 | N62: =IF(M62=0,"GAP","Covered") -> Covered
